Workbook

Sheet Dashboard
B2: Neurolumens · Dashboard mensual
B4: Mes seleccionado | C4: =DATE(Configuración!C5,Configuración!C6,1) -> 46023
B6: Indicador | C6: Mes | D6: Año completo
B7: Ingresos por servicios | C7: =INDEX(KPIs!$C$7:$N$7,1,Configuración!$C$6) -> 2200 | D7: =KPIs!O7 -> 2200
B8: Utilidad neta | C8: =INDEX(KPIs!$C$8:$N$8,1,Configuración!$C$6) -> 2200 | D8: =KPIs!O8 -> 2200
B9: Margen neto | C9: =INDEX(KPIs!$C$11:$N$11,1,Configuración!$C$6) -> 1 | D9: =KPIs!O11 -> 1
B10: Flujo operativo | C10: =INDEX(KPIs!$C$14:$N$14,1,Configuración!$C$6) -> 2200 | D10: =KPIs!O14 -> 2200
B11: Efectivo al cierre | C11: =INDEX(KPIs!$C$15:$N$15,1,Configuración!$C$6) -> 2200 | D11: =KPIs!O15 -> 2200
B12: Retiros familiares | C12: =INDEX(KPIs!$C$19:$N$19,1,Configuración!$C$6) -> 0 | D12: =KPIs!O19 -> 0
B13: Remuneraciones familiares pagadas | C13: =INDEX(KPIs!$C$20:$N$20,1,Configuración!$C$6) -> 0 | D13: =KPIs!O20 -> 0
B14: Salida total a la familia | C14: =INDEX(KPIs!$C$21:$N$21,1,Configuración!$C$6) -> 0 | D14: =KPIs!O21 -> 0
B15: Deuda financiera | C15: =INDEX(KPIs!$C$18:$N$18,1,Configuración!$C$6) -> 0 | D15: =KPIs!O18 -> 0
B16: Cuentas por cobrar | C16: =INDEX(KPIs!$C$23:$N$23,1,Configuración!$C$6) -> 0 | D16: =KPIs!O23 -> 0
B18: Empieza en Instrucciones y Configuración. Captura en amarillo; fórmulas en blanco.
B19: Los importes en cero no prueban que el mes esté completo. Revisa Control antes de cerrar.
B23: Mes | C23: Ingresos | D23: Utilidad neta | E23: Efectivo final | F23: Retiros familiares
B24: Ene | C24: ='Estado de Resultados'!C14 -> 2200 | D24: ='Estado de Resultados'!C33 -> 2200 | E24: ='Flujo de Efectivo'!C25 -> 2200 | F24: ='Flujo de Efectivo'!C20 -> 0
B25: Feb | C25: ='Estado de Resultados'!D14 -> 0 | D25: ='Estado de Resultados'!D33 -> 0 | E25: ='Flujo de Efectivo'!D25 -> 2200 | F25: ='Flujo de Efectivo'!D20 -> 0
B26: Mar | C26: ='Estado de Resultados'!E14 -> 0 | D26: ='Estado de Resultados'!E33 -> 0 | E26: ='Flujo de Efectivo'!E25 -> 2200 | F26: ='Flujo de Efectivo'!E20 -> 0
B27: Abr | C27: ='Estado de Resultados'!F14 -> 0 | D27: ='Estado de Resultados'!F33 -> 0 | E27: ='Flujo de Efectivo'!F25 -> 2200 | F27: ='Flujo de Efectivo'!F20 -> 0
B28: May | C28: ='Estado de Resultados'!G14 -> 0 | D28: ='Estado de Resultados'!G33 -> 0 | E28: ='Flujo de Efectivo'!G25 -> 2200 | F28: ='Flujo de Efectivo'!G20 -> 0
B29: Jun | C29: ='Estado de Resultados'!H14 -> 0 | D29: ='Estado de Resultados'!H33 -> 0 | E29: ='Flujo de Efectivo'!H25 -> 2200 | F29: ='Flujo de Efectivo'!H20 -> 0
B30: Jul | C30: ='Estado de Resultados'!I14 -> 0 | D30: ='Estado de Resultados'!I33 -> 0 | E30: ='Flujo de Efectivo'!I25 -> 2200 | F30: ='Flujo de Efectivo'!I20 -> 0
B31: Ago | C31: ='Estado de Resultados'!J14 -> 0 | D31: ='Estado de Resultados'!J33 -> 0 | E31: ='Flujo de Efectivo'!J25 -> 2200 | F31: ='Flujo de Efectivo'!J20 -> 0
B32: Sep | C32: ='Estado de Resultados'!K14 -> 0 | D32: ='Estado de Resultados'!K33 -> 0 | E32: ='Flujo de Efectivo'!K25 -> 2200 | F32: ='Flujo de Efectivo'!K20 -> 0
B33: Oct | C33: ='Estado de Resultados'!L14 -> 0 | D33: ='Estado de Resultados'!L33 -> 0 | E33: ='Flujo de Efectivo'!L25 -> 2200 | F33: ='Flujo de Efectivo'!L20 -> 0
B34: Nov | C34: ='Estado de Resultados'!M14 -> 0 | D34: ='Estado de Resultados'!M33 -> 0 | E34: ='Flujo de Efectivo'!M25 -> 2200 | F34: ='Flujo de Efectivo'!M20 -> 0
B35: Dic | C35: ='Estado de Resultados'!N14 -> 0 | D35: ='Estado de Resultados'!N33 -> 0 | E35: ='Flujo de Efectivo'!N25 -> 2200 | F35: ='Flujo de Efectivo'!N20 -> 0

Sheet Configuración
B2: Configuración
B5: Año de captura | C5: 2026
B6: Mes del dashboard (1–12) | C6: 1
B8: Saldos al 31 de diciembre anterior
B9: Efectivo y bancos iniciales | C9: 0 | E9: Activos iniciales: captúralos en Activos con fecha de compra anterior al año.
B10: Cuentas por cobrar iniciales | C10: 0
B11: IVA recuperable inicial | C11: 0 | E11: Deudas iniciales: usa Saldo inicial en Pasivos, con fecha 31/12 del año anterior.
B12: Retenciones ISR a favor iniciales | C12: 0
B13: Retenciones IVA a favor iniciales | C13: 0 | E13: Capital y resultados: captura saldos reales. No se calculan para forzar el balance.
B14: Cuentas por pagar iniciales | C14: 0
B15: Anticipos de pacientes iniciales | C15: 0 | E15: Un archivo por año. Para un año nuevo, usa una copia y traslada los saldos de cierre.
B16: IVA por pagar inicial | C16: 0
B17: ISR por pagar inicial | C17: 0 | E17: Ceros iniciales son campos por completar; no son cifras reales de Neurolumens.
B18: Capital / aportaciones iniciales | C18: 0
B19: Resultados acumulados iniciales | C19: 0

Sheet Estado de Resultados
B2: Estado de Resultados
B4: MXN · enero a diciembre
B6: Concepto | C6: =DATE(Configuración!$C$5,1,1) -> 46023 | D6: =DATE(Configuración!$C$5,2,1) -> 46054 | E6: =DATE(Configuración!$C$5,3,1) -> 46082 | F6: =DATE(Configuración!$C$5,4,1) -> 46113 | G6: =DATE(Configuración!$C$5,5,1) -> 46143 | H6: =DATE(Configuración!$C$5,6,1) -> 46174 | I6: =DATE(Configuración!$C$5,7,1) -> 46204 | J6: =DATE(Configuración!$C$5,8,1) -> 46235 | K6: =DATE(Configuración!$C$5,9,1) -> 46266 | L6: =DATE(Configuración!$C$5,10,1) -> 46296 | M6: =DATE(Configuración!$C$5,11,1) -> 46327 | N6: =DATE(Configuración!$C$5,12,1) -> 46357 | O6: Total anual
B7: TMS | C7: =SUMIFS(Ingresos!$G$7:$G$2006,Ingresos!$B$7:$B$2006,">="&C$6,Ingresos!$B$7:$B$2006,"<"&EDATE(C$6,1),Ingresos!$C$7:$C$2006,"Servicio",Ingresos!$F$7:$F$2006,"TMS") -> 2200 | D7: =SUMIFS(Ingresos!$G$7:$G$2006,Ingresos!$B$7:$B$2006,">="&D$6,Ingresos!$B$7:$B$2006,"<"&EDATE(D$6,1),Ingresos!$C$7:$C$2006,"Servicio",Ingresos!$F$7:$F$2006,"TMS") -> 0 | E7: =SUMIFS(Ingresos!$G$7:$G$2006,Ingresos!$B$7:$B$2006,">="&E$6,Ingresos!$B$7:$B$2006,"<"&EDATE(E$6,1),Ingresos!$C$7:$C$2006,"Servicio",Ingresos!$F$7:$F$2006,"TMS") -> 0 | F7: =SUMIFS(Ingresos!$G$7:$G$2006,Ingresos!$B$7:$B$2006,">="&F$6,Ingresos!$B$7:$B$2006,"<"&EDATE(F$6,1),Ingresos!$C$7:$C$2006,"Servicio",Ingresos!$F$7:$F$2006,"TMS") -> 0 | G7: =SUMIFS(Ingresos!$G$7:$G$2006,Ingresos!$B$7:$B$2006,">="&G$6,Ingresos!$B$7:$B$2006,"<"&EDATE(G$6,1),Ingresos!$C$7:$C$2006,"Servicio",Ingresos!$F$7:$F$2006,"TMS") -> 0 | H7: =SUMIFS(Ingresos!$G$7:$G$2006,Ingresos!$B$7:$B$2006,">="&H$6,Ingresos!$B$7:$B$2006,"<"&EDATE(H$6,1),Ingresos!$C$7:$C$2006,"Servicio",Ingresos!$F$7:$F$2006,"TMS") -> 0 | I7: =SUMIFS(Ingresos!$G$7:$G$2006,Ingresos!$B$7:$B$2006,">="&I$6,Ingresos!$B$7:$B$2006,"<"&EDATE(I$6,1),Ingresos!$C$7:$C$2006,"Servicio",Ingresos!$F$7:$F$2006,"TMS") -> 0 | J7: =SUMIFS(Ingresos!$G$7:$G$2006,Ingresos!$B$7:$B$2006,">="&J$6,Ingresos!$B$7:$B$2006,"<"&EDATE(J$6,1),Ingresos!$C$7:$C$2006,"Servicio",Ingresos!$F$7:$F$2006,"TMS") -> 0 | ... N7: =SUMIFS(Ingresos!$G$7:$G$2006,Ingresos!$B$7:$B$2006,">="&N$6,Ingresos!$B$7:$B$2006,"<"&EDATE(N$6,1),Ingresos!$C$7:$C$2006,"Servicio",Ingresos!$F$7:$F$2006,"TMS") -> 0 | O7: =SUM(C7:N7) -> 2200
B8: Valoración | C8: =SUMIFS(Ingresos!$G$7:$G$2006,Ingresos!$B$7:$B$2006,">="&C$6,Ingresos!$B$7:$B$2006,"<"&EDATE(C$6,1),Ingresos!$C$7:$C$2006,"Servicio",Ingresos!$F$7:$F$2006,"Valoración") -> 0 | D8: =SUMIFS(Ingresos!$G$7:$G$2006,Ingresos!$B$7:$B$2006,">="&D$6,Ingresos!$B$7:$B$2006,"<"&EDATE(D$6,1),Ingresos!$C$7:$C$2006,"Servicio",Ingresos!$F$7:$F$2006,"Valoración") -> 0 | E8: =SUMIFS(Ingresos!$G$7:$G$2006,Ingresos!$B$7:$B$2006,">="&E$6,Ingresos!$B$7:$B$2006,"<"&EDATE(E$6,1),Ingresos!$C$7:$C$2006,"Servicio",Ingresos!$F$7:$F$2006,"Valoración") -> 0 | F8: =SUMIFS(Ingresos!$G$7:$G$2006,Ingresos!$B$7:$B$2006,">="&F$6,Ingresos!$B$7:$B$2006,"<"&EDATE(F$6,1),Ingresos!$C$7:$C$2006,"Servicio",Ingresos!$F$7:$F$2006,"Valoración") -> 0 | G8: =SUMIFS(Ingresos!$G$7:$G$2006,Ingresos!$B$7:$B$2006,">="&G$6,Ingresos!$B$7:$B$2006,"<"&EDATE(G$6,1),Ingresos!$C$7:$C$2006,"Servicio",Ingresos!$F$7:$F$2006,"Valoración") -> 0 | H8: =SUMIFS(Ingresos!$G$7:$G$2006,Ingresos!$B$7:$B$2006,">="&H$6,Ingresos!$B$7:$B$2006,"<"&EDATE(H$6,1),Ingresos!$C$7:$C$2006,"Servicio",Ingresos!$F$7:$F$2006,"Valoración") -> 0 | I8: =SUMIFS(Ingresos!$G$7:$G$2006,Ingresos!$B$7:$B$2006,">="&I$6,Ingresos!$B$7:$B$2006,"<"&EDATE(I$6,1),Ingresos!$C$7:$C$2006,"Servicio",Ingresos!$F$7:$F$2006,"Valoración") -> 0 | J8: =SUMIFS(Ingresos!$G$7:$G$2006,Ingresos!$B$7:$B$2006,">="&J$6,Ingresos!$B$7:$B$2006,"<"&EDATE(J$6,1),Ingresos!$C$7:$C$2006,"Servicio",Ingresos!$F$7:$F$2006,"Valoración") -> 0 | ... N8: =SUMIFS(Ingresos!$G$7:$G$2006,Ingresos!$B$7:$B$2006,">="&N$6,Ingresos!$B$7:$B$2006,"<"&EDATE(N$6,1),Ingresos!$C$7:$C$2006,"Servicio",Ingresos!$F$7:$F$2006,"Valoración") -> 0 | O8: =SUM(C8:N8) -> 0
B9: EEG | C9: =SUMIFS(Ingresos!$G$7:$G$2006,Ingresos!$B$7:$B$2006,">="&C$6,Ingresos!$B$7:$B$2006,"<"&EDATE(C$6,1),Ingresos!$C$7:$C$2006,"Servicio",Ingresos!$F$7:$F$2006,"EEG") -> 0 | D9: =SUMIFS(Ingresos!$G$7:$G$2006,Ingresos!$B$7:$B$2006,">="&D$6,Ingresos!$B$7:$B$2006,"<"&EDATE(D$6,1),Ingresos!$C$7:$C$2006,"Servicio",Ingresos!$F$7:$F$2006,"EEG") -> 0 | E9: =SUMIFS(Ingresos!$G$7:$G$2006,Ingresos!$B$7:$B$2006,">="&E$6,Ingresos!$B$7:$B$2006,"<"&EDATE(E$6,1),Ingresos!$C$7:$C$2006,"Servicio",Ingresos!$F$7:$F$2006,"EEG") -> 0 | F9: =SUMIFS(Ingresos!$G$7:$G$2006,Ingresos!$B$7:$B$2006,">="&F$6,Ingresos!$B$7:$B$2006,"<"&EDATE(F$6,1),Ingresos!$C$7:$C$2006,"Servicio",Ingresos!$F$7:$F$2006,"EEG") -> 0 | G9: =SUMIFS(Ingresos!$G$7:$G$2006,Ingresos!$B$7:$B$2006,">="&G$6,Ingresos!$B$7:$B$2006,"<"&EDATE(G$6,1),Ingresos!$C$7:$C$2006,"Servicio",Ingresos!$F$7:$F$2006,"EEG") -> 0 | H9: =SUMIFS(Ingresos!$G$7:$G$2006,Ingresos!$B$7:$B$2006,">="&H$6,Ingresos!$B$7:$B$2006,"<"&EDATE(H$6,1),Ingresos!$C$7:$C$2006,"Servicio",Ingresos!$F$7:$F$2006,"EEG") -> 0 | I9: =SUMIFS(Ingresos!$G$7:$G$2006,Ingresos!$B$7:$B$2006,">="&I$6,Ingresos!$B$7:$B$2006,"<"&EDATE(I$6,1),Ingresos!$C$7:$C$2006,"Servicio",Ingresos!$F$7:$F$2006,"EEG") -> 0 | J9: =SUMIFS(Ingresos!$G$7:$G$2006,Ingresos!$B$7:$B$2006,">="&J$6,Ingresos!$B$7:$B$2006,"<"&EDATE(J$6,1),Ingresos!$C$7:$C$2006,"Servicio",Ingresos!$F$7:$F$2006,"EEG") -> 0 | ... N9: =SUMIFS(Ingresos!$G$7:$G$2006,Ingresos!$B$7:$B$2006,">="&N$6,Ingresos!$B$7:$B$2006,"<"&EDATE(N$6,1),Ingresos!$C$7:$C$2006,"Servicio",Ingresos!$F$7:$F$2006,"EEG") -> 0 | O9: =SUM(C9:N9) -> 0
B10: Neurofeedback | C10: =SUMIFS(Ingresos!$G$7:$G$2006,Ingresos!$B$7:$B$2006,">="&C$6,Ingresos!$B$7:$B$2006,"<"&EDATE(C$6,1),Ingresos!$C$7:$C$2006,"Servicio",Ingresos!$F$7:$F$2006,"Neurofeedback") -> 0 | D10: =SUMIFS(Ingresos!$G$7:$G$2006,Ingresos!$B$7:$B$2006,">="&D$6,Ingresos!$B$7:$B$2006,"<"&EDATE(D$6,1),Ingresos!$C$7:$C$2006,"Servicio",Ingresos!$F$7:$F$2006,"Neurofeedback") -> 0 | E10: =SUMIFS(Ingresos!$G$7:$G$2006,Ingresos!$B$7:$B$2006,">="&E$6,Ingresos!$B$7:$B$2006,"<"&EDATE(E$6,1),Ingresos!$C$7:$C$2006,"Servicio",Ingresos!$F$7:$F$2006,"Neurofeedback") -> 0 | F10: =SUMIFS(Ingresos!$G$7:$G$2006,Ingresos!$B$7:$B$2006,">="&F$6,Ingresos!$B$7:$B$2006,"<"&EDATE(F$6,1),Ingresos!$C$7:$C$2006,"Servicio",Ingresos!$F$7:$F$2006,"Neurofeedback") -> 0 | G10: =SUMIFS(Ingresos!$G$7:$G$2006,Ingresos!$B$7:$B$2006,">="&G$6,Ingresos!$B$7:$B$2006,"<"&EDATE(G$6,1),Ingresos!$C$7:$C$2006,"Servicio",Ingresos!$F$7:$F$2006,"Neurofeedback") -> 0 | H10: =SUMIFS(Ingresos!$G$7:$G$2006,Ingresos!$B$7:$B$2006,">="&H$6,Ingresos!$B$7:$B$2006,"<"&EDATE(H$6,1),Ingresos!$C$7:$C$2006,"Servicio",Ingresos!$F$7:$F$2006,"Neurofeedback") -> 0 | I10: =SUMIFS(Ingresos!$G$7:$G$2006,Ingresos!$B$7:$B$2006,">="&I$6,Ingresos!$B$7:$B$2006,"<"&EDATE(I$6,1),Ingresos!$C$7:$C$2006,"Servicio",Ingresos!$F$7:$F$2006,"Neurofeedback") -> 0 | J10: =SUMIFS(Ingresos!$G$7:$G$2006,Ingresos!$B$7:$B$2006,">="&J$6,Ingresos!$B$7:$B$2006,"<"&EDATE(J$6,1),Ingresos!$C$7:$C$2006,"Servicio",Ingresos!$F$7:$F$2006,"Neurofeedback") -> 0 | ... N10: =SUMIFS(Ingresos!$G$7:$G$2006,Ingresos!$B$7:$B$2006,">="&N$6,Ingresos!$B$7:$B$2006,"<"&EDATE(N$6,1),Ingresos!$C$7:$C$2006,"Servicio",Ingresos!$F$7:$F$2006,"Neurofeedback") -> 0 | O10: =SUM(C10:N10) -> 0
B11: Fotobiomodulación | C11: =SUMIFS(Ingresos!$G$7:$G$2006,Ingresos!$B$7:$B$2006,">="&C$6,Ingresos!$B$7:$B$2006,"<"&EDATE(C$6,1),Ingresos!$C$7:$C$2006,"Servicio",Ingresos!$F$7:$F$2006,"Fotobiomodulación") -> 0 | D11: =SUMIFS(Ingresos!$G$7:$G$2006,Ingresos!$B$7:$B$2006,">="&D$6,Ingresos!$B$7:$B$2006,"<"&EDATE(D$6,1),Ingresos!$C$7:$C$2006,"Servicio",Ingresos!$F$7:$F$2006,"Fotobiomodulación") -> 0 | E11: =SUMIFS(Ingresos!$G$7:$G$2006,Ingresos!$B$7:$B$2006,">="&E$6,Ingresos!$B$7:$B$2006,"<"&EDATE(E$6,1),Ingresos!$C$7:$C$2006,"Servicio",Ingresos!$F$7:$F$2006,"Fotobiomodulación") -> 0 | F11: =SUMIFS(Ingresos!$G$7:$G$2006,Ingresos!$B$7:$B$2006,">="&F$6,Ingresos!$B$7:$B$2006,"<"&EDATE(F$6,1),Ingresos!$C$7:$C$2006,"Servicio",Ingresos!$F$7:$F$2006,"Fotobiomodulación") -> 0 | G11: =SUMIFS(Ingresos!$G$7:$G$2006,Ingresos!$B$7:$B$2006,">="&G$6,Ingresos!$B$7:$B$2006,"<"&EDATE(G$6,1),Ingresos!$C$7:$C$2006,"Servicio",Ingresos!$F$7:$F$2006,"Fotobiomodulación") -> 0 | H11: =SUMIFS(Ingresos!$G$7:$G$2006,Ingresos!$B$7:$B$2006,">="&H$6,Ingresos!$B$7:$B$2006,"<"&EDATE(H$6,1),Ingresos!$C$7:$C$2006,"Servicio",Ingresos!$F$7:$F$2006,"Fotobiomodulación") -> 0 | I11: =SUMIFS(Ingresos!$G$7:$G$2006,Ingresos!$B$7:$B$2006,">="&I$6,Ingresos!$B$7:$B$2006,"<"&EDATE(I$6,1),Ingresos!$C$7:$C$2006,"Servicio",Ingresos!$F$7:$F$2006,"Fotobiomodulación") -> 0 | J11: =SUMIFS(Ingresos!$G$7:$G$2006,Ingresos!$B$7:$B$2006,">="&J$6,Ingresos!$B$7:$B$2006,"<"&EDATE(J$6,1),Ingresos!$C$7:$C$2006,"Servicio",Ingresos!$F$7:$F$2006,"Fotobiomodulación") -> 0 | ... N11: =SUMIFS(Ingresos!$G$7:$G$2006,Ingresos!$B$7:$B$2006,">="&N$6,Ingresos!$B$7:$B$2006,"<"&EDATE(N$6,1),Ingresos!$C$7:$C$2006,"Servicio",Ingresos!$F$7:$F$2006,"Fotobiomodulación") -> 0 | O11: =SUM(C11:N11) -> 0
B12: Psicoterapia | C12: =SUMIFS(Ingresos!$G$7:$G$2006,Ingresos!$B$7:$B$2006,">="&C$6,Ingresos!$B$7:$B$2006,"<"&EDATE(C$6,1),Ingresos!$C$7:$C$2006,"Servicio",Ingresos!$F$7:$F$2006,"Psicoterapia") -> 0 | D12: =SUMIFS(Ingresos!$G$7:$G$2006,Ingresos!$B$7:$B$2006,">="&D$6,Ingresos!$B$7:$B$2006,"<"&EDATE(D$6,1),Ingresos!$C$7:$C$2006,"Servicio",Ingresos!$F$7:$F$2006,"Psicoterapia") -> 0 | E12: =SUMIFS(Ingresos!$G$7:$G$2006,Ingresos!$B$7:$B$2006,">="&E$6,Ingresos!$B$7:$B$2006,"<"&EDATE(E$6,1),Ingresos!$C$7:$C$2006,"Servicio",Ingresos!$F$7:$F$2006,"Psicoterapia") -> 0 | F12: =SUMIFS(Ingresos!$G$7:$G$2006,Ingresos!$B$7:$B$2006,">="&F$6,Ingresos!$B$7:$B$2006,"<"&EDATE(F$6,1),Ingresos!$C$7:$C$2006,"Servicio",Ingresos!$F$7:$F$2006,"Psicoterapia") -> 0 | G12: =SUMIFS(Ingresos!$G$7:$G$2006,Ingresos!$B$7:$B$2006,">="&G$6,Ingresos!$B$7:$B$2006,"<"&EDATE(G$6,1),Ingresos!$C$7:$C$2006,"Servicio",Ingresos!$F$7:$F$2006,"Psicoterapia") -> 0 | H12: =SUMIFS(Ingresos!$G$7:$G$2006,Ingresos!$B$7:$B$2006,">="&H$6,Ingresos!$B$7:$B$2006,"<"&EDATE(H$6,1),Ingresos!$C$7:$C$2006,"Servicio",Ingresos!$F$7:$F$2006,"Psicoterapia") -> 0 | I12: =SUMIFS(Ingresos!$G$7:$G$2006,Ingresos!$B$7:$B$2006,">="&I$6,Ingresos!$B$7:$B$2006,"<"&EDATE(I$6,1),Ingresos!$C$7:$C$2006,"Servicio",Ingresos!$F$7:$F$2006,"Psicoterapia") -> 0 | J12: =SUMIFS(Ingresos!$G$7:$G$2006,Ingresos!$B$7:$B$2006,">="&J$6,Ingresos!$B$7:$B$2006,"<"&EDATE(J$6,1),Ingresos!$C$7:$C$2006,"Servicio",Ingresos!$F$7:$F$2006,"Psicoterapia") -> 0 | ... N12: =SUMIFS(Ingresos!$G$7:$G$2006,Ingresos!$B$7:$B$2006,">="&N$6,Ingresos!$B$7:$B$2006,"<"&EDATE(N$6,1),Ingresos!$C$7:$C$2006,"Servicio",Ingresos!$F$7:$F$2006,"Psicoterapia") -> 0 | O12: =SUM(C12:N12) -> 0
B13: Otros | C13: =SUMIFS(Ingresos!$G$7:$G$2006,Ingresos!$B$7:$B$2006,">="&C$6,Ingresos!$B$7:$B$2006,"<"&EDATE(C$6,1),Ingresos!$C$7:$C$2006,"Servicio",Ingresos!$F$7:$F$2006,"Otros") -> 0 | D13: =SUMIFS(Ingresos!$G$7:$G$2006,Ingresos!$B$7:$B$2006,">="&D$6,Ingresos!$B$7:$B$2006,"<"&EDATE(D$6,1),Ingresos!$C$7:$C$2006,"Servicio",Ingresos!$F$7:$F$2006,"Otros") -> 0 | E13: =SUMIFS(Ingresos!$G$7:$G$2006,Ingresos!$B$7:$B$2006,">="&E$6,Ingresos!$B$7:$B$2006,"<"&EDATE(E$6,1),Ingresos!$C$7:$C$2006,"Servicio",Ingresos!$F$7:$F$2006,"Otros") -> 0 | F13: =SUMIFS(Ingresos!$G$7:$G$2006,Ingresos!$B$7:$B$2006,">="&F$6,Ingresos!$B$7:$B$2006,"<"&EDATE(F$6,1),Ingresos!$C$7:$C$2006,"Servicio",Ingresos!$F$7:$F$2006,"Otros") -> 0 | G13: =SUMIFS(Ingresos!$G$7:$G$2006,Ingresos!$B$7:$B$2006,">="&G$6,Ingresos!$B$7:$B$2006,"<"&EDATE(G$6,1),Ingresos!$C$7:$C$2006,"Servicio",Ingresos!$F$7:$F$2006,"Otros") -> 0 | H13: =SUMIFS(Ingresos!$G$7:$G$2006,Ingresos!$B$7:$B$2006,">="&H$6,Ingresos!$B$7:$B$2006,"<"&EDATE(H$6,1),Ingresos!$C$7:$C$2006,"Servicio",Ingresos!$F$7:$F$2006,"Otros") -> 0 | I13: =SUMIFS(Ingresos!$G$7:$G$2006,Ingresos!$B$7:$B$2006,">="&I$6,Ingresos!$B$7:$B$2006,"<"&EDATE(I$6,1),Ingresos!$C$7:$C$2006,"Servicio",Ingresos!$F$7:$F$2006,"Otros") -> 0 | J13: =SUMIFS(Ingresos!$G$7:$G$2006,Ingresos!$B$7:$B$2006,">="&J$6,Ingresos!$B$7:$B$2006,"<"&EDATE(J$6,1),Ingresos!$C$7:$C$2006,"Servicio",Ingresos!$F$7:$F$2006,"Otros") -> 0 | ... N13: =SUMIFS(Ingresos!$G$7:$G$2006,Ingresos!$B$7:$B$2006,">="&N$6,Ingresos!$B$7:$B$2006,"<"&EDATE(N$6,1),Ingresos!$C$7:$C$2006,"Servicio",Ingresos!$F$7:$F$2006,"Otros") -> 0 | O13: =SUM(C13:N13) -> 0
B14: Ingresos por servicios | C14: =SUM(C7:C13) -> 2200 | D14: =SUM(D7:D13) -> 0 | E14: =SUM(E7:E13) -> 0 | F14: =SUM(F7:F13) -> 0 | G14: =SUM(G7:G13) -> 0 | H14: =SUM(H7:H13) -> 0 | I14: =SUM(I7:I13) -> 0 | J14: =SUM(J7:J13) -> 0 | ... N14: =SUM(N7:N13) -> 0 | O14: =SUM(C14:N14) -> 2200
B16: Costos clínicos | C16: =SUMIFS(Gastos!$H$7:$H$2006,Gastos!$B$7:$B$2006,">="&C$6,Gastos!$B$7:$B$2006,"<"&EDATE(C$6,1),Gastos!$C$7:$C$2006,"Gasto",Gastos!$D$7:$D$2006,"Costos clínicos") -> 0 | D16: =SUMIFS(Gastos!$H$7:$H$2006,Gastos!$B$7:$B$2006,">="&D$6,Gastos!$B$7:$B$2006,"<"&EDATE(D$6,1),Gastos!$C$7:$C$2006,"Gasto",Gastos!$D$7:$D$2006,"Costos clínicos") -> 0 | E16: =SUMIFS(Gastos!$H$7:$H$2006,Gastos!$B$7:$B$2006,">="&E$6,Gastos!$B$7:$B$2006,"<"&EDATE(E$6,1),Gastos!$C$7:$C$2006,"Gasto",Gastos!$D$7:$D$2006,"Costos clínicos") -> 0 | F16: =SUMIFS(Gastos!$H$7:$H$2006,Gastos!$B$7:$B$2006,">="&F$6,Gastos!$B$7:$B$2006,"<"&EDATE(F$6,1),Gastos!$C$7:$C$2006,"Gasto",Gastos!$D$7:$D$2006,"Costos clínicos") -> 0 | G16: =SUMIFS(Gastos!$H$7:$H$2006,Gastos!$B$7:$B$2006,">="&G$6,Gastos!$B$7:$B$2006,"<"&EDATE(G$6,1),Gastos!$C$7:$C$2006,"Gasto",Gastos!$D$7:$D$2006,"Costos clínicos") -> 0 | H16: =SUMIFS(Gastos!$H$7:$H$2006,Gastos!$B$7:$B$2006,">="&H$6,Gastos!$B$7:$B$2006,"<"&EDATE(H$6,1),Gastos!$C$7:$C$2006,"Gasto",Gastos!$D$7:$D$2006,"Costos clínicos") -> 0 | I16: =SUMIFS(Gastos!$H$7:$H$2006,Gastos!$B$7:$B$2006,">="&I$6,Gastos!$B$7:$B$2006,"<"&EDATE(I$6,1),Gastos!$C$7:$C$2006,"Gasto",Gastos!$D$7:$D$2006,"Costos clínicos") -> 0 | J16: =SUMIFS(Gastos!$H$7:$H$2006,Gastos!$B$7:$B$2006,">="&J$6,Gastos!$B$7:$B$2006,"<"&EDATE(J$6,1),Gastos!$C$7:$C$2006,"Gasto",Gastos!$D$7:$D$2006,"Costos clínicos") -> 0 | ... N16: =SUMIFS(Gastos!$H$7:$H$2006,Gastos!$B$7:$B$2006,">="&N$6,Gastos!$B$7:$B$2006,"<"&EDATE(N$6,1),Gastos!$C$7:$C$2006,"Gasto",Gastos!$D$7:$D$2006,"Costos clínicos") -> 0 | O16: =SUM(C16:N16) -> 0
B17: Utilidad bruta | C17: =C14-C16 -> 2200 | D17: =D14-D16 -> 0 | E17: =E14-E16 -> 0 | F17: =F14-F16 -> 0 | G17: =G14-G16 -> 0 | H17: =H14-H16 -> 0 | I17: =I14-I16 -> 0 | J17: =J14-J16 -> 0 | ... N17: =N14-N16 -> 0 | O17: =SUM(C17:N17) -> 2200
B19: Remuneración familiar por trabajo | C19: =SUMIFS(Gastos!$H$7:$H$2006,Gastos!$B$7:$B$2006,">="&C$6,Gastos!$B$7:$B$2006,"<"&EDATE(C$6,1),Gastos!$C$7:$C$2006,"Gasto",Gastos!$D$7:$D$2006,"Remuneración familiar") -> 0 | D19: =SUMIFS(Gastos!$H$7:$H$2006,Gastos!$B$7:$B$2006,">="&D$6,Gastos!$B$7:$B$2006,"<"&EDATE(D$6,1),Gastos!$C$7:$C$2006,"Gasto",Gastos!$D$7:$D$2006,"Remuneración familiar") -> 0 | E19: =SUMIFS(Gastos!$H$7:$H$2006,Gastos!$B$7:$B$2006,">="&E$6,Gastos!$B$7:$B$2006,"<"&EDATE(E$6,1),Gastos!$C$7:$C$2006,"Gasto",Gastos!$D$7:$D$2006,"Remuneración familiar") -> 0 | F19: =SUMIFS(Gastos!$H$7:$H$2006,Gastos!$B$7:$B$2006,">="&F$6,Gastos!$B$7:$B$2006,"<"&EDATE(F$6,1),Gastos!$C$7:$C$2006,"Gasto",Gastos!$D$7:$D$2006,"Remuneración familiar") -> 0 | G19: =SUMIFS(Gastos!$H$7:$H$2006,Gastos!$B$7:$B$2006,">="&G$6,Gastos!$B$7:$B$2006,"<"&EDATE(G$6,1),Gastos!$C$7:$C$2006,"Gasto",Gastos!$D$7:$D$2006,"Remuneración familiar") -> 0 | H19: =SUMIFS(Gastos!$H$7:$H$2006,Gastos!$B$7:$B$2006,">="&H$6,Gastos!$B$7:$B$2006,"<"&EDATE(H$6,1),Gastos!$C$7:$C$2006,"Gasto",Gastos!$D$7:$D$2006,"Remuneración familiar") -> 0 | I19: =SUMIFS(Gastos!$H$7:$H$2006,Gastos!$B$7:$B$2006,">="&I$6,Gastos!$B$7:$B$2006,"<"&EDATE(I$6,1),Gastos!$C$7:$C$2006,"Gasto",Gastos!$D$7:$D$2006,"Remuneración familiar") -> 0 | J19: =SUMIFS(Gastos!$H$7:$H$2006,Gastos!$B$7:$B$2006,">="&J$6,Gastos!$B$7:$B$2006,"<"&EDATE(J$6,1),Gastos!$C$7:$C$2006,"Gasto",Gastos!$D$7:$D$2006,"Remuneración familiar") -> 0 | ... N19: =SUMIFS(Gastos!$H$7:$H$2006,Gastos!$B$7:$B$2006,">="&N$6,Gastos!$B$7:$B$2006,"<"&EDATE(N$6,1),Gastos!$C$7:$C$2006,"Gasto",Gastos!$D$7:$D$2006,"Remuneración familiar") -> 0 | O19: =SUM(C19:N19) -> 0
B20: Nómina y honorarios | C20: =SUMIFS(Gastos!$H$7:$H$2006,Gastos!$B$7:$B$2006,">="&C$6,Gastos!$B$7:$B$2006,"<"&EDATE(C$6,1),Gastos!$C$7:$C$2006,"Gasto",Gastos!$D$7:$D$2006,"Nómina y honorarios") -> 0 | D20: =SUMIFS(Gastos!$H$7:$H$2006,Gastos!$B$7:$B$2006,">="&D$6,Gastos!$B$7:$B$2006,"<"&EDATE(D$6,1),Gastos!$C$7:$C$2006,"Gasto",Gastos!$D$7:$D$2006,"Nómina y honorarios") -> 0 | E20: =SUMIFS(Gastos!$H$7:$H$2006,Gastos!$B$7:$B$2006,">="&E$6,Gastos!$B$7:$B$2006,"<"&EDATE(E$6,1),Gastos!$C$7:$C$2006,"Gasto",Gastos!$D$7:$D$2006,"Nómina y honorarios") -> 0 | F20: =SUMIFS(Gastos!$H$7:$H$2006,Gastos!$B$7:$B$2006,">="&F$6,Gastos!$B$7:$B$2006,"<"&EDATE(F$6,1),Gastos!$C$7:$C$2006,"Gasto",Gastos!$D$7:$D$2006,"Nómina y honorarios") -> 0 | G20: =SUMIFS(Gastos!$H$7:$H$2006,Gastos!$B$7:$B$2006,">="&G$6,Gastos!$B$7:$B$2006,"<"&EDATE(G$6,1),Gastos!$C$7:$C$2006,"Gasto",Gastos!$D$7:$D$2006,"Nómina y honorarios") -> 0 | H20: =SUMIFS(Gastos!$H$7:$H$2006,Gastos!$B$7:$B$2006,">="&H$6,Gastos!$B$7:$B$2006,"<"&EDATE(H$6,1),Gastos!$C$7:$C$2006,"Gasto",Gastos!$D$7:$D$2006,"Nómina y honorarios") -> 0 | I20: =SUMIFS(Gastos!$H$7:$H$2006,Gastos!$B$7:$B$2006,">="&I$6,Gastos!$B$7:$B$2006,"<"&EDATE(I$6,1),Gastos!$C$7:$C$2006,"Gasto",Gastos!$D$7:$D$2006,"Nómina y honorarios") -> 0 | J20: =SUMIFS(Gastos!$H$7:$H$2006,Gastos!$B$7:$B$2006,">="&J$6,Gastos!$B$7:$B$2006,"<"&EDATE(J$6,1),Gastos!$C$7:$C$2006,"Gasto",Gastos!$D$7:$D$2006,"Nómina y honorarios") -> 0 | ... N20: =SUMIFS(Gastos!$H$7:$H$2006,Gastos!$B$7:$B$2006,">="&N$6,Gastos!$B$7:$B$2006,"<"&EDATE(N$6,1),Gastos!$C$7:$C$2006,"Gasto",Gastos!$D$7:$D$2006,"Nómina y honorarios") -> 0 | O20: =SUM(C20:N20) -> 0
B21: Renta | C21: =SUMIFS(Gastos!$H$7:$H$2006,Gastos!$B$7:$B$2006,">="&C$6,Gastos!$B$7:$B$2006,"<"&EDATE(C$6,1),Gastos!$C$7:$C$2006,"Gasto",Gastos!$D$7:$D$2006,"Renta") -> 0 | D21: =SUMIFS(Gastos!$H$7:$H$2006,Gastos!$B$7:$B$2006,">="&D$6,Gastos!$B$7:$B$2006,"<"&EDATE(D$6,1),Gastos!$C$7:$C$2006,"Gasto",Gastos!$D$7:$D$2006,"Renta") -> 0 | E21: =SUMIFS(Gastos!$H$7:$H$2006,Gastos!$B$7:$B$2006,">="&E$6,Gastos!$B$7:$B$2006,"<"&EDATE(E$6,1),Gastos!$C$7:$C$2006,"Gasto",Gastos!$D$7:$D$2006,"Renta") -> 0 | F21: =SUMIFS(Gastos!$H$7:$H$2006,Gastos!$B$7:$B$2006,">="&F$6,Gastos!$B$7:$B$2006,"<"&EDATE(F$6,1),Gastos!$C$7:$C$2006,"Gasto",Gastos!$D$7:$D$2006,"Renta") -> 0 | G21: =SUMIFS(Gastos!$H$7:$H$2006,Gastos!$B$7:$B$2006,">="&G$6,Gastos!$B$7:$B$2006,"<"&EDATE(G$6,1),Gastos!$C$7:$C$2006,"Gasto",Gastos!$D$7:$D$2006,"Renta") -> 0 | H21: =SUMIFS(Gastos!$H$7:$H$2006,Gastos!$B$7:$B$2006,">="&H$6,Gastos!$B$7:$B$2006,"<"&EDATE(H$6,1),Gastos!$C$7:$C$2006,"Gasto",Gastos!$D$7:$D$2006,"Renta") -> 0 | I21: =SUMIFS(Gastos!$H$7:$H$2006,Gastos!$B$7:$B$2006,">="&I$6,Gastos!$B$7:$B$2006,"<"&EDATE(I$6,1),Gastos!$C$7:$C$2006,"Gasto",Gastos!$D$7:$D$2006,"Renta") -> 0 | J21: =SUMIFS(Gastos!$H$7:$H$2006,Gastos!$B$7:$B$2006,">="&J$6,Gastos!$B$7:$B$2006,"<"&EDATE(J$6,1),Gastos!$C$7:$C$2006,"Gasto",Gastos!$D$7:$D$2006,"Renta") -> 0 | ... N21: =SUMIFS(Gastos!$H$7:$H$2006,Gastos!$B$7:$B$2006,">="&N$6,Gastos!$B$7:$B$2006,"<"&EDATE(N$6,1),Gastos!$C$7:$C$2006,"Gasto",Gastos!$D$7:$D$2006,"Renta") -> 0 | O21: =SUM(C21:N21) -> 0
B22: Marketing | C22: =SUMIFS(Gastos!$H$7:$H$2006,Gastos!$B$7:$B$2006,">="&C$6,Gastos!$B$7:$B$2006,"<"&EDATE(C$6,1),Gastos!$C$7:$C$2006,"Gasto",Gastos!$D$7:$D$2006,"Marketing") -> 0 | D22: =SUMIFS(Gastos!$H$7:$H$2006,Gastos!$B$7:$B$2006,">="&D$6,Gastos!$B$7:$B$2006,"<"&EDATE(D$6,1),Gastos!$C$7:$C$2006,"Gasto",Gastos!$D$7:$D$2006,"Marketing") -> 0 | E22: =SUMIFS(Gastos!$H$7:$H$2006,Gastos!$B$7:$B$2006,">="&E$6,Gastos!$B$7:$B$2006,"<"&EDATE(E$6,1),Gastos!$C$7:$C$2006,"Gasto",Gastos!$D$7:$D$2006,"Marketing") -> 0 | F22: =SUMIFS(Gastos!$H$7:$H$2006,Gastos!$B$7:$B$2006,">="&F$6,Gastos!$B$7:$B$2006,"<"&EDATE(F$6,1),Gastos!$C$7:$C$2006,"Gasto",Gastos!$D$7:$D$2006,"Marketing") -> 0 | G22: =SUMIFS(Gastos!$H$7:$H$2006,Gastos!$B$7:$B$2006,">="&G$6,Gastos!$B$7:$B$2006,"<"&EDATE(G$6,1),Gastos!$C$7:$C$2006,"Gasto",Gastos!$D$7:$D$2006,"Marketing") -> 0 | H22: =SUMIFS(Gastos!$H$7:$H$2006,Gastos!$B$7:$B$2006,">="&H$6,Gastos!$B$7:$B$2006,"<"&EDATE(H$6,1),Gastos!$C$7:$C$2006,"Gasto",Gastos!$D$7:$D$2006,"Marketing") -> 0 | I22: =SUMIFS(Gastos!$H$7:$H$2006,Gastos!$B$7:$B$2006,">="&I$6,Gastos!$B$7:$B$2006,"<"&EDATE(I$6,1),Gastos!$C$7:$C$2006,"Gasto",Gastos!$D$7:$D$2006,"Marketing") -> 0 | J22: =SUMIFS(Gastos!$H$7:$H$2006,Gastos!$B$7:$B$2006,">="&J$6,Gastos!$B$7:$B$2006,"<"&EDATE(J$6,1),Gastos!$C$7:$C$2006,"Gasto",Gastos!$D$7:$D$2006,"Marketing") -> 0 | ... N22: =SUMIFS(Gastos!$H$7:$H$2006,Gastos!$B$7:$B$2006,">="&N$6,Gastos!$B$7:$B$2006,"<"&EDATE(N$6,1),Gastos!$C$7:$C$2006,"Gasto",Gastos!$D$7:$D$2006,"Marketing") -> 0 | O22: =SUM(C22:N22) -> 0
B23: Servicios y software | C23: =SUMIFS(Gastos!$H$7:$H$2006,Gastos!$B$7:$B$2006,">="&C$6,Gastos!$B$7:$B$2006,"<"&EDATE(C$6,1),Gastos!$C$7:$C$2006,"Gasto",Gastos!$D$7:$D$2006,"Servicios y software") -> 0 | D23: =SUMIFS(Gastos!$H$7:$H$2006,Gastos!$B$7:$B$2006,">="&D$6,Gastos!$B$7:$B$2006,"<"&EDATE(D$6,1),Gastos!$C$7:$C$2006,"Gasto",Gastos!$D$7:$D$2006,"Servicios y software") -> 0 | E23: =SUMIFS(Gastos!$H$7:$H$2006,Gastos!$B$7:$B$2006,">="&E$6,Gastos!$B$7:$B$2006,"<"&EDATE(E$6,1),Gastos!$C$7:$C$2006,"Gasto",Gastos!$D$7:$D$2006,"Servicios y software") -> 0 | F23: =SUMIFS(Gastos!$H$7:$H$2006,Gastos!$B$7:$B$2006,">="&F$6,Gastos!$B$7:$B$2006,"<"&EDATE(F$6,1),Gastos!$C$7:$C$2006,"Gasto",Gastos!$D$7:$D$2006,"Servicios y software") -> 0 | G23: =SUMIFS(Gastos!$H$7:$H$2006,Gastos!$B$7:$B$2006,">="&G$6,Gastos!$B$7:$B$2006,"<"&EDATE(G$6,1),Gastos!$C$7:$C$2006,"Gasto",Gastos!$D$7:$D$2006,"Servicios y software") -> 0 | H23: =SUMIFS(Gastos!$H$7:$H$2006,Gastos!$B$7:$B$2006,">="&H$6,Gastos!$B$7:$B$2006,"<"&EDATE(H$6,1),Gastos!$C$7:$C$2006,"Gasto",Gastos!$D$7:$D$2006,"Servicios y software") -> 0 | I23: =SUMIFS(Gastos!$H$7:$H$2006,Gastos!$B$7:$B$2006,">="&I$6,Gastos!$B$7:$B$2006,"<"&EDATE(I$6,1),Gastos!$C$7:$C$2006,"Gasto",Gastos!$D$7:$D$2006,"Servicios y software") -> 0 | J23: =SUMIFS(Gastos!$H$7:$H$2006,Gastos!$B$7:$B$2006,">="&J$6,Gastos!$B$7:$B$2006,"<"&EDATE(J$6,1),Gastos!$C$7:$C$2006,"Gasto",Gastos!$D$7:$D$2006,"Servicios y software") -> 0 | ... N23: =SUMIFS(Gastos!$H$7:$H$2006,Gastos!$B$7:$B$2006,">="&N$6,Gastos!$B$7:$B$2006,"<"&EDATE(N$6,1),Gastos!$C$7:$C$2006,"Gasto",Gastos!$D$7:$D$2006,"Servicios y software") -> 0 | O23: =SUM(C23:N23) -> 0
B24: Mantenimiento | C24: =SUMIFS(Gastos!$H$7:$H$2006,Gastos!$B$7:$B$2006,">="&C$6,Gastos!$B$7:$B$2006,"<"&EDATE(C$6,1),Gastos!$C$7:$C$2006,"Gasto",Gastos!$D$7:$D$2006,"Mantenimiento") -> 0 | D24: =SUMIFS(Gastos!$H$7:$H$2006,Gastos!$B$7:$B$2006,">="&D$6,Gastos!$B$7:$B$2006,"<"&EDATE(D$6,1),Gastos!$C$7:$C$2006,"Gasto",Gastos!$D$7:$D$2006,"Mantenimiento") -> 0 | E24: =SUMIFS(Gastos!$H$7:$H$2006,Gastos!$B$7:$B$2006,">="&E$6,Gastos!$B$7:$B$2006,"<"&EDATE(E$6,1),Gastos!$C$7:$C$2006,"Gasto",Gastos!$D$7:$D$2006,"Mantenimiento") -> 0 | F24: =SUMIFS(Gastos!$H$7:$H$2006,Gastos!$B$7:$B$2006,">="&F$6,Gastos!$B$7:$B$2006,"<"&EDATE(F$6,1),Gastos!$C$7:$C$2006,"Gasto",Gastos!$D$7:$D$2006,"Mantenimiento") -> 0 | G24: =SUMIFS(Gastos!$H$7:$H$2006,Gastos!$B$7:$B$2006,">="&G$6,Gastos!$B$7:$B$2006,"<"&EDATE(G$6,1),Gastos!$C$7:$C$2006,"Gasto",Gastos!$D$7:$D$2006,"Mantenimiento") -> 0 | H24: =SUMIFS(Gastos!$H$7:$H$2006,Gastos!$B$7:$B$2006,">="&H$6,Gastos!$B$7:$B$2006,"<"&EDATE(H$6,1),Gastos!$C$7:$C$2006,"Gasto",Gastos!$D$7:$D$2006,"Mantenimiento") -> 0 | I24: =SUMIFS(Gastos!$H$7:$H$2006,Gastos!$B$7:$B$2006,">="&I$6,Gastos!$B$7:$B$2006,"<"&EDATE(I$6,1),Gastos!$C$7:$C$2006,"Gasto",Gastos!$D$7:$D$2006,"Mantenimiento") -> 0 | J24: =SUMIFS(Gastos!$H$7:$H$2006,Gastos!$B$7:$B$2006,">="&J$6,Gastos!$B$7:$B$2006,"<"&EDATE(J$6,1),Gastos!$C$7:$C$2006,"Gasto",Gastos!$D$7:$D$2006,"Mantenimiento") -> 0 | ... N24: =SUMIFS(Gastos!$H$7:$H$2006,Gastos!$B$7:$B$2006,">="&N$6,Gastos!$B$7:$B$2006,"<"&EDATE(N$6,1),Gastos!$C$7:$C$2006,"Gasto",Gastos!$D$7:$D$2006,"Mantenimiento") -> 0 | O24: =SUM(C24:N24) -> 0
B25: Otros gastos operativos | C25: =SUMIFS(Gastos!$H$7:$H$2006,Gastos!$B$7:$B$2006,">="&C$6,Gastos!$B$7:$B$2006,"<"&EDATE(C$6,1),Gastos!$C$7:$C$2006,"Gasto",Gastos!$D$7:$D$2006,"Otros") -> 0 | D25: =SUMIFS(Gastos!$H$7:$H$2006,Gastos!$B$7:$B$2006,">="&D$6,Gastos!$B$7:$B$2006,"<"&EDATE(D$6,1),Gastos!$C$7:$C$2006,"Gasto",Gastos!$D$7:$D$2006,"Otros") -> 0 | E25: =SUMIFS(Gastos!$H$7:$H$2006,Gastos!$B$7:$B$2006,">="&E$6,Gastos!$B$7:$B$2006,"<"&EDATE(E$6,1),Gastos!$C$7:$C$2006,"Gasto",Gastos!$D$7:$D$2006,"Otros") -> 0 | F25: =SUMIFS(Gastos!$H$7:$H$2006,Gastos!$B$7:$B$2006,">="&F$6,Gastos!$B$7:$B$2006,"<"&EDATE(F$6,1),Gastos!$C$7:$C$2006,"Gasto",Gastos!$D$7:$D$2006,"Otros") -> 0 | G25: =SUMIFS(Gastos!$H$7:$H$2006,Gastos!$B$7:$B$2006,">="&G$6,Gastos!$B$7:$B$2006,"<"&EDATE(G$6,1),Gastos!$C$7:$C$2006,"Gasto",Gastos!$D$7:$D$2006,"Otros") -> 0 | H25: =SUMIFS(Gastos!$H$7:$H$2006,Gastos!$B$7:$B$2006,">="&H$6,Gastos!$B$7:$B$2006,"<"&EDATE(H$6,1),Gastos!$C$7:$C$2006,"Gasto",Gastos!$D$7:$D$2006,"Otros") -> 0 | I25: =SUMIFS(Gastos!$H$7:$H$2006,Gastos!$B$7:$B$2006,">="&I$6,Gastos!$B$7:$B$2006,"<"&EDATE(I$6,1),Gastos!$C$7:$C$2006,"Gasto",Gastos!$D$7:$D$2006,"Otros") -> 0 | J25: =SUMIFS(Gastos!$H$7:$H$2006,Gastos!$B$7:$B$2006,">="&J$6,Gastos!$B$7:$B$2006,"<"&EDATE(J$6,1),Gastos!$C$7:$C$2006,"Gasto",Gastos!$D$7:$D$2006,"Otros") -> 0 | ... N25: =SUMIFS(Gastos!$H$7:$H$2006,Gastos!$B$7:$B$2006,">="&N$6,Gastos!$B$7:$B$2006,"<"&EDATE(N$6,1),Gastos!$C$7:$C$2006,"Gasto",Gastos!$D$7:$D$2006,"Otros") -> 0 | O25: =SUM(C25:N25) -> 0
B26: Gastos operativos | C26: =SUM(C19:C25) -> 0 | D26: =SUM(D19:D25) -> 0 | E26: =SUM(E19:E25) -> 0 | F26: =SUM(F19:F25) -> 0 | G26: =SUM(G19:G25) -> 0 | H26: =SUM(H19:H25) -> 0 | I26: =SUM(I19:I25) -> 0 | J26: =SUM(J19:J25) -> 0 | ... N26: =SUM(N19:N25) -> 0 | O26: =SUM(C26:N26) -> 0
B27: Resultado antes de depreciación | C27: =C17-C26 -> 2200 | D27: =D17-D26 -> 0 | E27: =E17-E26 -> 0 | F27: =F17-F26 -> 0 | G27: =G17-G26 -> 0 | H27: =H17-H26 -> 0 | I27: =I17-I26 -> 0 | J27: =J17-J26 -> 0 | ... N27: =N17-N26 -> 0 | O27: =SUM(C27:N27) -> 2200
B28: Depreciación contable | C28: =SUM(Activos!M7:M106) -> 0 | D28: =SUM(Activos!N7:N106) -> 0 | E28: =SUM(Activos!O7:O106) -> 0 | F28: =SUM(Activos!P7:P106) -> 0 | G28: =SUM(Activos!Q7:Q106) -> 0 | H28: =SUM(Activos!R7:R106) -> 0 | I28: =SUM(Activos!S7:S106) -> 0 | J28: =SUM(Activos!T7:T106) -> 0 | ... N28: =SUM(Activos!X7:X106) -> 0 | O28: =SUM(C28:N28) -> 0
B29: Utilidad operativa | C29: =C27-C28 -> 2200 | D29: =D27-D28 -> 0 | E29: =E27-E28 -> 0 | F29: =F27-F28 -> 0 | G29: =G27-G28 -> 0 | H29: =H27-H28 -> 0 | I29: =I27-I28 -> 0 | J29: =J27-J28 -> 0 | ... N29: =N27-N28 -> 0 | O29: =SUM(C29:N29) -> 2200
B30: Intereses | C30: =SUMIFS(Gastos!$H$7:$H$2006,Gastos!$B$7:$B$2006,">="&C$6,Gastos!$B$7:$B$2006,"<"&EDATE(C$6,1),Gastos!$C$7:$C$2006,"Gasto",Gastos!$D$7:$D$2006,"Intereses") -> 0 | D30: =SUMIFS(Gastos!$H$7:$H$2006,Gastos!$B$7:$B$2006,">="&D$6,Gastos!$B$7:$B$2006,"<"&EDATE(D$6,1),Gastos!$C$7:$C$2006,"Gasto",Gastos!$D$7:$D$2006,"Intereses") -> 0 | E30: =SUMIFS(Gastos!$H$7:$H$2006,Gastos!$B$7:$B$2006,">="&E$6,Gastos!$B$7:$B$2006,"<"&EDATE(E$6,1),Gastos!$C$7:$C$2006,"Gasto",Gastos!$D$7:$D$2006,"Intereses") -> 0 | F30: =SUMIFS(Gastos!$H$7:$H$2006,Gastos!$B$7:$B$2006,">="&F$6,Gastos!$B$7:$B$2006,"<"&EDATE(F$6,1),Gastos!$C$7:$C$2006,"Gasto",Gastos!$D$7:$D$2006,"Intereses") -> 0 | G30: =SUMIFS(Gastos!$H$7:$H$2006,Gastos!$B$7:$B$2006,">="&G$6,Gastos!$B$7:$B$2006,"<"&EDATE(G$6,1),Gastos!$C$7:$C$2006,"Gasto",Gastos!$D$7:$D$2006,"Intereses") -> 0 | H30: =SUMIFS(Gastos!$H$7:$H$2006,Gastos!$B$7:$B$2006,">="&H$6,Gastos!$B$7:$B$2006,"<"&EDATE(H$6,1),Gastos!$C$7:$C$2006,"Gasto",Gastos!$D$7:$D$2006,"Intereses") -> 0 | I30: =SUMIFS(Gastos!$H$7:$H$2006,Gastos!$B$7:$B$2006,">="&I$6,Gastos!$B$7:$B$2006,"<"&EDATE(I$6,1),Gastos!$C$7:$C$2006,"Gasto",Gastos!$D$7:$D$2006,"Intereses") -> 0 | J30: =SUMIFS(Gastos!$H$7:$H$2006,Gastos!$B$7:$B$2006,">="&J$6,Gastos!$B$7:$B$2006,"<"&EDATE(J$6,1),Gastos!$C$7:$C$2006,"Gasto",Gastos!$D$7:$D$2006,"Intereses") -> 0 | ... N30: =SUMIFS(Gastos!$H$7:$H$2006,Gastos!$B$7:$B$2006,">="&N$6,Gastos!$B$7:$B$2006,"<"&EDATE(N$6,1),Gastos!$C$7:$C$2006,"Gasto",Gastos!$D$7:$D$2006,"Intereses") -> 0 | O30: =SUM(C30:N30) -> 0
B31: Utilidad antes de ISR | C31: =C29-C30 -> 2200 | D31: =D29-D30 -> 0 | E31: =E29-E30 -> 0 | F31: =F29-F30 -> 0 | G31: =G29-G30 -> 0 | H31: =H29-H30 -> 0 | I31: =I29-I30 -> 0 | J31: =J29-J30 -> 0 | ... N31: =N29-N30 -> 0 | O31: =SUM(C31:N31) -> 2200
B32: ISR devengado (capturado) | C32: =SUMIFS(Gastos!$H$7:$H$2006,Gastos!$B$7:$B$2006,">="&C$6,Gastos!$B$7:$B$2006,"<"&EDATE(C$6,1),Gastos!$C$7:$C$2006,"ISR devengado") -> 0 | D32: =SUMIFS(Gastos!$H$7:$H$2006,Gastos!$B$7:$B$2006,">="&D$6,Gastos!$B$7:$B$2006,"<"&EDATE(D$6,1),Gastos!$C$7:$C$2006,"ISR devengado") -> 0 | E32: =SUMIFS(Gastos!$H$7:$H$2006,Gastos!$B$7:$B$2006,">="&E$6,Gastos!$B$7:$B$2006,"<"&EDATE(E$6,1),Gastos!$C$7:$C$2006,"ISR devengado") -> 0 | F32: =SUMIFS(Gastos!$H$7:$H$2006,Gastos!$B$7:$B$2006,">="&F$6,Gastos!$B$7:$B$2006,"<"&EDATE(F$6,1),Gastos!$C$7:$C$2006,"ISR devengado") -> 0 | G32: =SUMIFS(Gastos!$H$7:$H$2006,Gastos!$B$7:$B$2006,">="&G$6,Gastos!$B$7:$B$2006,"<"&EDATE(G$6,1),Gastos!$C$7:$C$2006,"ISR devengado") -> 0 | H32: =SUMIFS(Gastos!$H$7:$H$2006,Gastos!$B$7:$B$2006,">="&H$6,Gastos!$B$7:$B$2006,"<"&EDATE(H$6,1),Gastos!$C$7:$C$2006,"ISR devengado") -> 0 | I32: =SUMIFS(Gastos!$H$7:$H$2006,Gastos!$B$7:$B$2006,">="&I$6,Gastos!$B$7:$B$2006,"<"&EDATE(I$6,1),Gastos!$C$7:$C$2006,"ISR devengado") -> 0 | J32: =SUMIFS(Gastos!$H$7:$H$2006,Gastos!$B$7:$B$2006,">="&J$6,Gastos!$B$7:$B$2006,"<"&EDATE(J$6,1),Gastos!$C$7:$C$2006,"ISR devengado") -> 0 | ... N32: =SUMIFS(Gastos!$H$7:$H$2006,Gastos!$B$7:$B$2006,">="&N$6,Gastos!$B$7:$B$2006,"<"&EDATE(N$6,1),Gastos!$C$7:$C$2006,"ISR devengado") -> 0 | O32: =SUM(C32:N32) -> 0
B33: Utilidad neta | C33: =C31-C32 -> 2200 | D33: =D31-D32 -> 0 | E33: =E31-E32 -> 0 | F33: =F31-F32 -> 0 | G33: =G31-G32 -> 0 | H33: =H31-H32 -> 0 | I33: =I31-I32 -> 0 | J33: =J31-J32 -> 0 | ... N33: =N31-N32 -> 0 | O33: =SUM(C33:N33) -> 2200
B35: Retiros familiares (fuera de gastos) | C35: ='Flujo de Efectivo'!C20 -> 0 | D35: ='Flujo de Efectivo'!D20 -> 0 | E35: ='Flujo de Efectivo'!E20 -> 0 | F35: ='Flujo de Efectivo'!F20 -> 0 | G35: ='Flujo de Efectivo'!G20 -> 0 | H35: ='Flujo de Efectivo'!H20 -> 0 | I35: ='Flujo de Efectivo'!I20 -> 0 | J35: ='Flujo de Efectivo'!J20 -> 0 | ... N35: ='Flujo de Efectivo'!N20 -> 0 | O35: =SUM(C35:N35) -> 0
B36: Utilidad menos retiros* | C36: =C33-C35 -> 2200 | D36: =D33-D35 -> 0 | E36: =E33-E35 -> 0 | F36: =F33-F35 -> 0 | G36: =G33-G35 -> 0 | H36: =H33-H35 -> 0 | I36: =I33-I35 -> 0 | J36: =J33-J35 -> 0 | ... N36: =N33-N35 -> 0 | O36: =SUM(C36:N36) -> 2200
B38: *No equivale al efectivo disponible.

Sheet Balance General
B2: Balance General
B4: MXN · enero a diciembre
B6: Concepto | C6: =DATE(Configuración!$C$5,1,1) -> 46023 | D6: =DATE(Configuración!$C$5,2,1) -> 46054 | E6: =DATE(Configuración!$C$5,3,1) -> 46082 | F6: =DATE(Configuración!$C$5,4,1) -> 46113 | G6: =DATE(Configuración!$C$5,5,1) -> 46143 | H6: =DATE(Configuración!$C$5,6,1) -> 46174 | I6: =DATE(Configuración!$C$5,7,1) -> 46204 | J6: =DATE(Configuración!$C$5,8,1) -> 46235 | K6: =DATE(Configuración!$C$5,9,1) -> 46266 | L6: =DATE(Configuración!$C$5,10,1) -> 46296 | M6: =DATE(Configuración!$C$5,11,1) -> 46327 | N6: =DATE(Configuración!$C$5,12,1) -> 46357 | O6: Cierre anual
B7: Efectivo y bancos | C7: ='Flujo de Efectivo'!C25 -> 2200 | D7: ='Flujo de Efectivo'!D25 -> 2200 | E7: ='Flujo de Efectivo'!E25 -> 2200 | F7: ='Flujo de Efectivo'!F25 -> 2200 | G7: ='Flujo de Efectivo'!G25 -> 2200 | H7: ='Flujo de Efectivo'!H25 -> 2200 | I7: ='Flujo de Efectivo'!I25 -> 2200 | J7: ='Flujo de Efectivo'!J25 -> 2200 | ... N7: ='Flujo de Efectivo'!N25 -> 2200 | O7: =N7 -> 2200
B8: Cuentas por cobrar | C8: =Configuración!$C$10+SUMIFS(Ingresos!$K$7:$K$2006,Ingresos!$B$7:$B$2006,">="&C$6,Ingresos!$B$7:$B$2006,"<"&EDATE(C$6,1),Ingresos!$C$7:$C$2006,"Servicio")-'Flujo de Efectivo'!C7-C41-C42-C43 -> 0 | D8: =C8+SUMIFS(Ingresos!$K$7:$K$2006,Ingresos!$B$7:$B$2006,">="&D$6,Ingresos!$B$7:$B$2006,"<"&EDATE(D$6,1),Ingresos!$C$7:$C$2006,"Servicio")-'Flujo de Efectivo'!D7-D41-D42-D43 -> 0 | E8: =D8+SUMIFS(Ingresos!$K$7:$K$2006,Ingresos!$B$7:$B$2006,">="&E$6,Ingresos!$B$7:$B$2006,"<"&EDATE(E$6,1),Ingresos!$C$7:$C$2006,"Servicio")-'Flujo de Efectivo'!E7-E41-E42-E43 -> 0 | F8: =E8+SUMIFS(Ingresos!$K$7:$K$2006,Ingresos!$B$7:$B$2006,">="&F$6,Ingresos!$B$7:$B$2006,"<"&EDATE(F$6,1),Ingresos!$C$7:$C$2006,"Servicio")-'Flujo de Efectivo'!F7-F41-F42-F43 -> 0 | G8: =F8+SUMIFS(Ingresos!$K$7:$K$2006,Ingresos!$B$7:$B$2006,">="&G$6,Ingresos!$B$7:$B$2006,"<"&EDATE(G$6,1),Ingresos!$C$7:$C$2006,"Servicio")-'Flujo de Efectivo'!G7-G41-G42-G43 -> 0 | H8: =G8+SUMIFS(Ingresos!$K$7:$K$2006,Ingresos!$B$7:$B$2006,">="&H$6,Ingresos!$B$7:$B$2006,"<"&EDATE(H$6,1),Ingresos!$C$7:$C$2006,"Servicio")-'Flujo de Efectivo'!H7-H41-H42-H43 -> 0 | I8: =H8+SUMIFS(Ingresos!$K$7:$K$2006,Ingresos!$B$7:$B$2006,">="&I$6,Ingresos!$B$7:$B$2006,"<"&EDATE(I$6,1),Ingresos!$C$7:$C$2006,"Servicio")-'Flujo de Efectivo'!I7-I41-I42-I43 -> 0 | J8: =I8+SUMIFS(Ingresos!$K$7:$K$2006,Ingresos!$B$7:$B$2006,">="&J$6,Ingresos!$B$7:$B$2006,"<"&EDATE(J$6,1),Ingresos!$C$7:$C$2006,"Servicio")-'Flujo de Efectivo'!J7-J41-J42-J43 -> 0 | K8: =J8+SUMIFS(Ingresos!$K$7:$K$2006,Ingresos!$B$7:$B$2006,">="&K$6,Ingresos!$B$7:$B$2006,"<"&EDATE(K$6,1),Ingresos!$C$7:$C$2006,"Servicio")-'Flujo de Efectivo'!K7-K41-K42-K43 -> 0 | ... N8: =M8+SUMIFS(Ingresos!$K$7:$K$2006,Ingresos!$B$7:$B$2006,">="&N$6,Ingresos!$B$7:$B$2006,"<"&EDATE(N$6,1),Ingresos!$C$7:$C$2006,"Servicio")-'Flujo de Efectivo'!N7-N41-N42-N43 -> 0 | O8: =N8 -> 0
B9: IVA neto a favor | C9: =MAX(0,-C38) -> 0 | D9: =MAX(0,-D38) -> 0 | E9: =MAX(0,-E38) -> 0 | F9: =MAX(0,-F38) -> 0 | G9: =MAX(0,-G38) -> 0 | H9: =MAX(0,-H38) -> 0 | I9: =MAX(0,-I38) -> 0 | J9: =MAX(0,-J38) -> 0 | ... N9: =MAX(0,-N38) -> 0 | O9: =N9 -> 0
B10: Retenciones ISR a favor | C10: =Configuración!$C$12+C42-C44 -> 0 | D10: =C10+D42-D44 -> 0 | E10: =D10+E42-E44 -> 0 | F10: =E10+F42-F44 -> 0 | G10: =F10+G42-G44 -> 0 | H10: =G10+H42-H44 -> 0 | I10: =H10+I42-I44 -> 0 | J10: =I10+J42-J44 -> 0 | K10: =J10+K42-K44 -> 0 | ... N10: =M10+N42-N44 -> 0 | O10: =N10 -> 0
B11: Retenciones IVA a favor | C11: =Configuración!$C$13+C43-C45 -> 0 | D11: =C11+D43-D45 -> 0 | E11: =D11+E43-E45 -> 0 | F11: =E11+F43-F45 -> 0 | G11: =F11+G43-G45 -> 0 | H11: =G11+H43-H45 -> 0 | I11: =H11+I43-I45 -> 0 | J11: =I11+J43-J45 -> 0 | K11: =J11+K43-K45 -> 0 | ... N11: =M11+N43-N45 -> 0 | O11: =N11 -> 0
B12: Activo circulante | C12: =SUM(C7:C11) -> 2200 | D12: =SUM(D7:D11) -> 2200 | E12: =SUM(E7:E11) -> 2200 | F12: =SUM(F7:F11) -> 2200 | G12: =SUM(G7:G11) -> 2200 | H12: =SUM(H7:H11) -> 2200 | I12: =SUM(I7:I11) -> 2200 | J12: =SUM(J7:J11) -> 2200 | ... N12: =SUM(N7:N11) -> 2200 | O12: =N12 -> 2200
B14: Activos fijos a costo | C14: =SUMIFS(Activos!$E$7:$E$106,Activos!$C$7:$C$106,"<"&DATE(Configuración!$C$5,1,1),Activos!$C$7:$C$106,">0")+C39 -> 0 | D14: =C14+D39 -> 0 | E14: =D14+E39 -> 0 | F14: =E14+F39 -> 0 | G14: =F14+G39 -> 0 | H14: =G14+H39 -> 0 | I14: =H14+I39 -> 0 | J14: =I14+J39 -> 0 | K14: =J14+K39 -> 0 | ... N14: =M14+N39 -> 0 | O14: =N14 -> 0
B15: Depreciación acumulada | C15: =SUMIFS(Activos!$I$7:$I$106,Activos!$C$7:$C$106,"<"&DATE(Configuración!$C$5,1,1),Activos!$C$7:$C$106,">0")+'Estado de Resultados'!C28 -> 0 | D15: =C15+'Estado de Resultados'!D28 -> 0 | E15: =D15+'Estado de Resultados'!E28 -> 0 | F15: =E15+'Estado de Resultados'!F28 -> 0 | G15: =F15+'Estado de Resultados'!G28 -> 0 | H15: =G15+'Estado de Resultados'!H28 -> 0 | I15: =H15+'Estado de Resultados'!I28 -> 0 | J15: =I15+'Estado de Resultados'!J28 -> 0 | K15: =J15+'Estado de Resultados'!K28 -> 0 | ... N15: =M15+'Estado de Resultados'!N28 -> 0 | O15: =N15 -> 0
B16: Activos fijos netos | C16: =C14-C15 -> 0 | D16: =D14-D15 -> 0 | E16: =E14-E15 -> 0 | F16: =F14-F15 -> 0 | G16: =G14-G15 -> 0 | H16: =H14-H15 -> 0 | I16: =I14-I15 -> 0 | J16: =J14-J15 -> 0 | ... N16: =N14-N15 -> 0 | O16: =N16 -> 0
B17: Total activo | C17: =C12+C16 -> 2200 | D17: =D12+D16 -> 2200 | E17: =E12+E16 -> 2200 | F17: =F12+F16 -> 2200 | G17: =G12+G16 -> 2200 | H17: =H12+H16 -> 2200 | I17: =I12+I16 -> 2200 | J17: =J12+J16 -> 2200 | ... N17: =N12+N16 -> 2200 | O17: =N17 -> 2200
B19: Proveedores y otras cuentas por pagar | C19: =Configuración!$C$14+SUMIFS(Gastos!$K$7:$K$2006,Gastos!$B$7:$B$2006,">="&C$6,Gastos!$B$7:$B$2006,"<"&EDATE(C$6,1),Gastos!$C$7:$C$2006,"Gasto")+C39+C40-'Flujo de Efectivo'!C9-'Flujo de Efectivo'!C14 -> 0 | D19: =C19+SUMIFS(Gastos!$K$7:$K$2006,Gastos!$B$7:$B$2006,">="&D$6,Gastos!$B$7:$B$2006,"<"&EDATE(D$6,1),Gastos!$C$7:$C$2006,"Gasto")+D39+D40-'Flujo de Efectivo'!D9-'Flujo de Efectivo'!D14 -> 0 | E19: =D19+SUMIFS(Gastos!$K$7:$K$2006,Gastos!$B$7:$B$2006,">="&E$6,Gastos!$B$7:$B$2006,"<"&EDATE(E$6,1),Gastos!$C$7:$C$2006,"Gasto")+E39+E40-'Flujo de Efectivo'!E9-'Flujo de Efectivo'!E14 -> 0 | F19: =E19+SUMIFS(Gastos!$K$7:$K$2006,Gastos!$B$7:$B$2006,">="&F$6,Gastos!$B$7:$B$2006,"<"&EDATE(F$6,1),Gastos!$C$7:$C$2006,"Gasto")+F39+F40-'Flujo de Efectivo'!F9-'Flujo de Efectivo'!F14 -> 0 | G19: =F19+SUMIFS(Gastos!$K$7:$K$2006,Gastos!$B$7:$B$2006,">="&G$6,Gastos!$B$7:$B$2006,"<"&EDATE(G$6,1),Gastos!$C$7:$C$2006,"Gasto")+G39+G40-'Flujo de Efectivo'!G9-'Flujo de Efectivo'!G14 -> 0 | H19: =G19+SUMIFS(Gastos!$K$7:$K$2006,Gastos!$B$7:$B$2006,">="&H$6,Gastos!$B$7:$B$2006,"<"&EDATE(H$6,1),Gastos!$C$7:$C$2006,"Gasto")+H39+H40-'Flujo de Efectivo'!H9-'Flujo de Efectivo'!H14 -> 0 | I19: =H19+SUMIFS(Gastos!$K$7:$K$2006,Gastos!$B$7:$B$2006,">="&I$6,Gastos!$B$7:$B$2006,"<"&EDATE(I$6,1),Gastos!$C$7:$C$2006,"Gasto")+I39+I40-'Flujo de Efectivo'!I9-'Flujo de Efectivo'!I14 -> 0 | J19: =I19+SUMIFS(Gastos!$K$7:$K$2006,Gastos!$B$7:$B$2006,">="&J$6,Gastos!$B$7:$B$2006,"<"&EDATE(J$6,1),Gastos!$C$7:$C$2006,"Gasto")+J39+J40-'Flujo de Efectivo'!J9-'Flujo de Efectivo'!J14 -> 0 | K19: =J19+SUMIFS(Gastos!$K$7:$K$2006,Gastos!$B$7:$B$2006,">="&K$6,Gastos!$B$7:$B$2006,"<"&EDATE(K$6,1),Gastos!$C$7:$C$2006,"Gasto")+K39+K40-'Flujo de Efectivo'!K9-'Flujo de Efectivo'!K14 -> 0 | ... N19: =M19+SUMIFS(Gastos!$K$7:$K$2006,Gastos!$B$7:$B$2006,">="&N$6,Gastos!$B$7:$B$2006,"<"&EDATE(N$6,1),Gastos!$C$7:$C$2006,"Gasto")+N39+N40-'Flujo de Efectivo'!N9-'Flujo de Efectivo'!N14 -> 0 | O19: =N19 -> 0
B20: Anticipos de pacientes | C20: =Configuración!$C$15+'Flujo de Efectivo'!C8-C41 -> 0 | D20: =C20+'Flujo de Efectivo'!D8-D41 -> 0 | E20: =D20+'Flujo de Efectivo'!E8-E41 -> 0 | F20: =E20+'Flujo de Efectivo'!F8-F41 -> 0 | G20: =F20+'Flujo de Efectivo'!G8-G41 -> 0 | H20: =G20+'Flujo de Efectivo'!H8-H41 -> 0 | I20: =H20+'Flujo de Efectivo'!I8-I41 -> 0 | J20: =I20+'Flujo de Efectivo'!J8-J41 -> 0 | K20: =J20+'Flujo de Efectivo'!K8-K41 -> 0 | ... N20: =M20+'Flujo de Efectivo'!N8-N41 -> 0 | O20: =N20 -> 0
B21: IVA neto por pagar | C21: =MAX(0,C38) -> 0 | D21: =MAX(0,D38) -> 0 | E21: =MAX(0,E38) -> 0 | F21: =MAX(0,F38) -> 0 | G21: =MAX(0,G38) -> 0 | H21: =MAX(0,H38) -> 0 | I21: =MAX(0,I38) -> 0 | J21: =MAX(0,J38) -> 0 | ... N21: =MAX(0,N38) -> 0 | O21: =N21 -> 0
B22: ISR por pagar | C22: =Configuración!$C$17+'Estado de Resultados'!C32-'Flujo de Efectivo'!C10-C44 -> 0 | D22: =C22+'Estado de Resultados'!D32-'Flujo de Efectivo'!D10-D44 -> 0 | E22: =D22+'Estado de Resultados'!E32-'Flujo de Efectivo'!E10-E44 -> 0 | F22: =E22+'Estado de Resultados'!F32-'Flujo de Efectivo'!F10-F44 -> 0 | G22: =F22+'Estado de Resultados'!G32-'Flujo de Efectivo'!G10-G44 -> 0 | H22: =G22+'Estado de Resultados'!H32-'Flujo de Efectivo'!H10-H44 -> 0 | I22: =H22+'Estado de Resultados'!I32-'Flujo de Efectivo'!I10-I44 -> 0 | J22: =I22+'Estado de Resultados'!J32-'Flujo de Efectivo'!J10-J44 -> 0 | K22: =J22+'Estado de Resultados'!K32-'Flujo de Efectivo'!K10-K44 -> 0 | ... N22: =M22+'Estado de Resultados'!N32-'Flujo de Efectivo'!N10-N44 -> 0 | O22: =N22 -> 0
B23: Préstamos a corto plazo | C23: =SUMIFS(Pasivos!$G$7:$G$506,Pasivos!$C$7:$C$506,"Saldo inicial",Pasivos!$F$7:$F$506,"Corto plazo",Pasivos!$B$7:$B$506,DATE(Configuración!$C$5,1,1)-1)+SUMIFS(Pasivos!$G$7:$G$506,Pasivos!$B$7:$B$506,">="&C$6,Pasivos!$B$7:$B$506,"<"&EDATE(C$6,1),Pasivos!$C$7:$C$506,"Desembolso",Pasivos!$F$7:$F$506,"Corto plazo")-SUMIFS(Pasivos!$G$7:$G$506,Pasivos!$B$7:$B$506,">="&C$6,Pasivos!$B$7:$B$506,"<"&EDATE(C$6,1),Pasivos!$C$7:$C$506,"Amortización",Pasivos!$F$7:$F$506,"Corto plazo")+1*(SUMIFS(Pasivos!$G$7:$G$506,Pasivos!$B$7:$B$506,">="&C$6,Pasivos!$B$7:$B$506,"<"&EDATE(C$6,1),Pasivos!$C$7:$C$506,"Reclasificar a CP")-SUMIFS(Pasivos!$G$7:$G$506,Pasivos!$B$7:$B$506,">="&C$6,Pasivos!$B$7:$B$506,"<"&EDATE(C$6,1),Pasivos!$C$7:$C$506,"Reclasificar a LP")) -> 0 | D23: =C23+SUMIFS(Pasivos!$G$7:$G$506,Pasivos!$B$7:$B$506,">="&D$6,Pasivos!$B$7:$B$506,"<"&EDATE(D$6,1),Pasivos!$C$7:$C$506,"Desembolso",Pasivos!$F$7:$F$506,"Corto plazo")-SUMIFS(Pasivos!$G$7:$G$506,Pasivos!$B$7:$B$506,">="&D$6,Pasivos!$B$7:$B$506,"<"&EDATE(D$6,1),Pasivos!$C$7:$C$506,"Amortización",Pasivos!$F$7:$F$506,"Corto plazo")+1*(SUMIFS(Pasivos!$G$7:$G$506,Pasivos!$B$7:$B$506,">="&D$6,Pasivos!$B$7:$B$506,"<"&EDATE(D$6,1),Pasivos!$C$7:$C$506,"Reclasificar a CP")-SUMIFS(Pasivos!$G$7:$G$506,Pasivos!$B$7:$B$506,">="&D$6,Pasivos!$B$7:$B$506,"<"&EDATE(D$6,1),Pasivos!$C$7:$C$506,"Reclasificar a LP")) -> 0 | E23: =D23+SUMIFS(Pasivos!$G$7:$G$506,Pasivos!$B$7:$B$506,">="&E$6,Pasivos!$B$7:$B$506,"<"&EDATE(E$6,1),Pasivos!$C$7:$C$506,"Desembolso",Pasivos!$F$7:$F$506,"Corto plazo")-SUMIFS(Pasivos!$G$7:$G$506,Pasivos!$B$7:$B$506,">="&E$6,Pasivos!$B$7:$B$506,"<"&EDATE(E$6,1),Pasivos!$C$7:$C$506,"Amortización",Pasivos!$F$7:$F$506,"Corto plazo")+1*(SUMIFS(Pasivos!$G$7:$G$506,Pasivos!$B$7:$B$506,">="&E$6,Pasivos!$B$7:$B$506,"<"&EDATE(E$6,1),Pasivos!$C$7:$C$506,"Reclasificar a CP")-SUMIFS(Pasivos!$G$7:$G$506,Pasivos!$B$7:$B$506,">="&E$6,Pasivos!$B$7:$B$506,"<"&EDATE(E$6,1),Pasivos!$C$7:$C$506,"Reclasificar a LP")) -> 0 | F23: =E23+SUMIFS(Pasivos!$G$7:$G$506,Pasivos!$B$7:$B$506,">="&F$6,Pasivos!$B$7:$B$506,"<"&EDATE(F$6,1),Pasivos!$C$7:$C$506,"Desembolso",Pasivos!$F$7:$F$506,"Corto plazo")-SUMIFS(Pasivos!$G$7:$G$506,Pasivos!$B$7:$B$506,">="&F$6,Pasivos!$B$7:$B$506,"<"&EDATE(F$6,1),Pasivos!$C$7:$C$506,"Amortización",Pasivos!$F$7:$F$506,"Corto plazo")+1*(SUMIFS(Pasivos!$G$7:$G$506,Pasivos!$B$7:$B$506,">="&F$6,Pasivos!$B$7:$B$506,"<"&EDATE(F$6,1),Pasivos!$C$7:$C$506,"Reclasificar a CP")-SUMIFS(Pasivos!$G$7:$G$506,Pasivos!$B$7:$B$506,">="&F$6,Pasivos!$B$7:$B$506,"<"&EDATE(F$6,1),Pasivos!$C$7:$C$506,"Reclasificar a LP")) -> 0 | G23: =F23+SUMIFS(Pasivos!$G$7:$G$506,Pasivos!$B$7:$B$506,">="&G$6,Pasivos!$B$7:$B$506,"<"&EDATE(G$6,1),Pasivos!$C$7:$C$506,"Desembolso",Pasivos!$F$7:$F$506,"Corto plazo")-SUMIFS(Pasivos!$G$7:$G$506,Pasivos!$B$7:$B$506,">="&G$6,Pasivos!$B$7:$B$506,"<"&EDATE(G$6,1),Pasivos!$C$7:$C$506,"Amortización",Pasivos!$F$7:$F$506,"Corto plazo")+1*(SUMIFS(Pasivos!$G$7:$G$506,Pasivos!$B$7:$B$506,">="&G$6,Pasivos!$B$7:$B$506,"<"&EDATE(G$6,1),Pasivos!$C$7:$C$506,"Reclasificar a CP")-SUMIFS(Pasivos!$G$7:$G$506,Pasivos!$B$7:$B$506,">="&G$6,Pasivos!$B$7:$B$506,"<"&EDATE(G$6,1),Pasivos!$C$7:$C$506,"Reclasificar a LP")) -> 0 | H23: =G23+SUMIFS(Pasivos!$G$7:$G$506,Pasivos!$B$7:$B$506,">="&H$6,Pasivos!$B$7:$B$506,"<"&EDATE(H$6,1),Pasivos!$C$7:$C$506,"Desembolso",Pasivos!$F$7:$F$506,"Corto plazo")-SUMIFS(Pasivos!$G$7:$G$506,Pasivos!$B$7:$B$506,">="&H$6,Pasivos!$B$7:$B$506,"<"&EDATE(H$6,1),Pasivos!$C$7:$C$506,"Amortización",Pasivos!$F$7:$F$506,"Corto plazo")+1*(SUMIFS(Pasivos!$G$7:$G$506,Pasivos!$B$7:$B$506,">="&H$6,Pasivos!$B$7:$B$506,"<"&EDATE(H$6,1),Pasivos!$C$7:$C$506,"Reclasificar a CP")-SUMIFS(Pasivos!$G$7:$G$506,Pasivos!$B$7:$B$506,">="&H$6,Pasivos!$B$7:$B$506,"<"&EDATE(H$6,1),Pasivos!$C$7:$C$506,"Reclasificar a LP")) -> 0 | I23: =H23+SUMIFS(Pasivos!$G$7:$G$506,Pasivos!$B$7:$B$506,">="&I$6,Pasivos!$B$7:$B$506,"<"&EDATE(I$6,1),Pasivos!$C$7:$C$506,"Desembolso",Pasivos!$F$7:$F$506,"Corto plazo")-SUMIFS(Pasivos!$G$7:$G$506,Pasivos!$B$7:$B$506,">="&I$6,Pasivos!$B$7:$B$506,"<"&EDATE(I$6,1),Pasivos!$C$7:$C$506,"Amortización",Pasivos!$F$7:$F$506,"Corto plazo")+1*(SUMIFS(Pasivos!$G$7:$G$506,Pasivos!$B$7:$B$506,">="&I$6,Pasivos!$B$7:$B$506,"<"&EDATE(I$6,1),Pasivos!$C$7:$C$506,"Reclasificar a CP")-SUMIFS(Pasivos!$G$7:$G$506,Pasivos!$B$7:$B$506,">="&I$6,Pasivos!$B$7:$B$506,"<"&EDATE(I$6,1),Pasivos!$C$7:$C$506,"Reclasificar a LP")) -> 0 | J23: =I23+SUMIFS(Pasivos!$G$7:$G$506,Pasivos!$B$7:$B$506,">="&J$6,Pasivos!$B$7:$B$506,"<"&EDATE(J$6,1),Pasivos!$C$7:$C$506,"Desembolso",Pasivos!$F$7:$F$506,"Corto plazo")-SUMIFS(Pasivos!$G$7:$G$506,Pasivos!$B$7:$B$506,">="&J$6,Pasivos!$B$7:$B$506,"<"&EDATE(J$6,1),Pasivos!$C$7:$C$506,"Amortización",Pasivos!$F$7:$F$506,"Corto plazo")+1*(SUMIFS(Pasivos!$G$7:$G$506,Pasivos!$B$7:$B$506,">="&J$6,Pasivos!$B$7:$B$506,"<"&EDATE(J$6,1),Pasivos!$C$7:$C$506,"Reclasificar a CP")-SUMIFS(Pasivos!$G$7:$G$506,Pasivos!$B$7:$B$506,">="&J$6,Pasivos!$B$7:$B$506,"<"&EDATE(J$6,1),Pasivos!$C$7:$C$506,"Reclasificar a LP")) -> 0 | K23: =J23+SUMIFS(Pasivos!$G$7:$G$506,Pasivos!$B$7:$B$506,">="&K$6,Pasivos!$B$7:$B$506,"<"&EDATE(K$6,1),Pasivos!$C$7:$C$506,"Desembolso",Pasivos!$F$7:$F$506,"Corto plazo")-SUMIFS(Pasivos!$G$7:$G$506,Pasivos!$B$7:$B$506,">="&K$6,Pasivos!$B$7:$B$506,"<"&EDATE(K$6,1),Pasivos!$C$7:$C$506,"Amortización",Pasivos!$F$7:$F$506,"Corto plazo")+1*(SUMIFS(Pasivos!$G$7:$G$506,Pasivos!$B$7:$B$506,">="&K$6,Pasivos!$B$7:$B$506,"<"&EDATE(K$6,1),Pasivos!$C$7:$C$506,"Reclasificar a CP")-SUMIFS(Pasivos!$G$7:$G$506,Pasivos!$B$7:$B$506,">="&K$6,Pasivos!$B$7:$B$506,"<"&EDATE(K$6,1),Pasivos!$C$7:$C$506,"Reclasificar a LP")) -> 0 | ... N23: =M23+SUMIFS(Pasivos!$G$7:$G$506,Pasivos!$B$7:$B$506,">="&N$6,Pasivos!$B$7:$B$506,"<"&EDATE(N$6,1),Pasivos!$C$7:$C$506,"Desembolso",Pasivos!$F$7:$F$506,"Corto plazo")-SUMIFS(Pasivos!$G$7:$G$506,Pasivos!$B$7:$B$506,">="&N$6,Pasivos!$B$7:$B$506,"<"&EDATE(N$6,1),Pasivos!$C$7:$C$506,"Amortización",Pasivos!$F$7:$F$506,"Corto plazo")+1*(SUMIFS(Pasivos!$G$7:$G$506,Pasivos!$B$7:$B$506,">="&N$6,Pasivos!$B$7:$B$506,"<"&EDATE(N$6,1),Pasivos!$C$7:$C$506,"Reclasificar a CP")-SUMIFS(Pasivos!$G$7:$G$506,Pasivos!$B$7:$B$506,">="&N$6,Pasivos!$B$7:$B$506,"<"&EDATE(N$6,1),Pasivos!$C$7:$C$506,"Reclasificar a LP")) -> 0 | O23: =N23 -> 0
B24: Pasivo circulante | C24: =SUM(C19:C23) -> 0 | D24: =SUM(D19:D23) -> 0 | E24: =SUM(E19:E23) -> 0 | F24: =SUM(F19:F23) -> 0 | G24: =SUM(G19:G23) -> 0 | H24: =SUM(H19:H23) -> 0 | I24: =SUM(I19:I23) -> 0 | J24: =SUM(J19:J23) -> 0 | ... N24: =SUM(N19:N23) -> 0 | O24: =N24 -> 0
B25: Préstamos a largo plazo | C25: =SUMIFS(Pasivos!$G$7:$G$506,Pasivos!$C$7:$C$506,"Saldo inicial",Pasivos!$F$7:$F$506,"Largo plazo",Pasivos!$B$7:$B$506,DATE(Configuración!$C$5,1,1)-1)+SUMIFS(Pasivos!$G$7:$G$506,Pasivos!$B$7:$B$506,">="&C$6,Pasivos!$B$7:$B$506,"<"&EDATE(C$6,1),Pasivos!$C$7:$C$506,"Desembolso",Pasivos!$F$7:$F$506,"Largo plazo")-SUMIFS(Pasivos!$G$7:$G$506,Pasivos!$B$7:$B$506,">="&C$6,Pasivos!$B$7:$B$506,"<"&EDATE(C$6,1),Pasivos!$C$7:$C$506,"Amortización",Pasivos!$F$7:$F$506,"Largo plazo")+-1*(SUMIFS(Pasivos!$G$7:$G$506,Pasivos!$B$7:$B$506,">="&C$6,Pasivos!$B$7:$B$506,"<"&EDATE(C$6,1),Pasivos!$C$7:$C$506,"Reclasificar a CP")-SUMIFS(Pasivos!$G$7:$G$506,Pasivos!$B$7:$B$506,">="&C$6,Pasivos!$B$7:$B$506,"<"&EDATE(C$6,1),Pasivos!$C$7:$C$506,"Reclasificar a LP")) -> 0 | D25: =C25+SUMIFS(Pasivos!$G$7:$G$506,Pasivos!$B$7:$B$506,">="&D$6,Pasivos!$B$7:$B$506,"<"&EDATE(D$6,1),Pasivos!$C$7:$C$506,"Desembolso",Pasivos!$F$7:$F$506,"Largo plazo")-SUMIFS(Pasivos!$G$7:$G$506,Pasivos!$B$7:$B$506,">="&D$6,Pasivos!$B$7:$B$506,"<"&EDATE(D$6,1),Pasivos!$C$7:$C$506,"Amortización",Pasivos!$F$7:$F$506,"Largo plazo")+-1*(SUMIFS(Pasivos!$G$7:$G$506,Pasivos!$B$7:$B$506,">="&D$6,Pasivos!$B$7:$B$506,"<"&EDATE(D$6,1),Pasivos!$C$7:$C$506,"Reclasificar a CP")-SUMIFS(Pasivos!$G$7:$G$506,Pasivos!$B$7:$B$506,">="&D$6,Pasivos!$B$7:$B$506,"<"&EDATE(D$6,1),Pasivos!$C$7:$C$506,"Reclasificar a LP")) -> 0 | E25: =D25+SUMIFS(Pasivos!$G$7:$G$506,Pasivos!$B$7:$B$506,">="&E$6,Pasivos!$B$7:$B$506,"<"&EDATE(E$6,1),Pasivos!$C$7:$C$506,"Desembolso",Pasivos!$F$7:$F$506,"Largo plazo")-SUMIFS(Pasivos!$G$7:$G$506,Pasivos!$B$7:$B$506,">="&E$6,Pasivos!$B$7:$B$506,"<"&EDATE(E$6,1),Pasivos!$C$7:$C$506,"Amortización",Pasivos!$F$7:$F$506,"Largo plazo")+-1*(SUMIFS(Pasivos!$G$7:$G$506,Pasivos!$B$7:$B$506,">="&E$6,Pasivos!$B$7:$B$506,"<"&EDATE(E$6,1),Pasivos!$C$7:$C$506,"Reclasificar a CP")-SUMIFS(Pasivos!$G$7:$G$506,Pasivos!$B$7:$B$506,">="&E$6,Pasivos!$B$7:$B$506,"<"&EDATE(E$6,1),Pasivos!$C$7:$C$506,"Reclasificar a LP")) -> 0 | F25: =E25+SUMIFS(Pasivos!$G$7:$G$506,Pasivos!$B$7:$B$506,">="&F$6,Pasivos!$B$7:$B$506,"<"&EDATE(F$6,1),Pasivos!$C$7:$C$506,"Desembolso",Pasivos!$F$7:$F$506,"Largo plazo")-SUMIFS(Pasivos!$G$7:$G$506,Pasivos!$B$7:$B$506,">="&F$6,Pasivos!$B$7:$B$506,"<"&EDATE(F$6,1),Pasivos!$C$7:$C$506,"Amortización",Pasivos!$F$7:$F$506,"Largo plazo")+-1*(SUMIFS(Pasivos!$G$7:$G$506,Pasivos!$B$7:$B$506,">="&F$6,Pasivos!$B$7:$B$506,"<"&EDATE(F$6,1),Pasivos!$C$7:$C$506,"Reclasificar a CP")-SUMIFS(Pasivos!$G$7:$G$506,Pasivos!$B$7:$B$506,">="&F$6,Pasivos!$B$7:$B$506,"<"&EDATE(F$6,1),Pasivos!$C$7:$C$506,"Reclasificar a LP")) -> 0 | G25: =F25+SUMIFS(Pasivos!$G$7:$G$506,Pasivos!$B$7:$B$506,">="&G$6,Pasivos!$B$7:$B$506,"<"&EDATE(G$6,1),Pasivos!$C$7:$C$506,"Desembolso",Pasivos!$F$7:$F$506,"Largo plazo")-SUMIFS(Pasivos!$G$7:$G$506,Pasivos!$B$7:$B$506,">="&G$6,Pasivos!$B$7:$B$506,"<"&EDATE(G$6,1),Pasivos!$C$7:$C$506,"Amortización",Pasivos!$F$7:$F$506,"Largo plazo")+-1*(SUMIFS(Pasivos!$G$7:$G$506,Pasivos!$B$7:$B$506,">="&G$6,Pasivos!$B$7:$B$506,"<"&EDATE(G$6,1),Pasivos!$C$7:$C$506,"Reclasificar a CP")-SUMIFS(Pasivos!$G$7:$G$506,Pasivos!$B$7:$B$506,">="&G$6,Pasivos!$B$7:$B$506,"<"&EDATE(G$6,1),Pasivos!$C$7:$C$506,"Reclasificar a LP")) -> 0 | H25: =G25+SUMIFS(Pasivos!$G$7:$G$506,Pasivos!$B$7:$B$506,">="&H$6,Pasivos!$B$7:$B$506,"<"&EDATE(H$6,1),Pasivos!$C$7:$C$506,"Desembolso",Pasivos!$F$7:$F$506,"Largo plazo")-SUMIFS(Pasivos!$G$7:$G$506,Pasivos!$B$7:$B$506,">="&H$6,Pasivos!$B$7:$B$506,"<"&EDATE(H$6,1),Pasivos!$C$7:$C$506,"Amortización",Pasivos!$F$7:$F$506,"Largo plazo")+-1*(SUMIFS(Pasivos!$G$7:$G$506,Pasivos!$B$7:$B$506,">="&H$6,Pasivos!$B$7:$B$506,"<"&EDATE(H$6,1),Pasivos!$C$7:$C$506,"Reclasificar a CP")-SUMIFS(Pasivos!$G$7:$G$506,Pasivos!$B$7:$B$506,">="&H$6,Pasivos!$B$7:$B$506,"<"&EDATE(H$6,1),Pasivos!$C$7:$C$506,"Reclasificar a LP")) -> 0 | I25: =H25+SUMIFS(Pasivos!$G$7:$G$506,Pasivos!$B$7:$B$506,">="&I$6,Pasivos!$B$7:$B$506,"<"&EDATE(I$6,1),Pasivos!$C$7:$C$506,"Desembolso",Pasivos!$F$7:$F$506,"Largo plazo")-SUMIFS(Pasivos!$G$7:$G$506,Pasivos!$B$7:$B$506,">="&I$6,Pasivos!$B$7:$B$506,"<"&EDATE(I$6,1),Pasivos!$C$7:$C$506,"Amortización",Pasivos!$F$7:$F$506,"Largo plazo")+-1*(SUMIFS(Pasivos!$G$7:$G$506,Pasivos!$B$7:$B$506,">="&I$6,Pasivos!$B$7:$B$506,"<"&EDATE(I$6,1),Pasivos!$C$7:$C$506,"Reclasificar a CP")-SUMIFS(Pasivos!$G$7:$G$506,Pasivos!$B$7:$B$506,">="&I$6,Pasivos!$B$7:$B$506,"<"&EDATE(I$6,1),Pasivos!$C$7:$C$506,"Reclasificar a LP")) -> 0 | J25: =I25+SUMIFS(Pasivos!$G$7:$G$506,Pasivos!$B$7:$B$506,">="&J$6,Pasivos!$B$7:$B$506,"<"&EDATE(J$6,1),Pasivos!$C$7:$C$506,"Desembolso",Pasivos!$F$7:$F$506,"Largo plazo")-SUMIFS(Pasivos!$G$7:$G$506,Pasivos!$B$7:$B$506,">="&J$6,Pasivos!$B$7:$B$506,"<"&EDATE(J$6,1),Pasivos!$C$7:$C$506,"Amortización",Pasivos!$F$7:$F$506,"Largo plazo")+-1*(SUMIFS(Pasivos!$G$7:$G$506,Pasivos!$B$7:$B$506,">="&J$6,Pasivos!$B$7:$B$506,"<"&EDATE(J$6,1),Pasivos!$C$7:$C$506,"Reclasificar a CP")-SUMIFS(Pasivos!$G$7:$G$506,Pasivos!$B$7:$B$506,">="&J$6,Pasivos!$B$7:$B$506,"<"&EDATE(J$6,1),Pasivos!$C$7:$C$506,"Reclasificar a LP")) -> 0 | K25: =J25+SUMIFS(Pasivos!$G$7:$G$506,Pasivos!$B$7:$B$506,">="&K$6,Pasivos!$B$7:$B$506,"<"&EDATE(K$6,1),Pasivos!$C$7:$C$506,"Desembolso",Pasivos!$F$7:$F$506,"Largo plazo")-SUMIFS(Pasivos!$G$7:$G$506,Pasivos!$B$7:$B$506,">="&K$6,Pasivos!$B$7:$B$506,"<"&EDATE(K$6,1),Pasivos!$C$7:$C$506,"Amortización",Pasivos!$F$7:$F$506,"Largo plazo")+-1*(SUMIFS(Pasivos!$G$7:$G$506,Pasivos!$B$7:$B$506,">="&K$6,Pasivos!$B$7:$B$506,"<"&EDATE(K$6,1),Pasivos!$C$7:$C$506,"Reclasificar a CP")-SUMIFS(Pasivos!$G$7:$G$506,Pasivos!$B$7:$B$506,">="&K$6,Pasivos!$B$7:$B$506,"<"&EDATE(K$6,1),Pasivos!$C$7:$C$506,"Reclasificar a LP")) -> 0 | ... N25: =M25+SUMIFS(Pasivos!$G$7:$G$506,Pasivos!$B$7:$B$506,">="&N$6,Pasivos!$B$7:$B$506,"<"&EDATE(N$6,1),Pasivos!$C$7:$C$506,"Desembolso",Pasivos!$F$7:$F$506,"Largo plazo")-SUMIFS(Pasivos!$G$7:$G$506,Pasivos!$B$7:$B$506,">="&N$6,Pasivos!$B$7:$B$506,"<"&EDATE(N$6,1),Pasivos!$C$7:$C$506,"Amortización",Pasivos!$F$7:$F$506,"Largo plazo")+-1*(SUMIFS(Pasivos!$G$7:$G$506,Pasivos!$B$7:$B$506,">="&N$6,Pasivos!$B$7:$B$506,"<"&EDATE(N$6,1),Pasivos!$C$7:$C$506,"Reclasificar a CP")-SUMIFS(Pasivos!$G$7:$G$506,Pasivos!$B$7:$B$506,">="&N$6,Pasivos!$B$7:$B$506,"<"&EDATE(N$6,1),Pasivos!$C$7:$C$506,"Reclasificar a LP")) -> 0 | O25: =N25 -> 0
B26: Total pasivo | C26: =C24+C25 -> 0 | D26: =D24+D25 -> 0 | E26: =E24+E25 -> 0 | F26: =F24+F25 -> 0 | G26: =G24+G25 -> 0 | H26: =H24+H25 -> 0 | I26: =I24+I25 -> 0 | J26: =J24+J25 -> 0 | ... N26: =N24+N25 -> 0 | O26: =N26 -> 0
B28: Capital y aportaciones | C28: =Configuración!$C$18+'Flujo de Efectivo'!C19 -> 0 | D28: =C28+'Flujo de Efectivo'!D19 -> 0 | E28: =D28+'Flujo de Efectivo'!E19 -> 0 | F28: =E28+'Flujo de Efectivo'!F19 -> 0 | G28: =F28+'Flujo de Efectivo'!G19 -> 0 | H28: =G28+'Flujo de Efectivo'!H19 -> 0 | I28: =H28+'Flujo de Efectivo'!I19 -> 0 | J28: =I28+'Flujo de Efectivo'!J19 -> 0 | K28: =J28+'Flujo de Efectivo'!K19 -> 0 | ... N28: =M28+'Flujo de Efectivo'!N19 -> 0 | O28: =N28 -> 0
B29: Resultados acumulados | C29: =Configuración!$C$19 -> 0 | D29: =Configuración!$C$19 -> 0 | E29: =Configuración!$C$19 -> 0 | F29: =Configuración!$C$19 -> 0 | G29: =Configuración!$C$19 -> 0 | H29: =Configuración!$C$19 -> 0 | I29: =Configuración!$C$19 -> 0 | J29: =Configuración!$C$19 -> 0 | ... N29: =Configuración!$C$19 -> 0 | O29: =N29 -> 0
B30: Resultado del ejercicio acumulado | C30: =0+'Estado de Resultados'!C33 -> 2200 | D30: =C30+'Estado de Resultados'!D33 -> 2200 | E30: =D30+'Estado de Resultados'!E33 -> 2200 | F30: =E30+'Estado de Resultados'!F33 -> 2200 | G30: =F30+'Estado de Resultados'!G33 -> 2200 | H30: =G30+'Estado de Resultados'!H33 -> 2200 | I30: =H30+'Estado de Resultados'!I33 -> 2200 | J30: =I30+'Estado de Resultados'!J33 -> 2200 | K30: =J30+'Estado de Resultados'!K33 -> 2200 | ... N30: =M30+'Estado de Resultados'!N33 -> 2200 | O30: =N30 -> 2200
B31: Retiros acumulados (restan) | C31: =0+'Flujo de Efectivo'!C20 -> 0 | D31: =C31+'Flujo de Efectivo'!D20 -> 0 | E31: =D31+'Flujo de Efectivo'!E20 -> 0 | F31: =E31+'Flujo de Efectivo'!F20 -> 0 | G31: =F31+'Flujo de Efectivo'!G20 -> 0 | H31: =G31+'Flujo de Efectivo'!H20 -> 0 | I31: =H31+'Flujo de Efectivo'!I20 -> 0 | J31: =I31+'Flujo de Efectivo'!J20 -> 0 | K31: =J31+'Flujo de Efectivo'!K20 -> 0 | ... N31: =M31+'Flujo de Efectivo'!N20 -> 0 | O31: =N31 -> 0
B32: Patrimonio | C32: =SUM(C28:C30)-C31 -> 2200 | D32: =SUM(D28:D30)-D31 -> 2200 | E32: =SUM(E28:E30)-E31 -> 2200 | F32: =SUM(F28:F30)-F31 -> 2200 | G32: =SUM(G28:G30)-G31 -> 2200 | H32: =SUM(H28:H30)-H31 -> 2200 | I32: =SUM(I28:I30)-I31 -> 2200 | J32: =SUM(J28:J30)-J31 -> 2200 | ... N32: =SUM(N28:N30)-N31 -> 2200 | O32: =N32 -> 2200
B33: Pasivo más patrimonio | C33: =C26+C32 -> 2200 | D33: =D26+D32 -> 2200 | E33: =E26+E32 -> 2200 | F33: =F26+F32 -> 2200 | G33: =G26+G32 -> 2200 | H33: =H26+H32 -> 2200 | I33: =I26+I32 -> 2200 | J33: =J26+J32 -> 2200 | ... N33: =N26+N32 -> 2200 | O33: =N33 -> 2200
B35: Diferencia de balance | C35: =C17-C33 -> 0 | D35: =D17-D33 -> 0 | E35: =E17-E33 -> 0 | F35: =F17-F33 -> 0 | G35: =G17-G33 -> 0 | H35: =H17-H33 -> 0 | I35: =I17-I33 -> 0 | J35: =J17-J33 -> 0 | ... N35: =N17-N33 -> 0 | O35: =N35 -> 0
B37: Cálculos de apoyo
B38: IVA neto: positivo por pagar | C38: =Configuración!$C$16-Configuración!$C$11+SUMIFS(Ingresos!$H$7:$H$2006,Ingresos!$B$7:$B$2006,">="&C$6,Ingresos!$B$7:$B$2006,"<"&EDATE(C$6,1),Ingresos!$C$7:$C$2006,"Servicio")-SUMIFS(Gastos!$I$7:$I$2006,Gastos!$B$7:$B$2006,">="&C$6,Gastos!$B$7:$B$2006,"<"&EDATE(C$6,1),Gastos!$C$7:$C$2006,"Gasto")-C40-'Flujo de Efectivo'!C11-C45 -> 0 | D38: =C38+SUMIFS(Ingresos!$H$7:$H$2006,Ingresos!$B$7:$B$2006,">="&D$6,Ingresos!$B$7:$B$2006,"<"&EDATE(D$6,1),Ingresos!$C$7:$C$2006,"Servicio")-SUMIFS(Gastos!$I$7:$I$2006,Gastos!$B$7:$B$2006,">="&D$6,Gastos!$B$7:$B$2006,"<"&EDATE(D$6,1),Gastos!$C$7:$C$2006,"Gasto")-D40-'Flujo de Efectivo'!D11-D45 -> 0 | E38: =D38+SUMIFS(Ingresos!$H$7:$H$2006,Ingresos!$B$7:$B$2006,">="&E$6,Ingresos!$B$7:$B$2006,"<"&EDATE(E$6,1),Ingresos!$C$7:$C$2006,"Servicio")-SUMIFS(Gastos!$I$7:$I$2006,Gastos!$B$7:$B$2006,">="&E$6,Gastos!$B$7:$B$2006,"<"&EDATE(E$6,1),Gastos!$C$7:$C$2006,"Gasto")-E40-'Flujo de Efectivo'!E11-E45 -> 0 | F38: =E38+SUMIFS(Ingresos!$H$7:$H$2006,Ingresos!$B$7:$B$2006,">="&F$6,Ingresos!$B$7:$B$2006,"<"&EDATE(F$6,1),Ingresos!$C$7:$C$2006,"Servicio")-SUMIFS(Gastos!$I$7:$I$2006,Gastos!$B$7:$B$2006,">="&F$6,Gastos!$B$7:$B$2006,"<"&EDATE(F$6,1),Gastos!$C$7:$C$2006,"Gasto")-F40-'Flujo de Efectivo'!F11-F45 -> 0 | G38: =F38+SUMIFS(Ingresos!$H$7:$H$2006,Ingresos!$B$7:$B$2006,">="&G$6,Ingresos!$B$7:$B$2006,"<"&EDATE(G$6,1),Ingresos!$C$7:$C$2006,"Servicio")-SUMIFS(Gastos!$I$7:$I$2006,Gastos!$B$7:$B$2006,">="&G$6,Gastos!$B$7:$B$2006,"<"&EDATE(G$6,1),Gastos!$C$7:$C$2006,"Gasto")-G40-'Flujo de Efectivo'!G11-G45 -> 0 | H38: =G38+SUMIFS(Ingresos!$H$7:$H$2006,Ingresos!$B$7:$B$2006,">="&H$6,Ingresos!$B$7:$B$2006,"<"&EDATE(H$6,1),Ingresos!$C$7:$C$2006,"Servicio")-SUMIFS(Gastos!$I$7:$I$2006,Gastos!$B$7:$B$2006,">="&H$6,Gastos!$B$7:$B$2006,"<"&EDATE(H$6,1),Gastos!$C$7:$C$2006,"Gasto")-H40-'Flujo de Efectivo'!H11-H45 -> 0 | I38: =H38+SUMIFS(Ingresos!$H$7:$H$2006,Ingresos!$B$7:$B$2006,">="&I$6,Ingresos!$B$7:$B$2006,"<"&EDATE(I$6,1),Ingresos!$C$7:$C$2006,"Servicio")-SUMIFS(Gastos!$I$7:$I$2006,Gastos!$B$7:$B$2006,">="&I$6,Gastos!$B$7:$B$2006,"<"&EDATE(I$6,1),Gastos!$C$7:$C$2006,"Gasto")-I40-'Flujo de Efectivo'!I11-I45 -> 0 | J38: =I38+SUMIFS(Ingresos!$H$7:$H$2006,Ingresos!$B$7:$B$2006,">="&J$6,Ingresos!$B$7:$B$2006,"<"&EDATE(J$6,1),Ingresos!$C$7:$C$2006,"Servicio")-SUMIFS(Gastos!$I$7:$I$2006,Gastos!$B$7:$B$2006,">="&J$6,Gastos!$B$7:$B$2006,"<"&EDATE(J$6,1),Gastos!$C$7:$C$2006,"Gasto")-J40-'Flujo de Efectivo'!J11-J45 -> 0 | K38: =J38+SUMIFS(Ingresos!$H$7:$H$2006,Ingresos!$B$7:$B$2006,">="&K$6,Ingresos!$B$7:$B$2006,"<"&EDATE(K$6,1),Ingresos!$C$7:$C$2006,"Servicio")-SUMIFS(Gastos!$I$7:$I$2006,Gastos!$B$7:$B$2006,">="&K$6,Gastos!$B$7:$B$2006,"<"&EDATE(K$6,1),Gastos!$C$7:$C$2006,"Gasto")-K40-'Flujo de Efectivo'!K11-K45 -> 0 | ... N38: =M38+SUMIFS(Ingresos!$H$7:$H$2006,Ingresos!$B$7:$B$2006,">="&N$6,Ingresos!$B$7:$B$2006,"<"&EDATE(N$6,1),Ingresos!$C$7:$C$2006,"Servicio")-SUMIFS(Gastos!$I$7:$I$2006,Gastos!$B$7:$B$2006,">="&N$6,Gastos!$B$7:$B$2006,"<"&EDATE(N$6,1),Gastos!$C$7:$C$2006,"Gasto")-N40-'Flujo de Efectivo'!N11-N45 -> 0 | O38: =N38 -> 0
B39: Altas de activos (costo) | C39: =SUMIFS(Activos!$E$7:$E$106,Activos!$C$7:$C$106,">="&C$6,Activos!$C$7:$C$106,"<"&EDATE(C$6,1)) -> 0 | D39: =SUMIFS(Activos!$E$7:$E$106,Activos!$C$7:$C$106,">="&D$6,Activos!$C$7:$C$106,"<"&EDATE(D$6,1)) -> 0 | E39: =SUMIFS(Activos!$E$7:$E$106,Activos!$C$7:$C$106,">="&E$6,Activos!$C$7:$C$106,"<"&EDATE(E$6,1)) -> 0 | F39: =SUMIFS(Activos!$E$7:$E$106,Activos!$C$7:$C$106,">="&F$6,Activos!$C$7:$C$106,"<"&EDATE(F$6,1)) -> 0 | G39: =SUMIFS(Activos!$E$7:$E$106,Activos!$C$7:$C$106,">="&G$6,Activos!$C$7:$C$106,"<"&EDATE(G$6,1)) -> 0 | H39: =SUMIFS(Activos!$E$7:$E$106,Activos!$C$7:$C$106,">="&H$6,Activos!$C$7:$C$106,"<"&EDATE(H$6,1)) -> 0 | I39: =SUMIFS(Activos!$E$7:$E$106,Activos!$C$7:$C$106,">="&I$6,Activos!$C$7:$C$106,"<"&EDATE(I$6,1)) -> 0 | J39: =SUMIFS(Activos!$E$7:$E$106,Activos!$C$7:$C$106,">="&J$6,Activos!$C$7:$C$106,"<"&EDATE(J$6,1)) -> 0 | ... N39: =SUMIFS(Activos!$E$7:$E$106,Activos!$C$7:$C$106,">="&N$6,Activos!$C$7:$C$106,"<"&EDATE(N$6,1)) -> 0 | O39: =SUM(C39:N39) -> 0
B40: IVA recuperable de activos | C40: =SUMIFS(Activos!$F$7:$F$106,Activos!$C$7:$C$106,">="&C$6,Activos!$C$7:$C$106,"<"&EDATE(C$6,1)) -> 0 | D40: =SUMIFS(Activos!$F$7:$F$106,Activos!$C$7:$C$106,">="&D$6,Activos!$C$7:$C$106,"<"&EDATE(D$6,1)) -> 0 | E40: =SUMIFS(Activos!$F$7:$F$106,Activos!$C$7:$C$106,">="&E$6,Activos!$C$7:$C$106,"<"&EDATE(E$6,1)) -> 0 | F40: =SUMIFS(Activos!$F$7:$F$106,Activos!$C$7:$C$106,">="&F$6,Activos!$C$7:$C$106,"<"&EDATE(F$6,1)) -> 0 | G40: =SUMIFS(Activos!$F$7:$F$106,Activos!$C$7:$C$106,">="&G$6,Activos!$C$7:$C$106,"<"&EDATE(G$6,1)) -> 0 | H40: =SUMIFS(Activos!$F$7:$F$106,Activos!$C$7:$C$106,">="&H$6,Activos!$C$7:$C$106,"<"&EDATE(H$6,1)) -> 0 | I40: =SUMIFS(Activos!$F$7:$F$106,Activos!$C$7:$C$106,">="&I$6,Activos!$C$7:$C$106,"<"&EDATE(I$6,1)) -> 0 | J40: =SUMIFS(Activos!$F$7:$F$106,Activos!$C$7:$C$106,">="&J$6,Activos!$C$7:$C$106,"<"&EDATE(J$6,1)) -> 0 | ... N40: =SUMIFS(Activos!$F$7:$F$106,Activos!$C$7:$C$106,">="&N$6,Activos!$C$7:$C$106,"<"&EDATE(N$6,1)) -> 0 | O40: =SUM(C40:N40) -> 0
B41: Aplicación de anticipos | C41: =SUMIFS(Ingresos!$K$7:$K$2006,Ingresos!$B$7:$B$2006,">="&C$6,Ingresos!$B$7:$B$2006,"<"&EDATE(C$6,1),Ingresos!$C$7:$C$2006,"Aplicación anticipo") -> 0 | D41: =SUMIFS(Ingresos!$K$7:$K$2006,Ingresos!$B$7:$B$2006,">="&D$6,Ingresos!$B$7:$B$2006,"<"&EDATE(D$6,1),Ingresos!$C$7:$C$2006,"Aplicación anticipo") -> 0 | E41: =SUMIFS(Ingresos!$K$7:$K$2006,Ingresos!$B$7:$B$2006,">="&E$6,Ingresos!$B$7:$B$2006,"<"&EDATE(E$6,1),Ingresos!$C$7:$C$2006,"Aplicación anticipo") -> 0 | F41: =SUMIFS(Ingresos!$K$7:$K$2006,Ingresos!$B$7:$B$2006,">="&F$6,Ingresos!$B$7:$B$2006,"<"&EDATE(F$6,1),Ingresos!$C$7:$C$2006,"Aplicación anticipo") -> 0 | G41: =SUMIFS(Ingresos!$K$7:$K$2006,Ingresos!$B$7:$B$2006,">="&G$6,Ingresos!$B$7:$B$2006,"<"&EDATE(G$6,1),Ingresos!$C$7:$C$2006,"Aplicación anticipo") -> 0 | H41: =SUMIFS(Ingresos!$K$7:$K$2006,Ingresos!$B$7:$B$2006,">="&H$6,Ingresos!$B$7:$B$2006,"<"&EDATE(H$6,1),Ingresos!$C$7:$C$2006,"Aplicación anticipo") -> 0 | I41: =SUMIFS(Ingresos!$K$7:$K$2006,Ingresos!$B$7:$B$2006,">="&I$6,Ingresos!$B$7:$B$2006,"<"&EDATE(I$6,1),Ingresos!$C$7:$C$2006,"Aplicación anticipo") -> 0 | J41: =SUMIFS(Ingresos!$K$7:$K$2006,Ingresos!$B$7:$B$2006,">="&J$6,Ingresos!$B$7:$B$2006,"<"&EDATE(J$6,1),Ingresos!$C$7:$C$2006,"Aplicación anticipo") -> 0 | ... N41: =SUMIFS(Ingresos!$K$7:$K$2006,Ingresos!$B$7:$B$2006,">="&N$6,Ingresos!$B$7:$B$2006,"<"&EDATE(N$6,1),Ingresos!$C$7:$C$2006,"Aplicación anticipo") -> 0 | O41: =SUM(C41:N41) -> 0
B42: Retenciones ISR del mes | C42: =SUMIFS(Ingresos!$K$7:$K$2006,Ingresos!$B$7:$B$2006,">="&C$6,Ingresos!$B$7:$B$2006,"<"&EDATE(C$6,1),Ingresos!$C$7:$C$2006,"Retención ISR") -> 0 | D42: =SUMIFS(Ingresos!$K$7:$K$2006,Ingresos!$B$7:$B$2006,">="&D$6,Ingresos!$B$7:$B$2006,"<"&EDATE(D$6,1),Ingresos!$C$7:$C$2006,"Retención ISR") -> 0 | E42: =SUMIFS(Ingresos!$K$7:$K$2006,Ingresos!$B$7:$B$2006,">="&E$6,Ingresos!$B$7:$B$2006,"<"&EDATE(E$6,1),Ingresos!$C$7:$C$2006,"Retención ISR") -> 0 | F42: =SUMIFS(Ingresos!$K$7:$K$2006,Ingresos!$B$7:$B$2006,">="&F$6,Ingresos!$B$7:$B$2006,"<"&EDATE(F$6,1),Ingresos!$C$7:$C$2006,"Retención ISR") -> 0 | G42: =SUMIFS(Ingresos!$K$7:$K$2006,Ingresos!$B$7:$B$2006,">="&G$6,Ingresos!$B$7:$B$2006,"<"&EDATE(G$6,1),Ingresos!$C$7:$C$2006,"Retención ISR") -> 0 | H42: =SUMIFS(Ingresos!$K$7:$K$2006,Ingresos!$B$7:$B$2006,">="&H$6,Ingresos!$B$7:$B$2006,"<"&EDATE(H$6,1),Ingresos!$C$7:$C$2006,"Retención ISR") -> 0 | I42: =SUMIFS(Ingresos!$K$7:$K$2006,Ingresos!$B$7:$B$2006,">="&I$6,Ingresos!$B$7:$B$2006,"<"&EDATE(I$6,1),Ingresos!$C$7:$C$2006,"Retención ISR") -> 0 | J42: =SUMIFS(Ingresos!$K$7:$K$2006,Ingresos!$B$7:$B$2006,">="&J$6,Ingresos!$B$7:$B$2006,"<"&EDATE(J$6,1),Ingresos!$C$7:$C$2006,"Retención ISR") -> 0 | ... N42: =SUMIFS(Ingresos!$K$7:$K$2006,Ingresos!$B$7:$B$2006,">="&N$6,Ingresos!$B$7:$B$2006,"<"&EDATE(N$6,1),Ingresos!$C$7:$C$2006,"Retención ISR") -> 0 | O42: =SUM(C42:N42) -> 0
B43: Retenciones IVA del mes | C43: =SUMIFS(Ingresos!$K$7:$K$2006,Ingresos!$B$7:$B$2006,">="&C$6,Ingresos!$B$7:$B$2006,"<"&EDATE(C$6,1),Ingresos!$C$7:$C$2006,"Retención IVA") -> 0 | D43: =SUMIFS(Ingresos!$K$7:$K$2006,Ingresos!$B$7:$B$2006,">="&D$6,Ingresos!$B$7:$B$2006,"<"&EDATE(D$6,1),Ingresos!$C$7:$C$2006,"Retención IVA") -> 0 | E43: =SUMIFS(Ingresos!$K$7:$K$2006,Ingresos!$B$7:$B$2006,">="&E$6,Ingresos!$B$7:$B$2006,"<"&EDATE(E$6,1),Ingresos!$C$7:$C$2006,"Retención IVA") -> 0 | F43: =SUMIFS(Ingresos!$K$7:$K$2006,Ingresos!$B$7:$B$2006,">="&F$6,Ingresos!$B$7:$B$2006,"<"&EDATE(F$6,1),Ingresos!$C$7:$C$2006,"Retención IVA") -> 0 | G43: =SUMIFS(Ingresos!$K$7:$K$2006,Ingresos!$B$7:$B$2006,">="&G$6,Ingresos!$B$7:$B$2006,"<"&EDATE(G$6,1),Ingresos!$C$7:$C$2006,"Retención IVA") -> 0 | H43: =SUMIFS(Ingresos!$K$7:$K$2006,Ingresos!$B$7:$B$2006,">="&H$6,Ingresos!$B$7:$B$2006,"<"&EDATE(H$6,1),Ingresos!$C$7:$C$2006,"Retención IVA") -> 0 | I43: =SUMIFS(Ingresos!$K$7:$K$2006,Ingresos!$B$7:$B$2006,">="&I$6,Ingresos!$B$7:$B$2006,"<"&EDATE(I$6,1),Ingresos!$C$7:$C$2006,"Retención IVA") -> 0 | J43: =SUMIFS(Ingresos!$K$7:$K$2006,Ingresos!$B$7:$B$2006,">="&J$6,Ingresos!$B$7:$B$2006,"<"&EDATE(J$6,1),Ingresos!$C$7:$C$2006,"Retención IVA") -> 0 | ... N43: =SUMIFS(Ingresos!$K$7:$K$2006,Ingresos!$B$7:$B$2006,">="&N$6,Ingresos!$B$7:$B$2006,"<"&EDATE(N$6,1),Ingresos!$C$7:$C$2006,"Retención IVA") -> 0 | O43: =SUM(C43:N43) -> 0
B44: Compensación ISR del mes | C44: =SUMIFS(Gastos!$K$7:$K$2006,Gastos!$B$7:$B$2006,">="&C$6,Gastos!$B$7:$B$2006,"<"&EDATE(C$6,1),Gastos!$C$7:$C$2006,"Compensación ISR") -> 0 | D44: =SUMIFS(Gastos!$K$7:$K$2006,Gastos!$B$7:$B$2006,">="&D$6,Gastos!$B$7:$B$2006,"<"&EDATE(D$6,1),Gastos!$C$7:$C$2006,"Compensación ISR") -> 0 | E44: =SUMIFS(Gastos!$K$7:$K$2006,Gastos!$B$7:$B$2006,">="&E$6,Gastos!$B$7:$B$2006,"<"&EDATE(E$6,1),Gastos!$C$7:$C$2006,"Compensación ISR") -> 0 | F44: =SUMIFS(Gastos!$K$7:$K$2006,Gastos!$B$7:$B$2006,">="&F$6,Gastos!$B$7:$B$2006,"<"&EDATE(F$6,1),Gastos!$C$7:$C$2006,"Compensación ISR") -> 0 | G44: =SUMIFS(Gastos!$K$7:$K$2006,Gastos!$B$7:$B$2006,">="&G$6,Gastos!$B$7:$B$2006,"<"&EDATE(G$6,1),Gastos!$C$7:$C$2006,"Compensación ISR") -> 0 | H44: =SUMIFS(Gastos!$K$7:$K$2006,Gastos!$B$7:$B$2006,">="&H$6,Gastos!$B$7:$B$2006,"<"&EDATE(H$6,1),Gastos!$C$7:$C$2006,"Compensación ISR") -> 0 | I44: =SUMIFS(Gastos!$K$7:$K$2006,Gastos!$B$7:$B$2006,">="&I$6,Gastos!$B$7:$B$2006,"<"&EDATE(I$6,1),Gastos!$C$7:$C$2006,"Compensación ISR") -> 0 | J44: =SUMIFS(Gastos!$K$7:$K$2006,Gastos!$B$7:$B$2006,">="&J$6,Gastos!$B$7:$B$2006,"<"&EDATE(J$6,1),Gastos!$C$7:$C$2006,"Compensación ISR") -> 0 | ... N44: =SUMIFS(Gastos!$K$7:$K$2006,Gastos!$B$7:$B$2006,">="&N$6,Gastos!$B$7:$B$2006,"<"&EDATE(N$6,1),Gastos!$C$7:$C$2006,"Compensación ISR") -> 0 | O44: =SUM(C44:N44) -> 0
B45: Compensación IVA del mes | C45: =SUMIFS(Gastos!$K$7:$K$2006,Gastos!$B$7:$B$2006,">="&C$6,Gastos!$B$7:$B$2006,"<"&EDATE(C$6,1),Gastos!$C$7:$C$2006,"Compensación IVA") -> 0 | D45: =SUMIFS(Gastos!$K$7:$K$2006,Gastos!$B$7:$B$2006,">="&D$6,Gastos!$B$7:$B$2006,"<"&EDATE(D$6,1),Gastos!$C$7:$C$2006,"Compensación IVA") -> 0 | E45: =SUMIFS(Gastos!$K$7:$K$2006,Gastos!$B$7:$B$2006,">="&E$6,Gastos!$B$7:$B$2006,"<"&EDATE(E$6,1),Gastos!$C$7:$C$2006,"Compensación IVA") -> 0 | F45: =SUMIFS(Gastos!$K$7:$K$2006,Gastos!$B$7:$B$2006,">="&F$6,Gastos!$B$7:$B$2006,"<"&EDATE(F$6,1),Gastos!$C$7:$C$2006,"Compensación IVA") -> 0 | G45: =SUMIFS(Gastos!$K$7:$K$2006,Gastos!$B$7:$B$2006,">="&G$6,Gastos!$B$7:$B$2006,"<"&EDATE(G$6,1),Gastos!$C$7:$C$2006,"Compensación IVA") -> 0 | H45: =SUMIFS(Gastos!$K$7:$K$2006,Gastos!$B$7:$B$2006,">="&H$6,Gastos!$B$7:$B$2006,"<"&EDATE(H$6,1),Gastos!$C$7:$C$2006,"Compensación IVA") -> 0 | I45: =SUMIFS(Gastos!$K$7:$K$2006,Gastos!$B$7:$B$2006,">="&I$6,Gastos!$B$7:$B$2006,"<"&EDATE(I$6,1),Gastos!$C$7:$C$2006,"Compensación IVA") -> 0 | J45: =SUMIFS(Gastos!$K$7:$K$2006,Gastos!$B$7:$B$2006,">="&J$6,Gastos!$B$7:$B$2006,"<"&EDATE(J$6,1),Gastos!$C$7:$C$2006,"Compensación IVA") -> 0 | ... N45: =SUMIFS(Gastos!$K$7:$K$2006,Gastos!$B$7:$B$2006,">="&N$6,Gastos!$B$7:$B$2006,"<"&EDATE(N$6,1),Gastos!$C$7:$C$2006,"Compensación IVA") -> 0 | O45: =SUM(C45:N45) -> 0

Sheet Flujo de Efectivo
B2: Flujo de Efectivo
B4: MXN · enero a diciembre
B6: Concepto | C6: =DATE(Configuración!$C$5,1,1) -> 46023 | D6: =DATE(Configuración!$C$5,2,1) -> 46054 | E6: =DATE(Configuración!$C$5,3,1) -> 46082 | F6: =DATE(Configuración!$C$5,4,1) -> 46113 | G6: =DATE(Configuración!$C$5,5,1) -> 46143 | H6: =DATE(Configuración!$C$5,6,1) -> 46174 | I6: =DATE(Configuración!$C$5,7,1) -> 46204 | J6: =DATE(Configuración!$C$5,8,1) -> 46235 | K6: =DATE(Configuración!$C$5,9,1) -> 46266 | L6: =DATE(Configuración!$C$5,10,1) -> 46296 | M6: =DATE(Configuración!$C$5,11,1) -> 46327 | N6: =DATE(Configuración!$C$5,12,1) -> 46357 | O6: Total anual
B7: Cobros de servicios | C7: =SUMIFS(Ingresos!$K$7:$K$2006,Ingresos!$B$7:$B$2006,">="&C$6,Ingresos!$B$7:$B$2006,"<"&EDATE(C$6,1),Ingresos!$C$7:$C$2006,"Cobro") -> 2200 | D7: =SUMIFS(Ingresos!$K$7:$K$2006,Ingresos!$B$7:$B$2006,">="&D$6,Ingresos!$B$7:$B$2006,"<"&EDATE(D$6,1),Ingresos!$C$7:$C$2006,"Cobro") -> 0 | E7: =SUMIFS(Ingresos!$K$7:$K$2006,Ingresos!$B$7:$B$2006,">="&E$6,Ingresos!$B$7:$B$2006,"<"&EDATE(E$6,1),Ingresos!$C$7:$C$2006,"Cobro") -> 0 | F7: =SUMIFS(Ingresos!$K$7:$K$2006,Ingresos!$B$7:$B$2006,">="&F$6,Ingresos!$B$7:$B$2006,"<"&EDATE(F$6,1),Ingresos!$C$7:$C$2006,"Cobro") -> 0 | G7: =SUMIFS(Ingresos!$K$7:$K$2006,Ingresos!$B$7:$B$2006,">="&G$6,Ingresos!$B$7:$B$2006,"<"&EDATE(G$6,1),Ingresos!$C$7:$C$2006,"Cobro") -> 0 | H7: =SUMIFS(Ingresos!$K$7:$K$2006,Ingresos!$B$7:$B$2006,">="&H$6,Ingresos!$B$7:$B$2006,"<"&EDATE(H$6,1),Ingresos!$C$7:$C$2006,"Cobro") -> 0 | I7: =SUMIFS(Ingresos!$K$7:$K$2006,Ingresos!$B$7:$B$2006,">="&I$6,Ingresos!$B$7:$B$2006,"<"&EDATE(I$6,1),Ingresos!$C$7:$C$2006,"Cobro") -> 0 | J7: =SUMIFS(Ingresos!$K$7:$K$2006,Ingresos!$B$7:$B$2006,">="&J$6,Ingresos!$B$7:$B$2006,"<"&EDATE(J$6,1),Ingresos!$C$7:$C$2006,"Cobro") -> 0 | ... N7: =SUMIFS(Ingresos!$K$7:$K$2006,Ingresos!$B$7:$B$2006,">="&N$6,Ingresos!$B$7:$B$2006,"<"&EDATE(N$6,1),Ingresos!$C$7:$C$2006,"Cobro") -> 0 | O7: =SUM(C7:N7) -> 2200
B8: Anticipos recibidos | C8: =SUMIFS(Ingresos!$K$7:$K$2006,Ingresos!$B$7:$B$2006,">="&C$6,Ingresos!$B$7:$B$2006,"<"&EDATE(C$6,1),Ingresos!$C$7:$C$2006,"Anticipo") -> 0 | D8: =SUMIFS(Ingresos!$K$7:$K$2006,Ingresos!$B$7:$B$2006,">="&D$6,Ingresos!$B$7:$B$2006,"<"&EDATE(D$6,1),Ingresos!$C$7:$C$2006,"Anticipo") -> 0 | E8: =SUMIFS(Ingresos!$K$7:$K$2006,Ingresos!$B$7:$B$2006,">="&E$6,Ingresos!$B$7:$B$2006,"<"&EDATE(E$6,1),Ingresos!$C$7:$C$2006,"Anticipo") -> 0 | F8: =SUMIFS(Ingresos!$K$7:$K$2006,Ingresos!$B$7:$B$2006,">="&F$6,Ingresos!$B$7:$B$2006,"<"&EDATE(F$6,1),Ingresos!$C$7:$C$2006,"Anticipo") -> 0 | G8: =SUMIFS(Ingresos!$K$7:$K$2006,Ingresos!$B$7:$B$2006,">="&G$6,Ingresos!$B$7:$B$2006,"<"&EDATE(G$6,1),Ingresos!$C$7:$C$2006,"Anticipo") -> 0 | H8: =SUMIFS(Ingresos!$K$7:$K$2006,Ingresos!$B$7:$B$2006,">="&H$6,Ingresos!$B$7:$B$2006,"<"&EDATE(H$6,1),Ingresos!$C$7:$C$2006,"Anticipo") -> 0 | I8: =SUMIFS(Ingresos!$K$7:$K$2006,Ingresos!$B$7:$B$2006,">="&I$6,Ingresos!$B$7:$B$2006,"<"&EDATE(I$6,1),Ingresos!$C$7:$C$2006,"Anticipo") -> 0 | J8: =SUMIFS(Ingresos!$K$7:$K$2006,Ingresos!$B$7:$B$2006,">="&J$6,Ingresos!$B$7:$B$2006,"<"&EDATE(J$6,1),Ingresos!$C$7:$C$2006,"Anticipo") -> 0 | ... N8: =SUMIFS(Ingresos!$K$7:$K$2006,Ingresos!$B$7:$B$2006,">="&N$6,Ingresos!$B$7:$B$2006,"<"&EDATE(N$6,1),Ingresos!$C$7:$C$2006,"Anticipo") -> 0 | O8: =SUM(C8:N8) -> 0
B9: Pagos a proveedores y personal | C9: =SUMIFS(Gastos!$K$7:$K$2006,Gastos!$B$7:$B$2006,">="&C$6,Gastos!$B$7:$B$2006,"<"&EDATE(C$6,1),Gastos!$C$7:$C$2006,"Pago proveedor") -> 0 | D9: =SUMIFS(Gastos!$K$7:$K$2006,Gastos!$B$7:$B$2006,">="&D$6,Gastos!$B$7:$B$2006,"<"&EDATE(D$6,1),Gastos!$C$7:$C$2006,"Pago proveedor") -> 0 | E9: =SUMIFS(Gastos!$K$7:$K$2006,Gastos!$B$7:$B$2006,">="&E$6,Gastos!$B$7:$B$2006,"<"&EDATE(E$6,1),Gastos!$C$7:$C$2006,"Pago proveedor") -> 0 | F9: =SUMIFS(Gastos!$K$7:$K$2006,Gastos!$B$7:$B$2006,">="&F$6,Gastos!$B$7:$B$2006,"<"&EDATE(F$6,1),Gastos!$C$7:$C$2006,"Pago proveedor") -> 0 | G9: =SUMIFS(Gastos!$K$7:$K$2006,Gastos!$B$7:$B$2006,">="&G$6,Gastos!$B$7:$B$2006,"<"&EDATE(G$6,1),Gastos!$C$7:$C$2006,"Pago proveedor") -> 0 | H9: =SUMIFS(Gastos!$K$7:$K$2006,Gastos!$B$7:$B$2006,">="&H$6,Gastos!$B$7:$B$2006,"<"&EDATE(H$6,1),Gastos!$C$7:$C$2006,"Pago proveedor") -> 0 | I9: =SUMIFS(Gastos!$K$7:$K$2006,Gastos!$B$7:$B$2006,">="&I$6,Gastos!$B$7:$B$2006,"<"&EDATE(I$6,1),Gastos!$C$7:$C$2006,"Pago proveedor") -> 0 | J9: =SUMIFS(Gastos!$K$7:$K$2006,Gastos!$B$7:$B$2006,">="&J$6,Gastos!$B$7:$B$2006,"<"&EDATE(J$6,1),Gastos!$C$7:$C$2006,"Pago proveedor") -> 0 | ... N9: =SUMIFS(Gastos!$K$7:$K$2006,Gastos!$B$7:$B$2006,">="&N$6,Gastos!$B$7:$B$2006,"<"&EDATE(N$6,1),Gastos!$C$7:$C$2006,"Pago proveedor") -> 0 | O9: =SUM(C9:N9) -> 0
B10: ISR pagado | C10: =SUMIFS(Gastos!$K$7:$K$2006,Gastos!$B$7:$B$2006,">="&C$6,Gastos!$B$7:$B$2006,"<"&EDATE(C$6,1),Gastos!$C$7:$C$2006,"Pago ISR") -> 0 | D10: =SUMIFS(Gastos!$K$7:$K$2006,Gastos!$B$7:$B$2006,">="&D$6,Gastos!$B$7:$B$2006,"<"&EDATE(D$6,1),Gastos!$C$7:$C$2006,"Pago ISR") -> 0 | E10: =SUMIFS(Gastos!$K$7:$K$2006,Gastos!$B$7:$B$2006,">="&E$6,Gastos!$B$7:$B$2006,"<"&EDATE(E$6,1),Gastos!$C$7:$C$2006,"Pago ISR") -> 0 | F10: =SUMIFS(Gastos!$K$7:$K$2006,Gastos!$B$7:$B$2006,">="&F$6,Gastos!$B$7:$B$2006,"<"&EDATE(F$6,1),Gastos!$C$7:$C$2006,"Pago ISR") -> 0 | G10: =SUMIFS(Gastos!$K$7:$K$2006,Gastos!$B$7:$B$2006,">="&G$6,Gastos!$B$7:$B$2006,"<"&EDATE(G$6,1),Gastos!$C$7:$C$2006,"Pago ISR") -> 0 | H10: =SUMIFS(Gastos!$K$7:$K$2006,Gastos!$B$7:$B$2006,">="&H$6,Gastos!$B$7:$B$2006,"<"&EDATE(H$6,1),Gastos!$C$7:$C$2006,"Pago ISR") -> 0 | I10: =SUMIFS(Gastos!$K$7:$K$2006,Gastos!$B$7:$B$2006,">="&I$6,Gastos!$B$7:$B$2006,"<"&EDATE(I$6,1),Gastos!$C$7:$C$2006,"Pago ISR") -> 0 | J10: =SUMIFS(Gastos!$K$7:$K$2006,Gastos!$B$7:$B$2006,">="&J$6,Gastos!$B$7:$B$2006,"<"&EDATE(J$6,1),Gastos!$C$7:$C$2006,"Pago ISR") -> 0 | ... N10: =SUMIFS(Gastos!$K$7:$K$2006,Gastos!$B$7:$B$2006,">="&N$6,Gastos!$B$7:$B$2006,"<"&EDATE(N$6,1),Gastos!$C$7:$C$2006,"Pago ISR") -> 0 | O10: =SUM(C10:N10) -> 0
B11: IVA pagado | C11: =SUMIFS(Gastos!$K$7:$K$2006,Gastos!$B$7:$B$2006,">="&C$6,Gastos!$B$7:$B$2006,"<"&EDATE(C$6,1),Gastos!$C$7:$C$2006,"Pago IVA") -> 0 | D11: =SUMIFS(Gastos!$K$7:$K$2006,Gastos!$B$7:$B$2006,">="&D$6,Gastos!$B$7:$B$2006,"<"&EDATE(D$6,1),Gastos!$C$7:$C$2006,"Pago IVA") -> 0 | E11: =SUMIFS(Gastos!$K$7:$K$2006,Gastos!$B$7:$B$2006,">="&E$6,Gastos!$B$7:$B$2006,"<"&EDATE(E$6,1),Gastos!$C$7:$C$2006,"Pago IVA") -> 0 | F11: =SUMIFS(Gastos!$K$7:$K$2006,Gastos!$B$7:$B$2006,">="&F$6,Gastos!$B$7:$B$2006,"<"&EDATE(F$6,1),Gastos!$C$7:$C$2006,"Pago IVA") -> 0 | G11: =SUMIFS(Gastos!$K$7:$K$2006,Gastos!$B$7:$B$2006,">="&G$6,Gastos!$B$7:$B$2006,"<"&EDATE(G$6,1),Gastos!$C$7:$C$2006,"Pago IVA") -> 0 | H11: =SUMIFS(Gastos!$K$7:$K$2006,Gastos!$B$7:$B$2006,">="&H$6,Gastos!$B$7:$B$2006,"<"&EDATE(H$6,1),Gastos!$C$7:$C$2006,"Pago IVA") -> 0 | I11: =SUMIFS(Gastos!$K$7:$K$2006,Gastos!$B$7:$B$2006,">="&I$6,Gastos!$B$7:$B$2006,"<"&EDATE(I$6,1),Gastos!$C$7:$C$2006,"Pago IVA") -> 0 | J11: =SUMIFS(Gastos!$K$7:$K$2006,Gastos!$B$7:$B$2006,">="&J$6,Gastos!$B$7:$B$2006,"<"&EDATE(J$6,1),Gastos!$C$7:$C$2006,"Pago IVA") -> 0 | ... N11: =SUMIFS(Gastos!$K$7:$K$2006,Gastos!$B$7:$B$2006,">="&N$6,Gastos!$B$7:$B$2006,"<"&EDATE(N$6,1),Gastos!$C$7:$C$2006,"Pago IVA") -> 0 | O11: =SUM(C11:N11) -> 0
B12: Flujo operativo | C12: =C7+C8-SUM(C9:C11) -> 2200 | D12: =D7+D8-SUM(D9:D11) -> 0 | E12: =E7+E8-SUM(E9:E11) -> 0 | F12: =F7+F8-SUM(F9:F11) -> 0 | G12: =G7+G8-SUM(G9:G11) -> 0 | H12: =H7+H8-SUM(H9:H11) -> 0 | I12: =I7+I8-SUM(I9:I11) -> 0 | J12: =J7+J8-SUM(J9:J11) -> 0 | ... N12: =N7+N8-SUM(N9:N11) -> 0 | O12: =SUM(C12:N12) -> 2200
B14: Pagos de activos | C14: =SUMIFS(Gastos!$K$7:$K$2006,Gastos!$B$7:$B$2006,">="&C$6,Gastos!$B$7:$B$2006,"<"&EDATE(C$6,1),Gastos!$C$7:$C$2006,"Pago activo") -> 0 | D14: =SUMIFS(Gastos!$K$7:$K$2006,Gastos!$B$7:$B$2006,">="&D$6,Gastos!$B$7:$B$2006,"<"&EDATE(D$6,1),Gastos!$C$7:$C$2006,"Pago activo") -> 0 | E14: =SUMIFS(Gastos!$K$7:$K$2006,Gastos!$B$7:$B$2006,">="&E$6,Gastos!$B$7:$B$2006,"<"&EDATE(E$6,1),Gastos!$C$7:$C$2006,"Pago activo") -> 0 | F14: =SUMIFS(Gastos!$K$7:$K$2006,Gastos!$B$7:$B$2006,">="&F$6,Gastos!$B$7:$B$2006,"<"&EDATE(F$6,1),Gastos!$C$7:$C$2006,"Pago activo") -> 0 | G14: =SUMIFS(Gastos!$K$7:$K$2006,Gastos!$B$7:$B$2006,">="&G$6,Gastos!$B$7:$B$2006,"<"&EDATE(G$6,1),Gastos!$C$7:$C$2006,"Pago activo") -> 0 | H14: =SUMIFS(Gastos!$K$7:$K$2006,Gastos!$B$7:$B$2006,">="&H$6,Gastos!$B$7:$B$2006,"<"&EDATE(H$6,1),Gastos!$C$7:$C$2006,"Pago activo") -> 0 | I14: =SUMIFS(Gastos!$K$7:$K$2006,Gastos!$B$7:$B$2006,">="&I$6,Gastos!$B$7:$B$2006,"<"&EDATE(I$6,1),Gastos!$C$7:$C$2006,"Pago activo") -> 0 | J14: =SUMIFS(Gastos!$K$7:$K$2006,Gastos!$B$7:$B$2006,">="&J$6,Gastos!$B$7:$B$2006,"<"&EDATE(J$6,1),Gastos!$C$7:$C$2006,"Pago activo") -> 0 | ... N14: =SUMIFS(Gastos!$K$7:$K$2006,Gastos!$B$7:$B$2006,">="&N$6,Gastos!$B$7:$B$2006,"<"&EDATE(N$6,1),Gastos!$C$7:$C$2006,"Pago activo") -> 0 | O14: =SUM(C14:N14) -> 0
B15: Flujo de inversión | C15: =-C14 -> 0 | D15: =-D14 -> 0 | E15: =-E14 -> 0 | F15: =-F14 -> 0 | G15: =-G14 -> 0 | H15: =-H14 -> 0 | I15: =-I14 -> 0 | J15: =-J14 -> 0 | ... N15: =-N14 -> 0 | O15: =SUM(C15:N15) -> 0
B17: Préstamos recibidos | C17: =SUMIFS(Pasivos!$G$7:$G$506,Pasivos!$B$7:$B$506,">="&C$6,Pasivos!$B$7:$B$506,"<"&EDATE(C$6,1),Pasivos!$C$7:$C$506,"Desembolso") -> 0 | D17: =SUMIFS(Pasivos!$G$7:$G$506,Pasivos!$B$7:$B$506,">="&D$6,Pasivos!$B$7:$B$506,"<"&EDATE(D$6,1),Pasivos!$C$7:$C$506,"Desembolso") -> 0 | E17: =SUMIFS(Pasivos!$G$7:$G$506,Pasivos!$B$7:$B$506,">="&E$6,Pasivos!$B$7:$B$506,"<"&EDATE(E$6,1),Pasivos!$C$7:$C$506,"Desembolso") -> 0 | F17: =SUMIFS(Pasivos!$G$7:$G$506,Pasivos!$B$7:$B$506,">="&F$6,Pasivos!$B$7:$B$506,"<"&EDATE(F$6,1),Pasivos!$C$7:$C$506,"Desembolso") -> 0 | G17: =SUMIFS(Pasivos!$G$7:$G$506,Pasivos!$B$7:$B$506,">="&G$6,Pasivos!$B$7:$B$506,"<"&EDATE(G$6,1),Pasivos!$C$7:$C$506,"Desembolso") -> 0 | H17: =SUMIFS(Pasivos!$G$7:$G$506,Pasivos!$B$7:$B$506,">="&H$6,Pasivos!$B$7:$B$506,"<"&EDATE(H$6,1),Pasivos!$C$7:$C$506,"Desembolso") -> 0 | I17: =SUMIFS(Pasivos!$G$7:$G$506,Pasivos!$B$7:$B$506,">="&I$6,Pasivos!$B$7:$B$506,"<"&EDATE(I$6,1),Pasivos!$C$7:$C$506,"Desembolso") -> 0 | J17: =SUMIFS(Pasivos!$G$7:$G$506,Pasivos!$B$7:$B$506,">="&J$6,Pasivos!$B$7:$B$506,"<"&EDATE(J$6,1),Pasivos!$C$7:$C$506,"Desembolso") -> 0 | ... N17: =SUMIFS(Pasivos!$G$7:$G$506,Pasivos!$B$7:$B$506,">="&N$6,Pasivos!$B$7:$B$506,"<"&EDATE(N$6,1),Pasivos!$C$7:$C$506,"Desembolso") -> 0 | O17: =SUM(C17:N17) -> 0
B18: Amortización de capital | C18: =SUMIFS(Pasivos!$G$7:$G$506,Pasivos!$B$7:$B$506,">="&C$6,Pasivos!$B$7:$B$506,"<"&EDATE(C$6,1),Pasivos!$C$7:$C$506,"Amortización") -> 0 | D18: =SUMIFS(Pasivos!$G$7:$G$506,Pasivos!$B$7:$B$506,">="&D$6,Pasivos!$B$7:$B$506,"<"&EDATE(D$6,1),Pasivos!$C$7:$C$506,"Amortización") -> 0 | E18: =SUMIFS(Pasivos!$G$7:$G$506,Pasivos!$B$7:$B$506,">="&E$6,Pasivos!$B$7:$B$506,"<"&EDATE(E$6,1),Pasivos!$C$7:$C$506,"Amortización") -> 0 | F18: =SUMIFS(Pasivos!$G$7:$G$506,Pasivos!$B$7:$B$506,">="&F$6,Pasivos!$B$7:$B$506,"<"&EDATE(F$6,1),Pasivos!$C$7:$C$506,"Amortización") -> 0 | G18: =SUMIFS(Pasivos!$G$7:$G$506,Pasivos!$B$7:$B$506,">="&G$6,Pasivos!$B$7:$B$506,"<"&EDATE(G$6,1),Pasivos!$C$7:$C$506,"Amortización") -> 0 | H18: =SUMIFS(Pasivos!$G$7:$G$506,Pasivos!$B$7:$B$506,">="&H$6,Pasivos!$B$7:$B$506,"<"&EDATE(H$6,1),Pasivos!$C$7:$C$506,"Amortización") -> 0 | I18: =SUMIFS(Pasivos!$G$7:$G$506,Pasivos!$B$7:$B$506,">="&I$6,Pasivos!$B$7:$B$506,"<"&EDATE(I$6,1),Pasivos!$C$7:$C$506,"Amortización") -> 0 | J18: =SUMIFS(Pasivos!$G$7:$G$506,Pasivos!$B$7:$B$506,">="&J$6,Pasivos!$B$7:$B$506,"<"&EDATE(J$6,1),Pasivos!$C$7:$C$506,"Amortización") -> 0 | ... N18: =SUMIFS(Pasivos!$G$7:$G$506,Pasivos!$B$7:$B$506,">="&N$6,Pasivos!$B$7:$B$506,"<"&EDATE(N$6,1),Pasivos!$C$7:$C$506,"Amortización") -> 0 | O18: =SUM(C18:N18) -> 0
B19: Aportaciones familiares / socios | C19: =SUMIFS(Gastos!$K$7:$K$2006,Gastos!$B$7:$B$2006,">="&C$6,Gastos!$B$7:$B$2006,"<"&EDATE(C$6,1),Gastos!$C$7:$C$2006,"Aportación") -> 0 | D19: =SUMIFS(Gastos!$K$7:$K$2006,Gastos!$B$7:$B$2006,">="&D$6,Gastos!$B$7:$B$2006,"<"&EDATE(D$6,1),Gastos!$C$7:$C$2006,"Aportación") -> 0 | E19: =SUMIFS(Gastos!$K$7:$K$2006,Gastos!$B$7:$B$2006,">="&E$6,Gastos!$B$7:$B$2006,"<"&EDATE(E$6,1),Gastos!$C$7:$C$2006,"Aportación") -> 0 | F19: =SUMIFS(Gastos!$K$7:$K$2006,Gastos!$B$7:$B$2006,">="&F$6,Gastos!$B$7:$B$2006,"<"&EDATE(F$6,1),Gastos!$C$7:$C$2006,"Aportación") -> 0 | G19: =SUMIFS(Gastos!$K$7:$K$2006,Gastos!$B$7:$B$2006,">="&G$6,Gastos!$B$7:$B$2006,"<"&EDATE(G$6,1),Gastos!$C$7:$C$2006,"Aportación") -> 0 | H19: =SUMIFS(Gastos!$K$7:$K$2006,Gastos!$B$7:$B$2006,">="&H$6,Gastos!$B$7:$B$2006,"<"&EDATE(H$6,1),Gastos!$C$7:$C$2006,"Aportación") -> 0 | I19: =SUMIFS(Gastos!$K$7:$K$2006,Gastos!$B$7:$B$2006,">="&I$6,Gastos!$B$7:$B$2006,"<"&EDATE(I$6,1),Gastos!$C$7:$C$2006,"Aportación") -> 0 | J19: =SUMIFS(Gastos!$K$7:$K$2006,Gastos!$B$7:$B$2006,">="&J$6,Gastos!$B$7:$B$2006,"<"&EDATE(J$6,1),Gastos!$C$7:$C$2006,"Aportación") -> 0 | ... N19: =SUMIFS(Gastos!$K$7:$K$2006,Gastos!$B$7:$B$2006,">="&N$6,Gastos!$B$7:$B$2006,"<"&EDATE(N$6,1),Gastos!$C$7:$C$2006,"Aportación") -> 0 | O19: =SUM(C19:N19) -> 0
B20: Retiros familiares / distribuciones | C20: =SUMIFS(Gastos!$K$7:$K$2006,Gastos!$B$7:$B$2006,">="&C$6,Gastos!$B$7:$B$2006,"<"&EDATE(C$6,1),Gastos!$C$7:$C$2006,"Retiro familiar") -> 0 | D20: =SUMIFS(Gastos!$K$7:$K$2006,Gastos!$B$7:$B$2006,">="&D$6,Gastos!$B$7:$B$2006,"<"&EDATE(D$6,1),Gastos!$C$7:$C$2006,"Retiro familiar") -> 0 | E20: =SUMIFS(Gastos!$K$7:$K$2006,Gastos!$B$7:$B$2006,">="&E$6,Gastos!$B$7:$B$2006,"<"&EDATE(E$6,1),Gastos!$C$7:$C$2006,"Retiro familiar") -> 0 | F20: =SUMIFS(Gastos!$K$7:$K$2006,Gastos!$B$7:$B$2006,">="&F$6,Gastos!$B$7:$B$2006,"<"&EDATE(F$6,1),Gastos!$C$7:$C$2006,"Retiro familiar") -> 0 | G20: =SUMIFS(Gastos!$K$7:$K$2006,Gastos!$B$7:$B$2006,">="&G$6,Gastos!$B$7:$B$2006,"<"&EDATE(G$6,1),Gastos!$C$7:$C$2006,"Retiro familiar") -> 0 | H20: =SUMIFS(Gastos!$K$7:$K$2006,Gastos!$B$7:$B$2006,">="&H$6,Gastos!$B$7:$B$2006,"<"&EDATE(H$6,1),Gastos!$C$7:$C$2006,"Retiro familiar") -> 0 | I20: =SUMIFS(Gastos!$K$7:$K$2006,Gastos!$B$7:$B$2006,">="&I$6,Gastos!$B$7:$B$2006,"<"&EDATE(I$6,1),Gastos!$C$7:$C$2006,"Retiro familiar") -> 0 | J20: =SUMIFS(Gastos!$K$7:$K$2006,Gastos!$B$7:$B$2006,">="&J$6,Gastos!$B$7:$B$2006,"<"&EDATE(J$6,1),Gastos!$C$7:$C$2006,"Retiro familiar") -> 0 | ... N20: =SUMIFS(Gastos!$K$7:$K$2006,Gastos!$B$7:$B$2006,">="&N$6,Gastos!$B$7:$B$2006,"<"&EDATE(N$6,1),Gastos!$C$7:$C$2006,"Retiro familiar") -> 0 | O20: =SUM(C20:N20) -> 0
B21: Flujo de financiamiento | C21: =C17-C18+C19-C20 -> 0 | D21: =D17-D18+D19-D20 -> 0 | E21: =E17-E18+E19-E20 -> 0 | F21: =F17-F18+F19-F20 -> 0 | G21: =G17-G18+G19-G20 -> 0 | H21: =H17-H18+H19-H20 -> 0 | I21: =I17-I18+I19-I20 -> 0 | J21: =J17-J18+J19-J20 -> 0 | ... N21: =N17-N18+N19-N20 -> 0 | O21: =SUM(C21:N21) -> 0
B23: Cambio neto de efectivo | C23: =C12+C15+C21 -> 2200 | D23: =D12+D15+D21 -> 0 | E23: =E12+E15+E21 -> 0 | F23: =F12+F15+F21 -> 0 | G23: =G12+G15+G21 -> 0 | H23: =H12+H15+H21 -> 0 | I23: =I12+I15+I21 -> 0 | J23: =J12+J15+J21 -> 0 | ... N23: =N12+N15+N21 -> 0 | O23: =SUM(C23:N23) -> 2200
B24: Efectivo inicial | C24: =Configuración!$C$9 -> 0 | D24: =C25 -> 2200 | E24: =D25 -> 2200 | F24: =E25 -> 2200 | G24: =F25 -> 2200 | H24: =G25 -> 2200 | I24: =H25 -> 2200 | J24: =I25 -> 2200 | K24: =J25 -> 2200 | ... N24: =M25 -> 2200 | O24: =C24 -> 0
B25: Efectivo final | C25: =C24+C23 -> 2200 | D25: =D24+D23 -> 2200 | E25: =E24+E23 -> 2200 | F25: =F24+F23 -> 2200 | G25: =G24+G23 -> 2200 | H25: =H24+H23 -> 2200 | I25: =I24+I23 -> 2200 | J25: =J24+J23 -> 2200 | ... N25: =N24+N23 -> 2200 | O25: =N25 -> 2200
B27: Remuneraciones familiares pagadas* | C27: =SUMIFS(Gastos!$K$7:$K$2006,Gastos!$B$7:$B$2006,">="&C$6,Gastos!$B$7:$B$2006,"<"&EDATE(C$6,1),Gastos!$C$7:$C$2006,"Pago proveedor",Gastos!$F$7:$F$2006,"Sí") -> 0 | D27: =SUMIFS(Gastos!$K$7:$K$2006,Gastos!$B$7:$B$2006,">="&D$6,Gastos!$B$7:$B$2006,"<"&EDATE(D$6,1),Gastos!$C$7:$C$2006,"Pago proveedor",Gastos!$F$7:$F$2006,"Sí") -> 0 | E27: =SUMIFS(Gastos!$K$7:$K$2006,Gastos!$B$7:$B$2006,">="&E$6,Gastos!$B$7:$B$2006,"<"&EDATE(E$6,1),Gastos!$C$7:$C$2006,"Pago proveedor",Gastos!$F$7:$F$2006,"Sí") -> 0 | F27: =SUMIFS(Gastos!$K$7:$K$2006,Gastos!$B$7:$B$2006,">="&F$6,Gastos!$B$7:$B$2006,"<"&EDATE(F$6,1),Gastos!$C$7:$C$2006,"Pago proveedor",Gastos!$F$7:$F$2006,"Sí") -> 0 | G27: =SUMIFS(Gastos!$K$7:$K$2006,Gastos!$B$7:$B$2006,">="&G$6,Gastos!$B$7:$B$2006,"<"&EDATE(G$6,1),Gastos!$C$7:$C$2006,"Pago proveedor",Gastos!$F$7:$F$2006,"Sí") -> 0 | H27: =SUMIFS(Gastos!$K$7:$K$2006,Gastos!$B$7:$B$2006,">="&H$6,Gastos!$B$7:$B$2006,"<"&EDATE(H$6,1),Gastos!$C$7:$C$2006,"Pago proveedor",Gastos!$F$7:$F$2006,"Sí") -> 0 | I27: =SUMIFS(Gastos!$K$7:$K$2006,Gastos!$B$7:$B$2006,">="&I$6,Gastos!$B$7:$B$2006,"<"&EDATE(I$6,1),Gastos!$C$7:$C$2006,"Pago proveedor",Gastos!$F$7:$F$2006,"Sí") -> 0 | J27: =SUMIFS(Gastos!$K$7:$K$2006,Gastos!$B$7:$B$2006,">="&J$6,Gastos!$B$7:$B$2006,"<"&EDATE(J$6,1),Gastos!$C$7:$C$2006,"Pago proveedor",Gastos!$F$7:$F$2006,"Sí") -> 0 | ... N27: =SUMIFS(Gastos!$K$7:$K$2006,Gastos!$B$7:$B$2006,">="&N$6,Gastos!$B$7:$B$2006,"<"&EDATE(N$6,1),Gastos!$C$7:$C$2006,"Pago proveedor",Gastos!$F$7:$F$2006,"Sí") -> 0 | O27: =SUM(C27:N27) -> 0
B29: *Parte de pagos a proveedores; no sumar de nuevo.

Sheet KPIs
B2: KPIs
B4: MXN · enero a diciembre
B6: Concepto | C6: =DATE(Configuración!$C$5,1,1) -> 46023 | D6: =DATE(Configuración!$C$5,2,1) -> 46054 | E6: =DATE(Configuración!$C$5,3,1) -> 46082 | F6: =DATE(Configuración!$C$5,4,1) -> 46113 | G6: =DATE(Configuración!$C$5,5,1) -> 46143 | H6: =DATE(Configuración!$C$5,6,1) -> 46174 | I6: =DATE(Configuración!$C$5,7,1) -> 46204 | J6: =DATE(Configuración!$C$5,8,1) -> 46235 | K6: =DATE(Configuración!$C$5,9,1) -> 46266 | L6: =DATE(Configuración!$C$5,10,1) -> 46296 | M6: =DATE(Configuración!$C$5,11,1) -> 46327 | N6: =DATE(Configuración!$C$5,12,1) -> 46357 | O6: Total anual
B7: Ingresos por servicios | C7: ='Estado de Resultados'!C14 -> 2200 | D7: ='Estado de Resultados'!D14 -> 0 | E7: ='Estado de Resultados'!E14 -> 0 | F7: ='Estado de Resultados'!F14 -> 0 | G7: ='Estado de Resultados'!G14 -> 0 | H7: ='Estado de Resultados'!H14 -> 0 | I7: ='Estado de Resultados'!I14 -> 0 | J7: ='Estado de Resultados'!J14 -> 0 | ... O7: ='Estado de Resultados'!O14 -> 2200
B8: Utilidad neta | C8: ='Estado de Resultados'!C33 -> 2200 | D8: ='Estado de Resultados'!D33 -> 0 | E8: ='Estado de Resultados'!E33 -> 0 | F8: ='Estado de Resultados'!F33 -> 0 | G8: ='Estado de Resultados'!G33 -> 0 | H8: ='Estado de Resultados'!H33 -> 0 | I8: ='Estado de Resultados'!I33 -> 0 | J8: ='Estado de Resultados'!J33 -> 0 | ... O8: ='Estado de Resultados'!O33 -> 2200
B9: Margen bruto | C9: =IF(C7=0,"n.d.",'Estado de Resultados'!C17/C7) -> 1 | D9: =IF(D7=0,"n.d.",'Estado de Resultados'!D17/D7) -> n.d. | E9: =IF(E7=0,"n.d.",'Estado de Resultados'!E17/E7) -> n.d. | F9: =IF(F7=0,"n.d.",'Estado de Resultados'!F17/F7) -> n.d. | G9: =IF(G7=0,"n.d.",'Estado de Resultados'!G17/G7) -> n.d. | H9: =IF(H7=0,"n.d.",'Estado de Resultados'!H17/H7) -> n.d. | I9: =IF(I7=0,"n.d.",'Estado de Resultados'!I17/I7) -> n.d. | J9: =IF(J7=0,"n.d.",'Estado de Resultados'!J17/J7) -> n.d. | ... O9: =IF(O7=0,"n.d.",'Estado de Resultados'!O17/O7) -> 1
B10: Margen operativo | C10: =IF(C7=0,"n.d.",'Estado de Resultados'!C29/C7) -> 1 | D10: =IF(D7=0,"n.d.",'Estado de Resultados'!D29/D7) -> n.d. | E10: =IF(E7=0,"n.d.",'Estado de Resultados'!E29/E7) -> n.d. | F10: =IF(F7=0,"n.d.",'Estado de Resultados'!F29/F7) -> n.d. | G10: =IF(G7=0,"n.d.",'Estado de Resultados'!G29/G7) -> n.d. | H10: =IF(H7=0,"n.d.",'Estado de Resultados'!H29/H7) -> n.d. | I10: =IF(I7=0,"n.d.",'Estado de Resultados'!I29/I7) -> n.d. | J10: =IF(J7=0,"n.d.",'Estado de Resultados'!J29/J7) -> n.d. | ... O10: =IF(O7=0,"n.d.",'Estado de Resultados'!O29/O7) -> 1
B11: Margen neto | C11: =IF(C7=0,"n.d.",C8/C7) -> 1 | D11: =IF(D7=0,"n.d.",D8/D7) -> n.d. | E11: =IF(E7=0,"n.d.",E8/E7) -> n.d. | F11: =IF(F7=0,"n.d.",F8/F7) -> n.d. | G11: =IF(G7=0,"n.d.",G8/G7) -> n.d. | H11: =IF(H7=0,"n.d.",H8/H7) -> n.d. | I11: =IF(I7=0,"n.d.",I8/I7) -> n.d. | J11: =IF(J7=0,"n.d.",J8/J7) -> n.d. | ... O11: =IF(O7=0,"n.d.",O8/O7) -> 1
B12: Sesiones prestadas | C12: =SUMIFS(Ingresos!$I$7:$I$2006,Ingresos!$B$7:$B$2006,">="&C$6,Ingresos!$B$7:$B$2006,"<"&EDATE(C$6,1),Ingresos!$C$7:$C$2006,"Servicio") -> 2 | D12: =SUMIFS(Ingresos!$I$7:$I$2006,Ingresos!$B$7:$B$2006,">="&D$6,Ingresos!$B$7:$B$2006,"<"&EDATE(D$6,1),Ingresos!$C$7:$C$2006,"Servicio") -> 0 | E12: =SUMIFS(Ingresos!$I$7:$I$2006,Ingresos!$B$7:$B$2006,">="&E$6,Ingresos!$B$7:$B$2006,"<"&EDATE(E$6,1),Ingresos!$C$7:$C$2006,"Servicio") -> 0 | F12: =SUMIFS(Ingresos!$I$7:$I$2006,Ingresos!$B$7:$B$2006,">="&F$6,Ingresos!$B$7:$B$2006,"<"&EDATE(F$6,1),Ingresos!$C$7:$C$2006,"Servicio") -> 0 | G12: =SUMIFS(Ingresos!$I$7:$I$2006,Ingresos!$B$7:$B$2006,">="&G$6,Ingresos!$B$7:$B$2006,"<"&EDATE(G$6,1),Ingresos!$C$7:$C$2006,"Servicio") -> 0 | H12: =SUMIFS(Ingresos!$I$7:$I$2006,Ingresos!$B$7:$B$2006,">="&H$6,Ingresos!$B$7:$B$2006,"<"&EDATE(H$6,1),Ingresos!$C$7:$C$2006,"Servicio") -> 0 | I12: =SUMIFS(Ingresos!$I$7:$I$2006,Ingresos!$B$7:$B$2006,">="&I$6,Ingresos!$B$7:$B$2006,"<"&EDATE(I$6,1),Ingresos!$C$7:$C$2006,"Servicio") -> 0 | J12: =SUMIFS(Ingresos!$I$7:$I$2006,Ingresos!$B$7:$B$2006,">="&J$6,Ingresos!$B$7:$B$2006,"<"&EDATE(J$6,1),Ingresos!$C$7:$C$2006,"Servicio") -> 0 | ... N12: =SUMIFS(Ingresos!$I$7:$I$2006,Ingresos!$B$7:$B$2006,">="&N$6,Ingresos!$B$7:$B$2006,"<"&EDATE(N$6,1),Ingresos!$C$7:$C$2006,"Servicio") -> 0 | O12: =SUM(C12:N12) -> 2
B13: Ingreso por sesión (MXN) | C13: =IF(C12=0,"n.d.",C7/C12) -> 1100 | D13: =IF(D12=0,"n.d.",D7/D12) -> n.d. | E13: =IF(E12=0,"n.d.",E7/E12) -> n.d. | F13: =IF(F12=0,"n.d.",F7/F12) -> n.d. | G13: =IF(G12=0,"n.d.",G7/G12) -> n.d. | H13: =IF(H12=0,"n.d.",H7/H12) -> n.d. | I13: =IF(I12=0,"n.d.",I7/I12) -> n.d. | J13: =IF(J12=0,"n.d.",J7/J12) -> n.d. | ... O13: =IF(O12=0,"n.d.",O7/O12) -> 1100
B14: Flujo operativo | C14: ='Flujo de Efectivo'!C12 -> 2200 | D14: ='Flujo de Efectivo'!D12 -> 0 | E14: ='Flujo de Efectivo'!E12 -> 0 | F14: ='Flujo de Efectivo'!F12 -> 0 | G14: ='Flujo de Efectivo'!G12 -> 0 | H14: ='Flujo de Efectivo'!H12 -> 0 | I14: ='Flujo de Efectivo'!I12 -> 0 | J14: ='Flujo de Efectivo'!J12 -> 0 | ... O14: ='Flujo de Efectivo'!O12 -> 2200
B15: Efectivo al cierre | C15: ='Balance General'!C7 -> 2200 | D15: ='Balance General'!D7 -> 2200 | E15: ='Balance General'!E7 -> 2200 | F15: ='Balance General'!F7 -> 2200 | G15: ='Balance General'!G7 -> 2200 | H15: ='Balance General'!H7 -> 2200 | I15: ='Balance General'!I7 -> 2200 | J15: ='Balance General'!J7 -> 2200 | ... N15: ='Balance General'!N7 -> 2200 | O15: ='Balance General'!N7 -> 2200
B16: Capital de trabajo | C16: ='Balance General'!C12-'Balance General'!C24 -> 2200 | D16: ='Balance General'!D12-'Balance General'!D24 -> 2200 | E16: ='Balance General'!E12-'Balance General'!E24 -> 2200 | F16: ='Balance General'!F12-'Balance General'!F24 -> 2200 | G16: ='Balance General'!G12-'Balance General'!G24 -> 2200 | H16: ='Balance General'!H12-'Balance General'!H24 -> 2200 | I16: ='Balance General'!I12-'Balance General'!I24 -> 2200 | J16: ='Balance General'!J12-'Balance General'!J24 -> 2200 | ... N16: ='Balance General'!N12-'Balance General'!N24 -> 2200 | O16: ='Balance General'!N12-'Balance General'!N24 -> 2200
B17: Razón circulante | C17: =IF('Balance General'!C24=0,"n.d.",'Balance General'!C12/'Balance General'!C24) -> n.d. | D17: =IF('Balance General'!D24=0,"n.d.",'Balance General'!D12/'Balance General'!D24) -> n.d. | E17: =IF('Balance General'!E24=0,"n.d.",'Balance General'!E12/'Balance General'!E24) -> n.d. | F17: =IF('Balance General'!F24=0,"n.d.",'Balance General'!F12/'Balance General'!F24) -> n.d. | G17: =IF('Balance General'!G24=0,"n.d.",'Balance General'!G12/'Balance General'!G24) -> n.d. | H17: =IF('Balance General'!H24=0,"n.d.",'Balance General'!H12/'Balance General'!H24) -> n.d. | I17: =IF('Balance General'!I24=0,"n.d.",'Balance General'!I12/'Balance General'!I24) -> n.d. | J17: =IF('Balance General'!J24=0,"n.d.",'Balance General'!J12/'Balance General'!J24) -> n.d. | ... N17: =IF('Balance General'!N24=0,"n.d.",'Balance General'!N12/'Balance General'!N24) -> n.d. | O17: =IF('Balance General'!N24=0,"n.d.",'Balance General'!N12/'Balance General'!N24) -> n.d.
B18: Deuda financiera | C18: ='Balance General'!C23+'Balance General'!C25 -> 0 | D18: ='Balance General'!D23+'Balance General'!D25 -> 0 | E18: ='Balance General'!E23+'Balance General'!E25 -> 0 | F18: ='Balance General'!F23+'Balance General'!F25 -> 0 | G18: ='Balance General'!G23+'Balance General'!G25 -> 0 | H18: ='Balance General'!H23+'Balance General'!H25 -> 0 | I18: ='Balance General'!I23+'Balance General'!I25 -> 0 | J18: ='Balance General'!J23+'Balance General'!J25 -> 0 | ... N18: ='Balance General'!N23+'Balance General'!N25 -> 0 | O18: ='Balance General'!N23+'Balance General'!N25 -> 0
B19: Retiros familiares | C19: ='Flujo de Efectivo'!C20 -> 0 | D19: ='Flujo de Efectivo'!D20 -> 0 | E19: ='Flujo de Efectivo'!E20 -> 0 | F19: ='Flujo de Efectivo'!F20 -> 0 | G19: ='Flujo de Efectivo'!G20 -> 0 | H19: ='Flujo de Efectivo'!H20 -> 0 | I19: ='Flujo de Efectivo'!I20 -> 0 | J19: ='Flujo de Efectivo'!J20 -> 0 | ... O19: ='Flujo de Efectivo'!O20 -> 0
B20: Remuneraciones familiares pagadas | C20: ='Flujo de Efectivo'!C27 -> 0 | D20: ='Flujo de Efectivo'!D27 -> 0 | E20: ='Flujo de Efectivo'!E27 -> 0 | F20: ='Flujo de Efectivo'!F27 -> 0 | G20: ='Flujo de Efectivo'!G27 -> 0 | H20: ='Flujo de Efectivo'!H27 -> 0 | I20: ='Flujo de Efectivo'!I27 -> 0 | J20: ='Flujo de Efectivo'!J27 -> 0 | ... O20: ='Flujo de Efectivo'!O27 -> 0
B21: Salida total a la familia | C21: =SUM(C19:C20) -> 0 | D21: =SUM(D19:D20) -> 0 | E21: =SUM(E19:E20) -> 0 | F21: =SUM(F19:F20) -> 0 | G21: =SUM(G19:G20) -> 0 | H21: =SUM(H19:H20) -> 0 | I21: =SUM(I19:I20) -> 0 | J21: =SUM(J19:J20) -> 0 | ... O21: =SUM(O19:O20) -> 0
B22: Retiros / utilidad neta positiva | C22: =IF(C8<=0,"n.d.",C19/C8) -> 0 | D22: =IF(D8<=0,"n.d.",D19/D8) -> n.d. | E22: =IF(E8<=0,"n.d.",E19/E8) -> n.d. | F22: =IF(F8<=0,"n.d.",F19/F8) -> n.d. | G22: =IF(G8<=0,"n.d.",G19/G8) -> n.d. | H22: =IF(H8<=0,"n.d.",H19/H8) -> n.d. | I22: =IF(I8<=0,"n.d.",I19/I8) -> n.d. | J22: =IF(J8<=0,"n.d.",J19/J8) -> n.d. | ... O22: =IF(O8<=0,"n.d.",O19/O8) -> 0
B23: Saldo de cuentas por cobrar | C23: ='Balance General'!C8 -> 0 | D23: ='Balance General'!D8 -> 0 | E23: ='Balance General'!E8 -> 0 | F23: ='Balance General'!F8 -> 0 | G23: ='Balance General'!G8 -> 0 | H23: ='Balance General'!H8 -> 0 | I23: ='Balance General'!I8 -> 0 | J23: ='Balance General'!J8 -> 0 | ... N23: ='Balance General'!N8 -> 0 | O23: ='Balance General'!N8 -> 0
B26: n.d. = sin denominador válido. Razones anuales recalculadas; saldos anuales son de diciembre.
B28: Ingreso por sesión requiere capturar todas las sesiones prestadas, incluidas las de paquetes.

Sheet Ingresos
A2: Ingresos
A4: Servicio reconoce la venta. Cobro registra el banco. Captura ambos aunque ocurran el mismo día.
A6: ID único | B6: Fecha | C6: Tipo de registro | D6: Folio relacionado | E6: Paciente (alias) | F6: Servicio | G6: Base / importe | H6: IVA trasladado | I6: Sesiones prestadas | J6: Nota | K6: Total | L6: Revisión
A7: Ing-001 | B7: 46023 | C7: Servicio | D7: V001 | E7: C130 | F7: TMS | G7: 1100 | H7: 0 | I7: 1 | J7: No notes | K7: =IF(A7="","",G7+H7) -> 1100 | L7: =IF(COUNTA(A7:J7)=0,"",IF(OR(AND(C7<>"Servicio",C7<>"Cobro",C7<>"Anticipo",C7<>"Aplicación anticipo",C7<>"Retención ISR",C7<>"Retención IVA"),AND(C7="Servicio",F7<>"TMS",F7<>"Valoración",F7<>"EEG",F7<>"Neurofeedback",F7<>"Fotobiomodulación",F7<>"Psicoterapia",F7<>"Otros")),"Tipo o categoría inválido",IF(COUNTA(A7:J7)=0,"",IF(OR(A7="",B7="",C7="",G7=""),"Faltan datos",IF(COUNTIF($A$7:$A$2006,A7)>1,"ID duplicado",IF(OR(B7<DATE(Configuración!$C$5,1,1),B7>=DATE(Configuración!$C$5+1,1,1)),"Fecha fuera del año",IF(OR(G7<0,H7<0),"Revisar signo",IF(AND(C7<>"Servicio",H7<>0),"IVA solo en Servicio",IF(AND(C7="Servicio",F7=""),"Falta servicio","OK"))))))))) -> OK
A8: Ing-002 | B8: 46023 | C8: Cobro | D8: V001 | E8: C130 | F8: TMS | G8: 1100 | H8: 0 | I8: 0 | K8: =IF(A8="","",G8+H8) -> 1100 | L8: =IF(COUNTA(A8:J8)=0,"",IF(OR(AND(C8<>"Servicio",C8<>"Cobro",C8<>"Anticipo",C8<>"Aplicación anticipo",C8<>"Retención ISR",C8<>"Retención IVA"),AND(C8="Servicio",F8<>"TMS",F8<>"Valoración",F8<>"EEG",F8<>"Neurofeedback",F8<>"Fotobiomodulación",F8<>"Psicoterapia",F8<>"Otros")),"Tipo o categoría inválido",IF(COUNTA(A8:J8)=0,"",IF(OR(A8="",B8="",C8="",G8=""),"Faltan datos",IF(COUNTIF($A$7:$A$2006,A8)>1,"ID duplicado",IF(OR(B8<DATE(Configuración!$C$5,1,1),B8>=DATE(Configuración!$C$5+1,1,1)),"Fecha fuera del año",IF(OR(G8<0,H8<0),"Revisar signo",IF(AND(C8<>"Servicio",H8<>0),"IVA solo en Servicio",IF(AND(C8="Servicio",F8=""),"Falta servicio","OK"))))))))) -> OK
A9: Ing-003 | B9: 46024 | C9: Servicio | D9: V002 | E9: C126 | F9: TMS | G9: 1100 | H9: 0 | I9: 1 | K9: =IF(A9="","",G9+H9) -> 1100 | L9: =IF(COUNTA(A9:J9)=0,"",IF(OR(AND(C9<>"Servicio",C9<>"Cobro",C9<>"Anticipo",C9<>"Aplicación anticipo",C9<>"Retención ISR",C9<>"Retención IVA"),AND(C9="Servicio",F9<>"TMS",F9<>"Valoración",F9<>"EEG",F9<>"Neurofeedback",F9<>"Fotobiomodulación",F9<>"Psicoterapia",F9<>"Otros")),"Tipo o categoría inválido",IF(COUNTA(A9:J9)=0,"",IF(OR(A9="",B9="",C9="",G9=""),"Faltan datos",IF(COUNTIF($A$7:$A$2006,A9)>1,"ID duplicado",IF(OR(B9<DATE(Configuración!$C$5,1,1),B9>=DATE(Configuración!$C$5+1,1,1)),"Fecha fuera del año",IF(OR(G9<0,H9<0),"Revisar signo",IF(AND(C9<>"Servicio",H9<>0),"IVA solo en Servicio",IF(AND(C9="Servicio",F9=""),"Falta servicio","OK"))))))))) -> OK
A10: Ing-004 | B10: 46024 | C10: Cobro | D10: v002 | E10: C126 | F10: TMS | G10: 1100 | H10: 0 | I10: 0 | K10: =IF(A10="","",G10+H10) -> 1100 | L10: =IF(COUNTA(A10:J10)=0,"",IF(OR(AND(C10<>"Servicio",C10<>"Cobro",C10<>"Anticipo",C10<>"Aplicación anticipo",C10<>"Retención ISR",C10<>"Retención IVA"),AND(C10="Servicio",F10<>"TMS",F10<>"Valoración",F10<>"EEG",F10<>"Neurofeedback",F10<>"Fotobiomodulación",F10<>"Psicoterapia",F10<>"Otros")),"Tipo o categoría inválido",IF(COUNTA(A10:J10)=0,"",IF(OR(A10="",B10="",C10="",G10=""),"Faltan datos",IF(COUNTIF($A$7:$A$2006,A10)>1,"ID duplicado",IF(OR(B10<DATE(Configuración!$C$5,1,1),B10>=DATE(Configuración!$C$5+1,1,1)),"Fecha fuera del año",IF(OR(G10<0,H10<0),"Revisar signo",IF(AND(C10<>"Servicio",H10<>0),"IVA solo en Servicio",IF(AND(C10="Servicio",F10=""),"Falta servicio","OK"))))))))) -> OK
K11: =IF(A11="","",G11+H11) | L11: =IF(COUNTA(A11:J11)=0,"",IF(OR(AND(C11<>"Servicio",C11<>"Cobro",C11<>"Anticipo",C11<>"Aplicación anticipo",C11<>"Retención ISR",C11<>"Retención IVA"),AND(C11="Servicio",F11<>"TMS",F11<>"Valoración",F11<>"EEG",F11<>"Neurofeedback",F11<>"Fotobiomodulación",F11<>"Psicoterapia",F11<>"Otros")),"Tipo o categoría inválido",IF(COUNTA(A11:J11)=0,"",IF(OR(A11="",B11="",C11="",G11=""),"Faltan datos",IF(COUNTIF($A$7:$A$2006,A11)>1,"ID duplicado",IF(OR(B11<DATE(Configuración!$C$5,1,1),B11>=DATE(Configuración!$C$5+1,1,1)),"Fecha fuera del año",IF(OR(G11<0,H11<0),"Revisar signo",IF(AND(C11<>"Servicio",H11<>0),"IVA solo en Servicio",IF(AND(C11="Servicio",F11=""),"Falta servicio","OK")))))))))
K12: =IF(A12="","",G12+H12) | L12: =IF(COUNTA(A12:J12)=0,"",IF(OR(AND(C12<>"Servicio",C12<>"Cobro",C12<>"Anticipo",C12<>"Aplicación anticipo",C12<>"Retención ISR",C12<>"Retención IVA"),AND(C12="Servicio",F12<>"TMS",F12<>"Valoración",F12<>"EEG",F12<>"Neurofeedback",F12<>"Fotobiomodulación",F12<>"Psicoterapia",F12<>"Otros")),"Tipo o categoría inválido",IF(COUNTA(A12:J12)=0,"",IF(OR(A12="",B12="",C12="",G12=""),"Faltan datos",IF(COUNTIF($A$7:$A$2006,A12)>1,"ID duplicado",IF(OR(B12<DATE(Configuración!$C$5,1,1),B12>=DATE(Configuración!$C$5+1,1,1)),"Fecha fuera del año",IF(OR(G12<0,H12<0),"Revisar signo",IF(AND(C12<>"Servicio",H12<>0),"IVA solo en Servicio",IF(AND(C12="Servicio",F12=""),"Falta servicio","OK")))))))))
K13: =IF(A13="","",G13+H13) | L13: =IF(COUNTA(A13:J13)=0,"",IF(OR(AND(C13<>"Servicio",C13<>"Cobro",C13<>"Anticipo",C13<>"Aplicación anticipo",C13<>"Retención ISR",C13<>"Retención IVA"),AND(C13="Servicio",F13<>"TMS",F13<>"Valoración",F13<>"EEG",F13<>"Neurofeedback",F13<>"Fotobiomodulación",F13<>"Psicoterapia",F13<>"Otros")),"Tipo o categoría inválido",IF(COUNTA(A13:J13)=0,"",IF(OR(A13="",B13="",C13="",G13=""),"Faltan datos",IF(COUNTIF($A$7:$A$2006,A13)>1,"ID duplicado",IF(OR(B13<DATE(Configuración!$C$5,1,1),B13>=DATE(Configuración!$C$5+1,1,1)),"Fecha fuera del año",IF(OR(G13<0,H13<0),"Revisar signo",IF(AND(C13<>"Servicio",H13<>0),"IVA solo en Servicio",IF(AND(C13="Servicio",F13=""),"Falta servicio","OK")))))))))
K14: =IF(A14="","",G14+H14) | L14: =IF(COUNTA(A14:J14)=0,"",IF(OR(AND(C14<>"Servicio",C14<>"Cobro",C14<>"Anticipo",C14<>"Aplicación anticipo",C14<>"Retención ISR",C14<>"Retención IVA"),AND(C14="Servicio",F14<>"TMS",F14<>"Valoración",F14<>"EEG",F14<>"Neurofeedback",F14<>"Fotobiomodulación",F14<>"Psicoterapia",F14<>"Otros")),"Tipo o categoría inválido",IF(COUNTA(A14:J14)=0,"",IF(OR(A14="",B14="",C14="",G14=""),"Faltan datos",IF(COUNTIF($A$7:$A$2006,A14)>1,"ID duplicado",IF(OR(B14<DATE(Configuración!$C$5,1,1),B14>=DATE(Configuración!$C$5+1,1,1)),"Fecha fuera del año",IF(OR(G14<0,H14<0),"Revisar signo",IF(AND(C14<>"Servicio",H14<>0),"IVA solo en Servicio",IF(AND(C14="Servicio",F14=""),"Falta servicio","OK")))))))))
K15: =IF(A15="","",G15+H15) | L15: =IF(COUNTA(A15:J15)=0,"",IF(OR(AND(C15<>"Servicio",C15<>"Cobro",C15<>"Anticipo",C15<>"Aplicación anticipo",C15<>"Retención ISR",C15<>"Retención IVA"),AND(C15="Servicio",F15<>"TMS",F15<>"Valoración",F15<>"EEG",F15<>"Neurofeedback",F15<>"Fotobiomodulación",F15<>"Psicoterapia",F15<>"Otros")),"Tipo o categoría inválido",IF(COUNTA(A15:J15)=0,"",IF(OR(A15="",B15="",C15="",G15=""),"Faltan datos",IF(COUNTIF($A$7:$A$2006,A15)>1,"ID duplicado",IF(OR(B15<DATE(Configuración!$C$5,1,1),B15>=DATE(Configuración!$C$5+1,1,1)),"Fecha fuera del año",IF(OR(G15<0,H15<0),"Revisar signo",IF(AND(C15<>"Servicio",H15<>0),"IVA solo en Servicio",IF(AND(C15="Servicio",F15=""),"Falta servicio","OK")))))))))
K16: =IF(A16="","",G16+H16) | L16: =IF(COUNTA(A16:J16)=0,"",IF(OR(AND(C16<>"Servicio",C16<>"Cobro",C16<>"Anticipo",C16<>"Aplicación anticipo",C16<>"Retención ISR",C16<>"Retención IVA"),AND(C16="Servicio",F16<>"TMS",F16<>"Valoración",F16<>"EEG",F16<>"Neurofeedback",F16<>"Fotobiomodulación",F16<>"Psicoterapia",F16<>"Otros")),"Tipo o categoría inválido",IF(COUNTA(A16:J16)=0,"",IF(OR(A16="",B16="",C16="",G16=""),"Faltan datos",IF(COUNTIF($A$7:$A$2006,A16)>1,"ID duplicado",IF(OR(B16<DATE(Configuración!$C$5,1,1),B16>=DATE(Configuración!$C$5+1,1,1)),"Fecha fuera del año",IF(OR(G16<0,H16<0),"Revisar signo",IF(AND(C16<>"Servicio",H16<>0),"IVA solo en Servicio",IF(AND(C16="Servicio",F16=""),"Falta servicio","OK")))))))))
K17: =IF(A17="","",G17+H17) | L17: =IF(COUNTA(A17:J17)=0,"",IF(OR(AND(C17<>"Servicio",C17<>"Cobro",C17<>"Anticipo",C17<>"Aplicación anticipo",C17<>"Retención ISR",C17<>"Retención IVA"),AND(C17="Servicio",F17<>"TMS",F17<>"Valoración",F17<>"EEG",F17<>"Neurofeedback",F17<>"Fotobiomodulación",F17<>"Psicoterapia",F17<>"Otros")),"Tipo o categoría inválido",IF(COUNTA(A17:J17)=0,"",IF(OR(A17="",B17="",C17="",G17=""),"Faltan datos",IF(COUNTIF($A$7:$A$2006,A17)>1,"ID duplicado",IF(OR(B17<DATE(Configuración!$C$5,1,1),B17>=DATE(Configuración!$C$5+1,1,1)),"Fecha fuera del año",IF(OR(G17<0,H17<0),"Revisar signo",IF(AND(C17<>"Servicio",H17<>0),"IVA solo en Servicio",IF(AND(C17="Servicio",F17=""),"Falta servicio","OK")))))))))
K18: =IF(A18="","",G18+H18) | L18: =IF(COUNTA(A18:J18)=0,"",IF(OR(AND(C18<>"Servicio",C18<>"Cobro",C18<>"Anticipo",C18<>"Aplicación anticipo",C18<>"Retención ISR",C18<>"Retención IVA"),AND(C18="Servicio",F18<>"TMS",F18<>"Valoración",F18<>"EEG",F18<>"Neurofeedback",F18<>"Fotobiomodulación",F18<>"Psicoterapia",F18<>"Otros")),"Tipo o categoría inválido",IF(COUNTA(A18:J18)=0,"",IF(OR(A18="",B18="",C18="",G18=""),"Faltan datos",IF(COUNTIF($A$7:$A$2006,A18)>1,"ID duplicado",IF(OR(B18<DATE(Configuración!$C$5,1,1),B18>=DATE(Configuración!$C$5+1,1,1)),"Fecha fuera del año",IF(OR(G18<0,H18<0),"Revisar signo",IF(AND(C18<>"Servicio",H18<>0),"IVA solo en Servicio",IF(AND(C18="Servicio",F18=""),"Falta servicio","OK")))))))))
K19: =IF(A19="","",G19+H19) | L19: =IF(COUNTA(A19:J19)=0,"",IF(OR(AND(C19<>"Servicio",C19<>"Cobro",C19<>"Anticipo",C19<>"Aplicación anticipo",C19<>"Retención ISR",C19<>"Retención IVA"),AND(C19="Servicio",F19<>"TMS",F19<>"Valoración",F19<>"EEG",F19<>"Neurofeedback",F19<>"Fotobiomodulación",F19<>"Psicoterapia",F19<>"Otros")),"Tipo o categoría inválido",IF(COUNTA(A19:J19)=0,"",IF(OR(A19="",B19="",C19="",G19=""),"Faltan datos",IF(COUNTIF($A$7:$A$2006,A19)>1,"ID duplicado",IF(OR(B19<DATE(Configuración!$C$5,1,1),B19>=DATE(Configuración!$C$5+1,1,1)),"Fecha fuera del año",IF(OR(G19<0,H19<0),"Revisar signo",IF(AND(C19<>"Servicio",H19<>0),"IVA solo en Servicio",IF(AND(C19="Servicio",F19=""),"Falta servicio","OK")))))))))
K20: =IF(A20="","",G20+H20) | L20: =IF(COUNTA(A20:J20)=0,"",IF(OR(AND(C20<>"Servicio",C20<>"Cobro",C20<>"Anticipo",C20<>"Aplicación anticipo",C20<>"Retención ISR",C20<>"Retención IVA"),AND(C20="Servicio",F20<>"TMS",F20<>"Valoración",F20<>"EEG",F20<>"Neurofeedback",F20<>"Fotobiomodulación",F20<>"Psicoterapia",F20<>"Otros")),"Tipo o categoría inválido",IF(COUNTA(A20:J20)=0,"",IF(OR(A20="",B20="",C20="",G20=""),"Faltan datos",IF(COUNTIF($A$7:$A$2006,A20)>1,"ID duplicado",IF(OR(B20<DATE(Configuración!$C$5,1,1),B20>=DATE(Configuración!$C$5+1,1,1)),"Fecha fuera del año",IF(OR(G20<0,H20<0),"Revisar signo",IF(AND(C20<>"Servicio",H20<>0),"IVA solo en Servicio",IF(AND(C20="Servicio",F20=""),"Falta servicio","OK")))))))))
K21: =IF(A21="","",G21+H21) | L21: =IF(COUNTA(A21:J21)=0,"",IF(OR(AND(C21<>"Servicio",C21<>"Cobro",C21<>"Anticipo",C21<>"Aplicación anticipo",C21<>"Retención ISR",C21<>"Retención IVA"),AND(C21="Servicio",F21<>"TMS",F21<>"Valoración",F21<>"EEG",F21<>"Neurofeedback",F21<>"Fotobiomodulación",F21<>"Psicoterapia",F21<>"Otros")),"Tipo o categoría inválido",IF(COUNTA(A21:J21)=0,"",IF(OR(A21="",B21="",C21="",G21=""),"Faltan datos",IF(COUNTIF($A$7:$A$2006,A21)>1,"ID duplicado",IF(OR(B21<DATE(Configuración!$C$5,1,1),B21>=DATE(Configuración!$C$5+1,1,1)),"Fecha fuera del año",IF(OR(G21<0,H21<0),"Revisar signo",IF(AND(C21<>"Servicio",H21<>0),"IVA solo en Servicio",IF(AND(C21="Servicio",F21=""),"Falta servicio","OK")))))))))
K22: =IF(A22="","",G22+H22) | L22: =IF(COUNTA(A22:J22)=0,"",IF(OR(AND(C22<>"Servicio",C22<>"Cobro",C22<>"Anticipo",C22<>"Aplicación anticipo",C22<>"Retención ISR",C22<>"Retención IVA"),AND(C22="Servicio",F22<>"TMS",F22<>"Valoración",F22<>"EEG",F22<>"Neurofeedback",F22<>"Fotobiomodulación",F22<>"Psicoterapia",F22<>"Otros")),"Tipo o categoría inválido",IF(COUNTA(A22:J22)=0,"",IF(OR(A22="",B22="",C22="",G22=""),"Faltan datos",IF(COUNTIF($A$7:$A$2006,A22)>1,"ID duplicado",IF(OR(B22<DATE(Configuración!$C$5,1,1),B22>=DATE(Configuración!$C$5+1,1,1)),"Fecha fuera del año",IF(OR(G22<0,H22<0),"Revisar signo",IF(AND(C22<>"Servicio",H22<>0),"IVA solo en Servicio",IF(AND(C22="Servicio",F22=""),"Falta servicio","OK")))))))))
... K2006: =IF(A2006="","",G2006+H2006) | L2006: =IF(COUNTA(A2006:J2006)=0,"",IF(OR(AND(C2006<>"Servicio",C2006<>"Cobro",C2006<>"Anticipo",C2006<>"Aplicación anticipo",C2006<>"Retención ISR",C2006<>"Retención IVA"),AND(C2006="Servicio",F2006<>"TMS",F2006<>"Valoración",F2006<>"EEG",F2006<>"Neurofeedback",F2006<>"Fotobiomodulación",F2006<>"Psicoterapia",F2006<>"Otros")),"Tipo o categoría inválido",IF(COUNTA(A2006:J2006)=0,"",IF(OR(A2006="",B2006="",C2006="",G2006=""),"Faltan datos",IF(COUNTIF($A$7:$A$2006,A2006)>1,"ID duplicado",IF(OR(B2006<DATE(Configuración!$C$5,1,1),B2006>=DATE(Configuración!$C$5+1,1,1)),"Fecha fuera del año",IF(OR(G2006<0,H2006<0),"Revisar signo",IF(AND(C2006<>"Servicio",H2006<>0),"IVA solo en Servicio",IF(AND(C2006="Servicio",F2006=""),"Falta servicio","OK")))))))))

Sheet Gastos
A2: Gastos
A4: Gasto reconoce el consumo. Pago proveedor registra el banco. Retiros y aportaciones van por separado.
A6: ID único | B6: Fecha | C6: Tipo de registro | D6: Categoría | E6: Beneficiario | F6: ¿Es familiar? | G6: Folio relacionado | H6: Base / importe | I6: IVA recuperable | J6: Nota | K6: Total | L6: Revisión
K7: =IF(A7="","",H7+I7) | L7: =IF(COUNTA(A7:J7)=0,"",IF(OR(AND(C7<>"Gasto",C7<>"Pago proveedor",C7<>"Retiro familiar",C7<>"Aportación",C7<>"Pago activo",C7<>"ISR devengado",C7<>"Pago ISR",C7<>"Pago IVA",C7<>"Compensación ISR",C7<>"Compensación IVA"),AND(C7="Gasto",D7<>"Costos clínicos",D7<>"Remuneración familiar",D7<>"Nómina y honorarios",D7<>"Renta",D7<>"Marketing",D7<>"Servicios y software",D7<>"Mantenimiento",D7<>"Otros",D7<>"Intereses")),"Tipo o categoría inválido",IF(COUNTA(A7:J7)=0,"",IF(OR(A7="",B7="",C7="",H7=""),"Faltan datos",IF(COUNTIF($A$7:$A$2006,A7)>1,"ID duplicado",IF(OR(B7<DATE(Configuración!$C$5,1,1),B7>=DATE(Configuración!$C$5+1,1,1)),"Fecha fuera del año",IF(OR(H7<0,I7<0),"Revisar signo",IF(AND(C7<>"Gasto",I7<>0),"IVA solo en Gasto",IF(AND(C7="Gasto",D7=""),"Falta categoría","OK")))))))))
K8: =IF(A8="","",H8+I8) | L8: =IF(COUNTA(A8:J8)=0,"",IF(OR(AND(C8<>"Gasto",C8<>"Pago proveedor",C8<>"Retiro familiar",C8<>"Aportación",C8<>"Pago activo",C8<>"ISR devengado",C8<>"Pago ISR",C8<>"Pago IVA",C8<>"Compensación ISR",C8<>"Compensación IVA"),AND(C8="Gasto",D8<>"Costos clínicos",D8<>"Remuneración familiar",D8<>"Nómina y honorarios",D8<>"Renta",D8<>"Marketing",D8<>"Servicios y software",D8<>"Mantenimiento",D8<>"Otros",D8<>"Intereses")),"Tipo o categoría inválido",IF(COUNTA(A8:J8)=0,"",IF(OR(A8="",B8="",C8="",H8=""),"Faltan datos",IF(COUNTIF($A$7:$A$2006,A8)>1,"ID duplicado",IF(OR(B8<DATE(Configuración!$C$5,1,1),B8>=DATE(Configuración!$C$5+1,1,1)),"Fecha fuera del año",IF(OR(H8<0,I8<0),"Revisar signo",IF(AND(C8<>"Gasto",I8<>0),"IVA solo en Gasto",IF(AND(C8="Gasto",D8=""),"Falta categoría","OK")))))))))
K9: =IF(A9="","",H9+I9) | L9: =IF(COUNTA(A9:J9)=0,"",IF(OR(AND(C9<>"Gasto",C9<>"Pago proveedor",C9<>"Retiro familiar",C9<>"Aportación",C9<>"Pago activo",C9<>"ISR devengado",C9<>"Pago ISR",C9<>"Pago IVA",C9<>"Compensación ISR",C9<>"Compensación IVA"),AND(C9="Gasto",D9<>"Costos clínicos",D9<>"Remuneración familiar",D9<>"Nómina y honorarios",D9<>"Renta",D9<>"Marketing",D9<>"Servicios y software",D9<>"Mantenimiento",D9<>"Otros",D9<>"Intereses")),"Tipo o categoría inválido",IF(COUNTA(A9:J9)=0,"",IF(OR(A9="",B9="",C9="",H9=""),"Faltan datos",IF(COUNTIF($A$7:$A$2006,A9)>1,"ID duplicado",IF(OR(B9<DATE(Configuración!$C$5,1,1),B9>=DATE(Configuración!$C$5+1,1,1)),"Fecha fuera del año",IF(OR(H9<0,I9<0),"Revisar signo",IF(AND(C9<>"Gasto",I9<>0),"IVA solo en Gasto",IF(AND(C9="Gasto",D9=""),"Falta categoría","OK")))))))))
K10: =IF(A10="","",H10+I10) | L10: =IF(COUNTA(A10:J10)=0,"",IF(OR(AND(C10<>"Gasto",C10<>"Pago proveedor",C10<>"Retiro familiar",C10<>"Aportación",C10<>"Pago activo",C10<>"ISR devengado",C10<>"Pago ISR",C10<>"Pago IVA",C10<>"Compensación ISR",C10<>"Compensación IVA"),AND(C10="Gasto",D10<>"Costos clínicos",D10<>"Remuneración familiar",D10<>"Nómina y honorarios",D10<>"Renta",D10<>"Marketing",D10<>"Servicios y software",D10<>"Mantenimiento",D10<>"Otros",D10<>"Intereses")),"Tipo o categoría inválido",IF(COUNTA(A10:J10)=0,"",IF(OR(A10="",B10="",C10="",H10=""),"Faltan datos",IF(COUNTIF($A$7:$A$2006,A10)>1,"ID duplicado",IF(OR(B10<DATE(Configuración!$C$5,1,1),B10>=DATE(Configuración!$C$5+1,1,1)),"Fecha fuera del año",IF(OR(H10<0,I10<0),"Revisar signo",IF(AND(C10<>"Gasto",I10<>0),"IVA solo en Gasto",IF(AND(C10="Gasto",D10=""),"Falta categoría","OK")))))))))
K11: =IF(A11="","",H11+I11) | L11: =IF(COUNTA(A11:J11)=0,"",IF(OR(AND(C11<>"Gasto",C11<>"Pago proveedor",C11<>"Retiro familiar",C11<>"Aportación",C11<>"Pago activo",C11<>"ISR devengado",C11<>"Pago ISR",C11<>"Pago IVA",C11<>"Compensación ISR",C11<>"Compensación IVA"),AND(C11="Gasto",D11<>"Costos clínicos",D11<>"Remuneración familiar",D11<>"Nómina y honorarios",D11<>"Renta",D11<>"Marketing",D11<>"Servicios y software",D11<>"Mantenimiento",D11<>"Otros",D11<>"Intereses")),"Tipo o categoría inválido",IF(COUNTA(A11:J11)=0,"",IF(OR(A11="",B11="",C11="",H11=""),"Faltan datos",IF(COUNTIF($A$7:$A$2006,A11)>1,"ID duplicado",IF(OR(B11<DATE(Configuración!$C$5,1,1),B11>=DATE(Configuración!$C$5+1,1,1)),"Fecha fuera del año",IF(OR(H11<0,I11<0),"Revisar signo",IF(AND(C11<>"Gasto",I11<>0),"IVA solo en Gasto",IF(AND(C11="Gasto",D11=""),"Falta categoría","OK")))))))))
K12: =IF(A12="","",H12+I12) | L12: =IF(COUNTA(A12:J12)=0,"",IF(OR(AND(C12<>"Gasto",C12<>"Pago proveedor",C12<>"Retiro familiar",C12<>"Aportación",C12<>"Pago activo",C12<>"ISR devengado",C12<>"Pago ISR",C12<>"Pago IVA",C12<>"Compensación ISR",C12<>"Compensación IVA"),AND(C12="Gasto",D12<>"Costos clínicos",D12<>"Remuneración familiar",D12<>"Nómina y honorarios",D12<>"Renta",D12<>"Marketing",D12<>"Servicios y software",D12<>"Mantenimiento",D12<>"Otros",D12<>"Intereses")),"Tipo o categoría inválido",IF(COUNTA(A12:J12)=0,"",IF(OR(A12="",B12="",C12="",H12=""),"Faltan datos",IF(COUNTIF($A$7:$A$2006,A12)>1,"ID duplicado",IF(OR(B12<DATE(Configuración!$C$5,1,1),B12>=DATE(Configuración!$C$5+1,1,1)),"Fecha fuera del año",IF(OR(H12<0,I12<0),"Revisar signo",IF(AND(C12<>"Gasto",I12<>0),"IVA solo en Gasto",IF(AND(C12="Gasto",D12=""),"Falta categoría","OK")))))))))
K13: =IF(A13="","",H13+I13) | L13: =IF(COUNTA(A13:J13)=0,"",IF(OR(AND(C13<>"Gasto",C13<>"Pago proveedor",C13<>"Retiro familiar",C13<>"Aportación",C13<>"Pago activo",C13<>"ISR devengado",C13<>"Pago ISR",C13<>"Pago IVA",C13<>"Compensación ISR",C13<>"Compensación IVA"),AND(C13="Gasto",D13<>"Costos clínicos",D13<>"Remuneración familiar",D13<>"Nómina y honorarios",D13<>"Renta",D13<>"Marketing",D13<>"Servicios y software",D13<>"Mantenimiento",D13<>"Otros",D13<>"Intereses")),"Tipo o categoría inválido",IF(COUNTA(A13:J13)=0,"",IF(OR(A13="",B13="",C13="",H13=""),"Faltan datos",IF(COUNTIF($A$7:$A$2006,A13)>1,"ID duplicado",IF(OR(B13<DATE(Configuración!$C$5,1,1),B13>=DATE(Configuración!$C$5+1,1,1)),"Fecha fuera del año",IF(OR(H13<0,I13<0),"Revisar signo",IF(AND(C13<>"Gasto",I13<>0),"IVA solo en Gasto",IF(AND(C13="Gasto",D13=""),"Falta categoría","OK")))))))))
K14: =IF(A14="","",H14+I14) | L14: =IF(COUNTA(A14:J14)=0,"",IF(OR(AND(C14<>"Gasto",C14<>"Pago proveedor",C14<>"Retiro familiar",C14<>"Aportación",C14<>"Pago activo",C14<>"ISR devengado",C14<>"Pago ISR",C14<>"Pago IVA",C14<>"Compensación ISR",C14<>"Compensación IVA"),AND(C14="Gasto",D14<>"Costos clínicos",D14<>"Remuneración familiar",D14<>"Nómina y honorarios",D14<>"Renta",D14<>"Marketing",D14<>"Servicios y software",D14<>"Mantenimiento",D14<>"Otros",D14<>"Intereses")),"Tipo o categoría inválido",IF(COUNTA(A14:J14)=0,"",IF(OR(A14="",B14="",C14="",H14=""),"Faltan datos",IF(COUNTIF($A$7:$A$2006,A14)>1,"ID duplicado",IF(OR(B14<DATE(Configuración!$C$5,1,1),B14>=DATE(Configuración!$C$5+1,1,1)),"Fecha fuera del año",IF(OR(H14<0,I14<0),"Revisar signo",IF(AND(C14<>"Gasto",I14<>0),"IVA solo en Gasto",IF(AND(C14="Gasto",D14=""),"Falta categoría","OK")))))))))
K15: =IF(A15="","",H15+I15) | L15: =IF(COUNTA(A15:J15)=0,"",IF(OR(AND(C15<>"Gasto",C15<>"Pago proveedor",C15<>"Retiro familiar",C15<>"Aportación",C15<>"Pago activo",C15<>"ISR devengado",C15<>"Pago ISR",C15<>"Pago IVA",C15<>"Compensación ISR",C15<>"Compensación IVA"),AND(C15="Gasto",D15<>"Costos clínicos",D15<>"Remuneración familiar",D15<>"Nómina y honorarios",D15<>"Renta",D15<>"Marketing",D15<>"Servicios y software",D15<>"Mantenimiento",D15<>"Otros",D15<>"Intereses")),"Tipo o categoría inválido",IF(COUNTA(A15:J15)=0,"",IF(OR(A15="",B15="",C15="",H15=""),"Faltan datos",IF(COUNTIF($A$7:$A$2006,A15)>1,"ID duplicado",IF(OR(B15<DATE(Configuración!$C$5,1,1),B15>=DATE(Configuración!$C$5+1,1,1)),"Fecha fuera del año",IF(OR(H15<0,I15<0),"Revisar signo",IF(AND(C15<>"Gasto",I15<>0),"IVA solo en Gasto",IF(AND(C15="Gasto",D15=""),"Falta categoría","OK")))))))))
K16: =IF(A16="","",H16+I16) | L16: =IF(COUNTA(A16:J16)=0,"",IF(OR(AND(C16<>"Gasto",C16<>"Pago proveedor",C16<>"Retiro familiar",C16<>"Aportación",C16<>"Pago activo",C16<>"ISR devengado",C16<>"Pago ISR",C16<>"Pago IVA",C16<>"Compensación ISR",C16<>"Compensación IVA"),AND(C16="Gasto",D16<>"Costos clínicos",D16<>"Remuneración familiar",D16<>"Nómina y honorarios",D16<>"Renta",D16<>"Marketing",D16<>"Servicios y software",D16<>"Mantenimiento",D16<>"Otros",D16<>"Intereses")),"Tipo o categoría inválido",IF(COUNTA(A16:J16)=0,"",IF(OR(A16="",B16="",C16="",H16=""),"Faltan datos",IF(COUNTIF($A$7:$A$2006,A16)>1,"ID duplicado",IF(OR(B16<DATE(Configuración!$C$5,1,1),B16>=DATE(Configuración!$C$5+1,1,1)),"Fecha fuera del año",IF(OR(H16<0,I16<0),"Revisar signo",IF(AND(C16<>"Gasto",I16<>0),"IVA solo en Gasto",IF(AND(C16="Gasto",D16=""),"Falta categoría","OK")))))))))
K17: =IF(A17="","",H17+I17) | L17: =IF(COUNTA(A17:J17)=0,"",IF(OR(AND(C17<>"Gasto",C17<>"Pago proveedor",C17<>"Retiro familiar",C17<>"Aportación",C17<>"Pago activo",C17<>"ISR devengado",C17<>"Pago ISR",C17<>"Pago IVA",C17<>"Compensación ISR",C17<>"Compensación IVA"),AND(C17="Gasto",D17<>"Costos clínicos",D17<>"Remuneración familiar",D17<>"Nómina y honorarios",D17<>"Renta",D17<>"Marketing",D17<>"Servicios y software",D17<>"Mantenimiento",D17<>"Otros",D17<>"Intereses")),"Tipo o categoría inválido",IF(COUNTA(A17:J17)=0,"",IF(OR(A17="",B17="",C17="",H17=""),"Faltan datos",IF(COUNTIF($A$7:$A$2006,A17)>1,"ID duplicado",IF(OR(B17<DATE(Configuración!$C$5,1,1),B17>=DATE(Configuración!$C$5+1,1,1)),"Fecha fuera del año",IF(OR(H17<0,I17<0),"Revisar signo",IF(AND(C17<>"Gasto",I17<>0),"IVA solo en Gasto",IF(AND(C17="Gasto",D17=""),"Falta categoría","OK")))))))))
K18: =IF(A18="","",H18+I18) | L18: =IF(COUNTA(A18:J18)=0,"",IF(OR(AND(C18<>"Gasto",C18<>"Pago proveedor",C18<>"Retiro familiar",C18<>"Aportación",C18<>"Pago activo",C18<>"ISR devengado",C18<>"Pago ISR",C18<>"Pago IVA",C18<>"Compensación ISR",C18<>"Compensación IVA"),AND(C18="Gasto",D18<>"Costos clínicos",D18<>"Remuneración familiar",D18<>"Nómina y honorarios",D18<>"Renta",D18<>"Marketing",D18<>"Servicios y software",D18<>"Mantenimiento",D18<>"Otros",D18<>"Intereses")),"Tipo o categoría inválido",IF(COUNTA(A18:J18)=0,"",IF(OR(A18="",B18="",C18="",H18=""),"Faltan datos",IF(COUNTIF($A$7:$A$2006,A18)>1,"ID duplicado",IF(OR(B18<DATE(Configuración!$C$5,1,1),B18>=DATE(Configuración!$C$5+1,1,1)),"Fecha fuera del año",IF(OR(H18<0,I18<0),"Revisar signo",IF(AND(C18<>"Gasto",I18<>0),"IVA solo en Gasto",IF(AND(C18="Gasto",D18=""),"Falta categoría","OK")))))))))
... K2006: =IF(A2006="","",H2006+I2006) | L2006: =IF(COUNTA(A2006:J2006)=0,"",IF(OR(AND(C2006<>"Gasto",C2006<>"Pago proveedor",C2006<>"Retiro familiar",C2006<>"Aportación",C2006<>"Pago activo",C2006<>"ISR devengado",C2006<>"Pago ISR",C2006<>"Pago IVA",C2006<>"Compensación ISR",C2006<>"Compensación IVA"),AND(C2006="Gasto",D2006<>"Costos clínicos",D2006<>"Remuneración familiar",D2006<>"Nómina y honorarios",D2006<>"Renta",D2006<>"Marketing",D2006<>"Servicios y software",D2006<>"Mantenimiento",D2006<>"Otros",D2006<>"Intereses")),"Tipo o categoría inválido",IF(COUNTA(A2006:J2006)=0,"",IF(OR(A2006="",B2006="",C2006="",H2006=""),"Faltan datos",IF(COUNTIF($A$7:$A$2006,A2006)>1,"ID duplicado",IF(OR(B2006<DATE(Configuración!$C$5,1,1),B2006>=DATE(Configuración!$C$5+1,1,1)),"Fecha fuera del año",IF(OR(H2006<0,I2006<0),"Revisar signo",IF(AND(C2006<>"Gasto",I2006<>0),"IVA solo en Gasto",IF(AND(C2006="Gasto",D2006=""),"Falta categoría","OK")))))))))

Sheet Activos
A2: Activos
A4: Una fila por equipo. Depreciación lineal contable desde el mes de puesta en uso. Pagos: Gastos, tipo Pago activo.
M5: =DATE(Configuración!$C$5,1,1) -> 46023 | N5: =DATE(Configuración!$C$5,2,1) -> 46054 | O5: =DATE(Configuración!$C$5,3,1) -> 46082 | P5: =DATE(Configuración!$C$5,4,1) -> 46113 | Q5: =DATE(Configuración!$C$5,5,1) -> 46143 | R5: =DATE(Configuración!$C$5,6,1) -> 46174 | S5: =DATE(Configuración!$C$5,7,1) -> 46204 | T5: =DATE(Configuración!$C$5,8,1) -> 46235 | U5: =DATE(Configuración!$C$5,9,1) -> 46266 | V5: =DATE(Configuración!$C$5,10,1) -> 46296 | W5: =DATE(Configuración!$C$5,11,1) -> 46327 | X5: =DATE(Configuración!$C$5,12,1) -> 46357
A6: ID activo | B6: Descripción | C6: Fecha compra | D6: En uso desde | E6: Costo capitalizado | F6: IVA recuperable | G6: Residual | H6: Vida útil (meses) | I6: Dep. inicial | J6: Nota | K6: Dep. mensual | L6: Revisión | M6: Dep. 1 | N6: Dep. 2 | O6: Dep. 3 | P6: Dep. 4 | Q6: Dep. 5 | R6: Dep. 6 | S6: Dep. 7 | T6: Dep. 8 | U6: Dep. 9 | V6: Dep. 10 | W6: Dep. 11 | X6: Dep. 12
K7: =IF(A7="","",IF(OR(H7="",H7<=0),0,(E7-G7)/H7)) | L7: =IF(COUNTA(A7:J7)=0,"",IF(OR(A7="",C7="",D7="",E7="",H7<=0),"Faltan datos",IF(COUNTIF($A$7:$A$106,A7)>1,"ID duplicado",IF(OR(E7<0,G7<0,I7<0,G7+I7>E7,D7<C7),"Revisar activo",IF(AND(C7>=DATE(Configuración!$C$5,1,1),I7<>0),"Dep. inicial no procede","OK"))))) | M7: =IF(OR($A7="",$D7="",$D7>=EDATE(M$5,1)),0,MAX(0,MIN($K7,$E7-$G7-$I7-0))) -> 0 | N7: =IF(OR($A7="",$D7="",$D7>=EDATE(N$5,1)),0,MAX(0,MIN($K7,$E7-$G7-$I7-SUM($M7:M7)))) -> 0 | O7: =IF(OR($A7="",$D7="",$D7>=EDATE(O$5,1)),0,MAX(0,MIN($K7,$E7-$G7-$I7-SUM($M7:N7)))) -> 0 | P7: =IF(OR($A7="",$D7="",$D7>=EDATE(P$5,1)),0,MAX(0,MIN($K7,$E7-$G7-$I7-SUM($M7:O7)))) -> 0 | Q7: =IF(OR($A7="",$D7="",$D7>=EDATE(Q$5,1)),0,MAX(0,MIN($K7,$E7-$G7-$I7-SUM($M7:P7)))) -> 0 | R7: =IF(OR($A7="",$D7="",$D7>=EDATE(R$5,1)),0,MAX(0,MIN($K7,$E7-$G7-$I7-SUM($M7:Q7)))) -> 0 | S7: =IF(OR($A7="",$D7="",$D7>=EDATE(S$5,1)),0,MAX(0,MIN($K7,$E7-$G7-$I7-SUM($M7:R7)))) -> 0 | T7: =IF(OR($A7="",$D7="",$D7>=EDATE(T$5,1)),0,MAX(0,MIN($K7,$E7-$G7-$I7-SUM($M7:S7)))) -> 0 | U7: =IF(OR($A7="",$D7="",$D7>=EDATE(U$5,1)),0,MAX(0,MIN($K7,$E7-$G7-$I7-SUM($M7:T7)))) -> 0 | ... X7: =IF(OR($A7="",$D7="",$D7>=EDATE(X$5,1)),0,MAX(0,MIN($K7,$E7-$G7-$I7-SUM($M7:W7)))) -> 0
K8: =IF(A8="","",IF(OR(H8="",H8<=0),0,(E8-G8)/H8)) | L8: =IF(COUNTA(A8:J8)=0,"",IF(OR(A8="",C8="",D8="",E8="",H8<=0),"Faltan datos",IF(COUNTIF($A$7:$A$106,A8)>1,"ID duplicado",IF(OR(E8<0,G8<0,I8<0,G8+I8>E8,D8<C8),"Revisar activo",IF(AND(C8>=DATE(Configuración!$C$5,1,1),I8<>0),"Dep. inicial no procede","OK"))))) | M8: =IF(OR($A8="",$D8="",$D8>=EDATE(M$5,1)),0,MAX(0,MIN($K8,$E8-$G8-$I8-0))) -> 0 | N8: =IF(OR($A8="",$D8="",$D8>=EDATE(N$5,1)),0,MAX(0,MIN($K8,$E8-$G8-$I8-SUM($M8:M8)))) -> 0 | O8: =IF(OR($A8="",$D8="",$D8>=EDATE(O$5,1)),0,MAX(0,MIN($K8,$E8-$G8-$I8-SUM($M8:N8)))) -> 0 | P8: =IF(OR($A8="",$D8="",$D8>=EDATE(P$5,1)),0,MAX(0,MIN($K8,$E8-$G8-$I8-SUM($M8:O8)))) -> 0 | Q8: =IF(OR($A8="",$D8="",$D8>=EDATE(Q$5,1)),0,MAX(0,MIN($K8,$E8-$G8-$I8-SUM($M8:P8)))) -> 0 | R8: =IF(OR($A8="",$D8="",$D8>=EDATE(R$5,1)),0,MAX(0,MIN($K8,$E8-$G8-$I8-SUM($M8:Q8)))) -> 0 | S8: =IF(OR($A8="",$D8="",$D8>=EDATE(S$5,1)),0,MAX(0,MIN($K8,$E8-$G8-$I8-SUM($M8:R8)))) -> 0 | T8: =IF(OR($A8="",$D8="",$D8>=EDATE(T$5,1)),0,MAX(0,MIN($K8,$E8-$G8-$I8-SUM($M8:S8)))) -> 0 | U8: =IF(OR($A8="",$D8="",$D8>=EDATE(U$5,1)),0,MAX(0,MIN($K8,$E8-$G8-$I8-SUM($M8:T8)))) -> 0 | ... X8: =IF(OR($A8="",$D8="",$D8>=EDATE(X$5,1)),0,MAX(0,MIN($K8,$E8-$G8-$I8-SUM($M8:W8)))) -> 0
K9: =IF(A9="","",IF(OR(H9="",H9<=0),0,(E9-G9)/H9)) | L9: =IF(COUNTA(A9:J9)=0,"",IF(OR(A9="",C9="",D9="",E9="",H9<=0),"Faltan datos",IF(COUNTIF($A$7:$A$106,A9)>1,"ID duplicado",IF(OR(E9<0,G9<0,I9<0,G9+I9>E9,D9<C9),"Revisar activo",IF(AND(C9>=DATE(Configuración!$C$5,1,1),I9<>0),"Dep. inicial no procede","OK"))))) | M9: =IF(OR($A9="",$D9="",$D9>=EDATE(M$5,1)),0,MAX(0,MIN($K9,$E9-$G9-$I9-0))) -> 0 | N9: =IF(OR($A9="",$D9="",$D9>=EDATE(N$5,1)),0,MAX(0,MIN($K9,$E9-$G9-$I9-SUM($M9:M9)))) -> 0 | O9: =IF(OR($A9="",$D9="",$D9>=EDATE(O$5,1)),0,MAX(0,MIN($K9,$E9-$G9-$I9-SUM($M9:N9)))) -> 0 | P9: =IF(OR($A9="",$D9="",$D9>=EDATE(P$5,1)),0,MAX(0,MIN($K9,$E9-$G9-$I9-SUM($M9:O9)))) -> 0 | Q9: =IF(OR($A9="",$D9="",$D9>=EDATE(Q$5,1)),0,MAX(0,MIN($K9,$E9-$G9-$I9-SUM($M9:P9)))) -> 0 | R9: =IF(OR($A9="",$D9="",$D9>=EDATE(R$5,1)),0,MAX(0,MIN($K9,$E9-$G9-$I9-SUM($M9:Q9)))) -> 0 | S9: =IF(OR($A9="",$D9="",$D9>=EDATE(S$5,1)),0,MAX(0,MIN($K9,$E9-$G9-$I9-SUM($M9:R9)))) -> 0 | T9: =IF(OR($A9="",$D9="",$D9>=EDATE(T$5,1)),0,MAX(0,MIN($K9,$E9-$G9-$I9-SUM($M9:S9)))) -> 0 | U9: =IF(OR($A9="",$D9="",$D9>=EDATE(U$5,1)),0,MAX(0,MIN($K9,$E9-$G9-$I9-SUM($M9:T9)))) -> 0 | ... X9: =IF(OR($A9="",$D9="",$D9>=EDATE(X$5,1)),0,MAX(0,MIN($K9,$E9-$G9-$I9-SUM($M9:W9)))) -> 0
K10: =IF(A10="","",IF(OR(H10="",H10<=0),0,(E10-G10)/H10)) | L10: =IF(COUNTA(A10:J10)=0,"",IF(OR(A10="",C10="",D10="",E10="",H10<=0),"Faltan datos",IF(COUNTIF($A$7:$A$106,A10)>1,"ID duplicado",IF(OR(E10<0,G10<0,I10<0,G10+I10>E10,D10<C10),"Revisar activo",IF(AND(C10>=DATE(Configuración!$C$5,1,1),I10<>0),"Dep. inicial no procede","OK"))))) | M10: =IF(OR($A10="",$D10="",$D10>=EDATE(M$5,1)),0,MAX(0,MIN($K10,$E10-$G10-$I10-0))) -> 0 | N10: =IF(OR($A10="",$D10="",$D10>=EDATE(N$5,1)),0,MAX(0,MIN($K10,$E10-$G10-$I10-SUM($M10:M10)))) -> 0 | O10: =IF(OR($A10="",$D10="",$D10>=EDATE(O$5,1)),0,MAX(0,MIN($K10,$E10-$G10-$I10-SUM($M10:N10)))) -> 0 | P10: =IF(OR($A10="",$D10="",$D10>=EDATE(P$5,1)),0,MAX(0,MIN($K10,$E10-$G10-$I10-SUM($M10:O10)))) -> 0 | Q10: =IF(OR($A10="",$D10="",$D10>=EDATE(Q$5,1)),0,MAX(0,MIN($K10,$E10-$G10-$I10-SUM($M10:P10)))) -> 0 | R10: =IF(OR($A10="",$D10="",$D10>=EDATE(R$5,1)),0,MAX(0,MIN($K10,$E10-$G10-$I10-SUM($M10:Q10)))) -> 0 | S10: =IF(OR($A10="",$D10="",$D10>=EDATE(S$5,1)),0,MAX(0,MIN($K10,$E10-$G10-$I10-SUM($M10:R10)))) -> 0 | T10: =IF(OR($A10="",$D10="",$D10>=EDATE(T$5,1)),0,MAX(0,MIN($K10,$E10-$G10-$I10-SUM($M10:S10)))) -> 0 | U10: =IF(OR($A10="",$D10="",$D10>=EDATE(U$5,1)),0,MAX(0,MIN($K10,$E10-$G10-$I10-SUM($M10:T10)))) -> 0 | ... X10: =IF(OR($A10="",$D10="",$D10>=EDATE(X$5,1)),0,MAX(0,MIN($K10,$E10-$G10-$I10-SUM($M10:W10)))) -> 0
K11: =IF(A11="","",IF(OR(H11="",H11<=0),0,(E11-G11)/H11)) | L11: =IF(COUNTA(A11:J11)=0,"",IF(OR(A11="",C11="",D11="",E11="",H11<=0),"Faltan datos",IF(COUNTIF($A$7:$A$106,A11)>1,"ID duplicado",IF(OR(E11<0,G11<0,I11<0,G11+I11>E11,D11<C11),"Revisar activo",IF(AND(C11>=DATE(Configuración!$C$5,1,1),I11<>0),"Dep. inicial no procede","OK"))))) | M11: =IF(OR($A11="",$D11="",$D11>=EDATE(M$5,1)),0,MAX(0,MIN($K11,$E11-$G11-$I11-0))) -> 0 | N11: =IF(OR($A11="",$D11="",$D11>=EDATE(N$5,1)),0,MAX(0,MIN($K11,$E11-$G11-$I11-SUM($M11:M11)))) -> 0 | O11: =IF(OR($A11="",$D11="",$D11>=EDATE(O$5,1)),0,MAX(0,MIN($K11,$E11-$G11-$I11-SUM($M11:N11)))) -> 0 | P11: =IF(OR($A11="",$D11="",$D11>=EDATE(P$5,1)),0,MAX(0,MIN($K11,$E11-$G11-$I11-SUM($M11:O11)))) -> 0 | Q11: =IF(OR($A11="",$D11="",$D11>=EDATE(Q$5,1)),0,MAX(0,MIN($K11,$E11-$G11-$I11-SUM($M11:P11)))) -> 0 | R11: =IF(OR($A11="",$D11="",$D11>=EDATE(R$5,1)),0,MAX(0,MIN($K11,$E11-$G11-$I11-SUM($M11:Q11)))) -> 0 | S11: =IF(OR($A11="",$D11="",$D11>=EDATE(S$5,1)),0,MAX(0,MIN($K11,$E11-$G11-$I11-SUM($M11:R11)))) -> 0 | T11: =IF(OR($A11="",$D11="",$D11>=EDATE(T$5,1)),0,MAX(0,MIN($K11,$E11-$G11-$I11-SUM($M11:S11)))) -> 0 | U11: =IF(OR($A11="",$D11="",$D11>=EDATE(U$5,1)),0,MAX(0,MIN($K11,$E11-$G11-$I11-SUM($M11:T11)))) -> 0 | ... X11: =IF(OR($A11="",$D11="",$D11>=EDATE(X$5,1)),0,MAX(0,MIN($K11,$E11-$G11-$I11-SUM($M11:W11)))) -> 0
K12: =IF(A12="","",IF(OR(H12="",H12<=0),0,(E12-G12)/H12)) | L12: =IF(COUNTA(A12:J12)=0,"",IF(OR(A12="",C12="",D12="",E12="",H12<=0),"Faltan datos",IF(COUNTIF($A$7:$A$106,A12)>1,"ID duplicado",IF(OR(E12<0,G12<0,I12<0,G12+I12>E12,D12<C12),"Revisar activo",IF(AND(C12>=DATE(Configuración!$C$5,1,1),I12<>0),"Dep. inicial no procede","OK"))))) | M12: =IF(OR($A12="",$D12="",$D12>=EDATE(M$5,1)),0,MAX(0,MIN($K12,$E12-$G12-$I12-0))) -> 0 | N12: =IF(OR($A12="",$D12="",$D12>=EDATE(N$5,1)),0,MAX(0,MIN($K12,$E12-$G12-$I12-SUM($M12:M12)))) -> 0 | O12: =IF(OR($A12="",$D12="",$D12>=EDATE(O$5,1)),0,MAX(0,MIN($K12,$E12-$G12-$I12-SUM($M12:N12)))) -> 0 | P12: =IF(OR($A12="",$D12="",$D12>=EDATE(P$5,1)),0,MAX(0,MIN($K12,$E12-$G12-$I12-SUM($M12:O12)))) -> 0 | Q12: =IF(OR($A12="",$D12="",$D12>=EDATE(Q$5,1)),0,MAX(0,MIN($K12,$E12-$G12-$I12-SUM($M12:P12)))) -> 0 | R12: =IF(OR($A12="",$D12="",$D12>=EDATE(R$5,1)),0,MAX(0,MIN($K12,$E12-$G12-$I12-SUM($M12:Q12)))) -> 0 | S12: =IF(OR($A12="",$D12="",$D12>=EDATE(S$5,1)),0,MAX(0,MIN($K12,$E12-$G12-$I12-SUM($M12:R12)))) -> 0 | T12: =IF(OR($A12="",$D12="",$D12>=EDATE(T$5,1)),0,MAX(0,MIN($K12,$E12-$G12-$I12-SUM($M12:S12)))) -> 0 | U12: =IF(OR($A12="",$D12="",$D12>=EDATE(U$5,1)),0,MAX(0,MIN($K12,$E12-$G12-$I12-SUM($M12:T12)))) -> 0 | ... X12: =IF(OR($A12="",$D12="",$D12>=EDATE(X$5,1)),0,MAX(0,MIN($K12,$E12-$G12-$I12-SUM($M12:W12)))) -> 0
K13: =IF(A13="","",IF(OR(H13="",H13<=0),0,(E13-G13)/H13)) | L13: =IF(COUNTA(A13:J13)=0,"",IF(OR(A13="",C13="",D13="",E13="",H13<=0),"Faltan datos",IF(COUNTIF($A$7:$A$106,A13)>1,"ID duplicado",IF(OR(E13<0,G13<0,I13<0,G13+I13>E13,D13<C13),"Revisar activo",IF(AND(C13>=DATE(Configuración!$C$5,1,1),I13<>0),"Dep. inicial no procede","OK"))))) | M13: =IF(OR($A13="",$D13="",$D13>=EDATE(M$5,1)),0,MAX(0,MIN($K13,$E13-$G13-$I13-0))) -> 0 | N13: =IF(OR($A13="",$D13="",$D13>=EDATE(N$5,1)),0,MAX(0,MIN($K13,$E13-$G13-$I13-SUM($M13:M13)))) -> 0 | O13: =IF(OR($A13="",$D13="",$D13>=EDATE(O$5,1)),0,MAX(0,MIN($K13,$E13-$G13-$I13-SUM($M13:N13)))) -> 0 | P13: =IF(OR($A13="",$D13="",$D13>=EDATE(P$5,1)),0,MAX(0,MIN($K13,$E13-$G13-$I13-SUM($M13:O13)))) -> 0 | Q13: =IF(OR($A13="",$D13="",$D13>=EDATE(Q$5,1)),0,MAX(0,MIN($K13,$E13-$G13-$I13-SUM($M13:P13)))) -> 0 | R13: =IF(OR($A13="",$D13="",$D13>=EDATE(R$5,1)),0,MAX(0,MIN($K13,$E13-$G13-$I13-SUM($M13:Q13)))) -> 0 | S13: =IF(OR($A13="",$D13="",$D13>=EDATE(S$5,1)),0,MAX(0,MIN($K13,$E13-$G13-$I13-SUM($M13:R13)))) -> 0 | T13: =IF(OR($A13="",$D13="",$D13>=EDATE(T$5,1)),0,MAX(0,MIN($K13,$E13-$G13-$I13-SUM($M13:S13)))) -> 0 | U13: =IF(OR($A13="",$D13="",$D13>=EDATE(U$5,1)),0,MAX(0,MIN($K13,$E13-$G13-$I13-SUM($M13:T13)))) -> 0 | ... X13: =IF(OR($A13="",$D13="",$D13>=EDATE(X$5,1)),0,MAX(0,MIN($K13,$E13-$G13-$I13-SUM($M13:W13)))) -> 0
K14: =IF(A14="","",IF(OR(H14="",H14<=0),0,(E14-G14)/H14)) | L14: =IF(COUNTA(A14:J14)=0,"",IF(OR(A14="",C14="",D14="",E14="",H14<=0),"Faltan datos",IF(COUNTIF($A$7:$A$106,A14)>1,"ID duplicado",IF(OR(E14<0,G14<0,I14<0,G14+I14>E14,D14<C14),"Revisar activo",IF(AND(C14>=DATE(Configuración!$C$5,1,1),I14<>0),"Dep. inicial no procede","OK"))))) | M14: =IF(OR($A14="",$D14="",$D14>=EDATE(M$5,1)),0,MAX(0,MIN($K14,$E14-$G14-$I14-0))) -> 0 | N14: =IF(OR($A14="",$D14="",$D14>=EDATE(N$5,1)),0,MAX(0,MIN($K14,$E14-$G14-$I14-SUM($M14:M14)))) -> 0 | O14: =IF(OR($A14="",$D14="",$D14>=EDATE(O$5,1)),0,MAX(0,MIN($K14,$E14-$G14-$I14-SUM($M14:N14)))) -> 0 | P14: =IF(OR($A14="",$D14="",$D14>=EDATE(P$5,1)),0,MAX(0,MIN($K14,$E14-$G14-$I14-SUM($M14:O14)))) -> 0 | Q14: =IF(OR($A14="",$D14="",$D14>=EDATE(Q$5,1)),0,MAX(0,MIN($K14,$E14-$G14-$I14-SUM($M14:P14)))) -> 0 | R14: =IF(OR($A14="",$D14="",$D14>=EDATE(R$5,1)),0,MAX(0,MIN($K14,$E14-$G14-$I14-SUM($M14:Q14)))) -> 0 | S14: =IF(OR($A14="",$D14="",$D14>=EDATE(S$5,1)),0,MAX(0,MIN($K14,$E14-$G14-$I14-SUM($M14:R14)))) -> 0 | T14: =IF(OR($A14="",$D14="",$D14>=EDATE(T$5,1)),0,MAX(0,MIN($K14,$E14-$G14-$I14-SUM($M14:S14)))) -> 0 | U14: =IF(OR($A14="",$D14="",$D14>=EDATE(U$5,1)),0,MAX(0,MIN($K14,$E14-$G14-$I14-SUM($M14:T14)))) -> 0 | ... X14: =IF(OR($A14="",$D14="",$D14>=EDATE(X$5,1)),0,MAX(0,MIN($K14,$E14-$G14-$I14-SUM($M14:W14)))) -> 0
K15: =IF(A15="","",IF(OR(H15="",H15<=0),0,(E15-G15)/H15)) | L15: =IF(COUNTA(A15:J15)=0,"",IF(OR(A15="",C15="",D15="",E15="",H15<=0),"Faltan datos",IF(COUNTIF($A$7:$A$106,A15)>1,"ID duplicado",IF(OR(E15<0,G15<0,I15<0,G15+I15>E15,D15<C15),"Revisar activo",IF(AND(C15>=DATE(Configuración!$C$5,1,1),I15<>0),"Dep. inicial no procede","OK"))))) | M15: =IF(OR($A15="",$D15="",$D15>=EDATE(M$5,1)),0,MAX(0,MIN($K15,$E15-$G15-$I15-0))) -> 0 | N15: =IF(OR($A15="",$D15="",$D15>=EDATE(N$5,1)),0,MAX(0,MIN($K15,$E15-$G15-$I15-SUM($M15:M15)))) -> 0 | O15: =IF(OR($A15="",$D15="",$D15>=EDATE(O$5,1)),0,MAX(0,MIN($K15,$E15-$G15-$I15-SUM($M15:N15)))) -> 0 | P15: =IF(OR($A15="",$D15="",$D15>=EDATE(P$5,1)),0,MAX(0,MIN($K15,$E15-$G15-$I15-SUM($M15:O15)))) -> 0 | Q15: =IF(OR($A15="",$D15="",$D15>=EDATE(Q$5,1)),0,MAX(0,MIN($K15,$E15-$G15-$I15-SUM($M15:P15)))) -> 0 | R15: =IF(OR($A15="",$D15="",$D15>=EDATE(R$5,1)),0,MAX(0,MIN($K15,$E15-$G15-$I15-SUM($M15:Q15)))) -> 0 | S15: =IF(OR($A15="",$D15="",$D15>=EDATE(S$5,1)),0,MAX(0,MIN($K15,$E15-$G15-$I15-SUM($M15:R15)))) -> 0 | T15: =IF(OR($A15="",$D15="",$D15>=EDATE(T$5,1)),0,MAX(0,MIN($K15,$E15-$G15-$I15-SUM($M15:S15)))) -> 0 | U15: =IF(OR($A15="",$D15="",$D15>=EDATE(U$5,1)),0,MAX(0,MIN($K15,$E15-$G15-$I15-SUM($M15:T15)))) -> 0 | ... X15: =IF(OR($A15="",$D15="",$D15>=EDATE(X$5,1)),0,MAX(0,MIN($K15,$E15-$G15-$I15-SUM($M15:W15)))) -> 0
K16: =IF(A16="","",IF(OR(H16="",H16<=0),0,(E16-G16)/H16)) | L16: =IF(COUNTA(A16:J16)=0,"",IF(OR(A16="",C16="",D16="",E16="",H16<=0),"Faltan datos",IF(COUNTIF($A$7:$A$106,A16)>1,"ID duplicado",IF(OR(E16<0,G16<0,I16<0,G16+I16>E16,D16<C16),"Revisar activo",IF(AND(C16>=DATE(Configuración!$C$5,1,1),I16<>0),"Dep. inicial no procede","OK"))))) | M16: =IF(OR($A16="",$D16="",$D16>=EDATE(M$5,1)),0,MAX(0,MIN($K16,$E16-$G16-$I16-0))) -> 0 | N16: =IF(OR($A16="",$D16="",$D16>=EDATE(N$5,1)),0,MAX(0,MIN($K16,$E16-$G16-$I16-SUM($M16:M16)))) -> 0 | O16: =IF(OR($A16="",$D16="",$D16>=EDATE(O$5,1)),0,MAX(0,MIN($K16,$E16-$G16-$I16-SUM($M16:N16)))) -> 0 | P16: =IF(OR($A16="",$D16="",$D16>=EDATE(P$5,1)),0,MAX(0,MIN($K16,$E16-$G16-$I16-SUM($M16:O16)))) -> 0 | Q16: =IF(OR($A16="",$D16="",$D16>=EDATE(Q$5,1)),0,MAX(0,MIN($K16,$E16-$G16-$I16-SUM($M16:P16)))) -> 0 | R16: =IF(OR($A16="",$D16="",$D16>=EDATE(R$5,1)),0,MAX(0,MIN($K16,$E16-$G16-$I16-SUM($M16:Q16)))) -> 0 | S16: =IF(OR($A16="",$D16="",$D16>=EDATE(S$5,1)),0,MAX(0,MIN($K16,$E16-$G16-$I16-SUM($M16:R16)))) -> 0 | T16: =IF(OR($A16="",$D16="",$D16>=EDATE(T$5,1)),0,MAX(0,MIN($K16,$E16-$G16-$I16-SUM($M16:S16)))) -> 0 | U16: =IF(OR($A16="",$D16="",$D16>=EDATE(U$5,1)),0,MAX(0,MIN($K16,$E16-$G16-$I16-SUM($M16:T16)))) -> 0 | ... X16: =IF(OR($A16="",$D16="",$D16>=EDATE(X$5,1)),0,MAX(0,MIN($K16,$E16-$G16-$I16-SUM($M16:W16)))) -> 0
K17: =IF(A17="","",IF(OR(H17="",H17<=0),0,(E17-G17)/H17)) | L17: =IF(COUNTA(A17:J17)=0,"",IF(OR(A17="",C17="",D17="",E17="",H17<=0),"Faltan datos",IF(COUNTIF($A$7:$A$106,A17)>1,"ID duplicado",IF(OR(E17<0,G17<0,I17<0,G17+I17>E17,D17<C17),"Revisar activo",IF(AND(C17>=DATE(Configuración!$C$5,1,1),I17<>0),"Dep. inicial no procede","OK"))))) | M17: =IF(OR($A17="",$D17="",$D17>=EDATE(M$5,1)),0,MAX(0,MIN($K17,$E17-$G17-$I17-0))) -> 0 | N17: =IF(OR($A17="",$D17="",$D17>=EDATE(N$5,1)),0,MAX(0,MIN($K17,$E17-$G17-$I17-SUM($M17:M17)))) -> 0 | O17: =IF(OR($A17="",$D17="",$D17>=EDATE(O$5,1)),0,MAX(0,MIN($K17,$E17-$G17-$I17-SUM($M17:N17)))) -> 0 | P17: =IF(OR($A17="",$D17="",$D17>=EDATE(P$5,1)),0,MAX(0,MIN($K17,$E17-$G17-$I17-SUM($M17:O17)))) -> 0 | Q17: =IF(OR($A17="",$D17="",$D17>=EDATE(Q$5,1)),0,MAX(0,MIN($K17,$E17-$G17-$I17-SUM($M17:P17)))) -> 0 | R17: =IF(OR($A17="",$D17="",$D17>=EDATE(R$5,1)),0,MAX(0,MIN($K17,$E17-$G17-$I17-SUM($M17:Q17)))) -> 0 | S17: =IF(OR($A17="",$D17="",$D17>=EDATE(S$5,1)),0,MAX(0,MIN($K17,$E17-$G17-$I17-SUM($M17:R17)))) -> 0 | T17: =IF(OR($A17="",$D17="",$D17>=EDATE(T$5,1)),0,MAX(0,MIN($K17,$E17-$G17-$I17-SUM($M17:S17)))) -> 0 | U17: =IF(OR($A17="",$D17="",$D17>=EDATE(U$5,1)),0,MAX(0,MIN($K17,$E17-$G17-$I17-SUM($M17:T17)))) -> 0 | ... X17: =IF(OR($A17="",$D17="",$D17>=EDATE(X$5,1)),0,MAX(0,MIN($K17,$E17-$G17-$I17-SUM($M17:W17)))) -> 0
K18: =IF(A18="","",IF(OR(H18="",H18<=0),0,(E18-G18)/H18)) | L18: =IF(COUNTA(A18:J18)=0,"",IF(OR(A18="",C18="",D18="",E18="",H18<=0),"Faltan datos",IF(COUNTIF($A$7:$A$106,A18)>1,"ID duplicado",IF(OR(E18<0,G18<0,I18<0,G18+I18>E18,D18<C18),"Revisar activo",IF(AND(C18>=DATE(Configuración!$C$5,1,1),I18<>0),"Dep. inicial no procede","OK"))))) | M18: =IF(OR($A18="",$D18="",$D18>=EDATE(M$5,1)),0,MAX(0,MIN($K18,$E18-$G18-$I18-0))) -> 0 | N18: =IF(OR($A18="",$D18="",$D18>=EDATE(N$5,1)),0,MAX(0,MIN($K18,$E18-$G18-$I18-SUM($M18:M18)))) -> 0 | O18: =IF(OR($A18="",$D18="",$D18>=EDATE(O$5,1)),0,MAX(0,MIN($K18,$E18-$G18-$I18-SUM($M18:N18)))) -> 0 | P18: =IF(OR($A18="",$D18="",$D18>=EDATE(P$5,1)),0,MAX(0,MIN($K18,$E18-$G18-$I18-SUM($M18:O18)))) -> 0 | Q18: =IF(OR($A18="",$D18="",$D18>=EDATE(Q$5,1)),0,MAX(0,MIN($K18,$E18-$G18-$I18-SUM($M18:P18)))) -> 0 | R18: =IF(OR($A18="",$D18="",$D18>=EDATE(R$5,1)),0,MAX(0,MIN($K18,$E18-$G18-$I18-SUM($M18:Q18)))) -> 0 | S18: =IF(OR($A18="",$D18="",$D18>=EDATE(S$5,1)),0,MAX(0,MIN($K18,$E18-$G18-$I18-SUM($M18:R18)))) -> 0 | T18: =IF(OR($A18="",$D18="",$D18>=EDATE(T$5,1)),0,MAX(0,MIN($K18,$E18-$G18-$I18-SUM($M18:S18)))) -> 0 | U18: =IF(OR($A18="",$D18="",$D18>=EDATE(U$5,1)),0,MAX(0,MIN($K18,$E18-$G18-$I18-SUM($M18:T18)))) -> 0 | ... X18: =IF(OR($A18="",$D18="",$D18>=EDATE(X$5,1)),0,MAX(0,MIN($K18,$E18-$G18-$I18-SUM($M18:W18)))) -> 0
... K106: =IF(A106="","",IF(OR(H106="",H106<=0),0,(E106-G106)/H106)) | L106: =IF(COUNTA(A106:J106)=0,"",IF(OR(A106="",C106="",D106="",E106="",H106<=0),"Faltan datos",IF(COUNTIF($A$7:$A$106,A106)>1,"ID duplicado",IF(OR(E106<0,G106<0,I106<0,G106+I106>E106,D106<C106),"Revisar activo",IF(AND(C106>=DATE(Configuración!$C$5,1,1),I106<>0),"Dep. inicial no procede","OK"))))) | M106: =IF(OR($A106="",$D106="",$D106>=EDATE(M$5,1)),0,MAX(0,MIN($K106,$E106-$G106-$I106-0))) -> 0 | N106: =IF(OR($A106="",$D106="",$D106>=EDATE(N$5,1)),0,MAX(0,MIN($K106,$E106-$G106-$I106-SUM($M106:M106)))) -> 0 | O106: =IF(OR($A106="",$D106="",$D106>=EDATE(O$5,1)),0,MAX(0,MIN($K106,$E106-$G106-$I106-SUM($M106:N106)))) -> 0 | P106: =IF(OR($A106="",$D106="",$D106>=EDATE(P$5,1)),0,MAX(0,MIN($K106,$E106-$G106-$I106-SUM($M106:O106)))) -> 0 | Q106: =IF(OR($A106="",$D106="",$D106>=EDATE(Q$5,1)),0,MAX(0,MIN($K106,$E106-$G106-$I106-SUM($M106:P106)))) -> 0 | R106: =IF(OR($A106="",$D106="",$D106>=EDATE(R$5,1)),0,MAX(0,MIN($K106,$E106-$G106-$I106-SUM($M106:Q106)))) -> 0 | S106: =IF(OR($A106="",$D106="",$D106>=EDATE(S$5,1)),0,MAX(0,MIN($K106,$E106-$G106-$I106-SUM($M106:R106)))) -> 0 | T106: =IF(OR($A106="",$D106="",$D106>=EDATE(T$5,1)),0,MAX(0,MIN($K106,$E106-$G106-$I106-SUM($M106:S106)))) -> 0 | U106: =IF(OR($A106="",$D106="",$D106>=EDATE(U$5,1)),0,MAX(0,MIN($K106,$E106-$G106-$I106-SUM($M106:T106)))) -> 0 | ... X106: =IF(OR($A106="",$D106="",$D106>=EDATE(X$5,1)),0,MAX(0,MIN($K106,$E106-$G106-$I106-SUM($M106:W106)))) -> 0

Sheet Pasivos
A2: Pasivos
A4: Solo capital de préstamos. Los intereses se registran como Gasto y Pago proveedor en Gastos.
A6: ID único | B6: Fecha | C6: Tipo | D6: ID deuda | E6: Acreedor | F6: Clasificación | G6: Capital / importe | H6: Nota | I6: Revisión
I7: =IF(COUNTA(A7:H7)=0,"",IF(OR(A7="",B7="",C7="",D7="",F7="",G7=""),"Faltan datos",IF(COUNTIF($A$7:$A$506,A7)>1,"ID duplicado",IF(G7<0,"Revisar signo",IF(OR(AND(C7="Saldo inicial",B7<>DATE(Configuración!$C$5,1,1)-1),AND(C7<>"Saldo inicial",OR(B7<DATE(Configuración!$C$5,1,1),B7>=DATE(Configuración!$C$5+1,1,1)))),"Revisar fecha","OK")))))
I8: =IF(COUNTA(A8:H8)=0,"",IF(OR(A8="",B8="",C8="",D8="",F8="",G8=""),"Faltan datos",IF(COUNTIF($A$7:$A$506,A8)>1,"ID duplicado",IF(G8<0,"Revisar signo",IF(OR(AND(C8="Saldo inicial",B8<>DATE(Configuración!$C$5,1,1)-1),AND(C8<>"Saldo inicial",OR(B8<DATE(Configuración!$C$5,1,1),B8>=DATE(Configuración!$C$5+1,1,1)))),"Revisar fecha","OK")))))
I9: =IF(COUNTA(A9:H9)=0,"",IF(OR(A9="",B9="",C9="",D9="",F9="",G9=""),"Faltan datos",IF(COUNTIF($A$7:$A$506,A9)>1,"ID duplicado",IF(G9<0,"Revisar signo",IF(OR(AND(C9="Saldo inicial",B9<>DATE(Configuración!$C$5,1,1)-1),AND(C9<>"Saldo inicial",OR(B9<DATE(Configuración!$C$5,1,1),B9>=DATE(Configuración!$C$5+1,1,1)))),"Revisar fecha","OK")))))
I10: =IF(COUNTA(A10:H10)=0,"",IF(OR(A10="",B10="",C10="",D10="",F10="",G10=""),"Faltan datos",IF(COUNTIF($A$7:$A$506,A10)>1,"ID duplicado",IF(G10<0,"Revisar signo",IF(OR(AND(C10="Saldo inicial",B10<>DATE(Configuración!$C$5,1,1)-1),AND(C10<>"Saldo inicial",OR(B10<DATE(Configuración!$C$5,1,1),B10>=DATE(Configuración!$C$5+1,1,1)))),"Revisar fecha","OK")))))
I11: =IF(COUNTA(A11:H11)=0,"",IF(OR(A11="",B11="",C11="",D11="",F11="",G11=""),"Faltan datos",IF(COUNTIF($A$7:$A$506,A11)>1,"ID duplicado",IF(G11<0,"Revisar signo",IF(OR(AND(C11="Saldo inicial",B11<>DATE(Configuración!$C$5,1,1)-1),AND(C11<>"Saldo inicial",OR(B11<DATE(Configuración!$C$5,1,1),B11>=DATE(Configuración!$C$5+1,1,1)))),"Revisar fecha","OK")))))
I12: =IF(COUNTA(A12:H12)=0,"",IF(OR(A12="",B12="",C12="",D12="",F12="",G12=""),"Faltan datos",IF(COUNTIF($A$7:$A$506,A12)>1,"ID duplicado",IF(G12<0,"Revisar signo",IF(OR(AND(C12="Saldo inicial",B12<>DATE(Configuración!$C$5,1,1)-1),AND(C12<>"Saldo inicial",OR(B12<DATE(Configuración!$C$5,1,1),B12>=DATE(Configuración!$C$5+1,1,1)))),"Revisar fecha","OK")))))
I13: =IF(COUNTA(A13:H13)=0,"",IF(OR(A13="",B13="",C13="",D13="",F13="",G13=""),"Faltan datos",IF(COUNTIF($A$7:$A$506,A13)>1,"ID duplicado",IF(G13<0,"Revisar signo",IF(OR(AND(C13="Saldo inicial",B13<>DATE(Configuración!$C$5,1,1)-1),AND(C13<>"Saldo inicial",OR(B13<DATE(Configuración!$C$5,1,1),B13>=DATE(Configuración!$C$5+1,1,1)))),"Revisar fecha","OK")))))
I14: =IF(COUNTA(A14:H14)=0,"",IF(OR(A14="",B14="",C14="",D14="",F14="",G14=""),"Faltan datos",IF(COUNTIF($A$7:$A$506,A14)>1,"ID duplicado",IF(G14<0,"Revisar signo",IF(OR(AND(C14="Saldo inicial",B14<>DATE(Configuración!$C$5,1,1)-1),AND(C14<>"Saldo inicial",OR(B14<DATE(Configuración!$C$5,1,1),B14>=DATE(Configuración!$C$5+1,1,1)))),"Revisar fecha","OK")))))
I15: =IF(COUNTA(A15:H15)=0,"",IF(OR(A15="",B15="",C15="",D15="",F15="",G15=""),"Faltan datos",IF(COUNTIF($A$7:$A$506,A15)>1,"ID duplicado",IF(G15<0,"Revisar signo",IF(OR(AND(C15="Saldo inicial",B15<>DATE(Configuración!$C$5,1,1)-1),AND(C15<>"Saldo inicial",OR(B15<DATE(Configuración!$C$5,1,1),B15>=DATE(Configuración!$C$5+1,1,1)))),"Revisar fecha","OK")))))
I16: =IF(COUNTA(A16:H16)=0,"",IF(OR(A16="",B16="",C16="",D16="",F16="",G16=""),"Faltan datos",IF(COUNTIF($A$7:$A$506,A16)>1,"ID duplicado",IF(G16<0,"Revisar signo",IF(OR(AND(C16="Saldo inicial",B16<>DATE(Configuración!$C$5,1,1)-1),AND(C16<>"Saldo inicial",OR(B16<DATE(Configuración!$C$5,1,1),B16>=DATE(Configuración!$C$5+1,1,1)))),"Revisar fecha","OK")))))
I17: =IF(COUNTA(A17:H17)=0,"",IF(OR(A17="",B17="",C17="",D17="",F17="",G17=""),"Faltan datos",IF(COUNTIF($A$7:$A$506,A17)>1,"ID duplicado",IF(G17<0,"Revisar signo",IF(OR(AND(C17="Saldo inicial",B17<>DATE(Configuración!$C$5,1,1)-1),AND(C17<>"Saldo inicial",OR(B17<DATE(Configuración!$C$5,1,1),B17>=DATE(Configuración!$C$5+1,1,1)))),"Revisar fecha","OK")))))
I18: =IF(COUNTA(A18:H18)=0,"",IF(OR(A18="",B18="",C18="",D18="",F18="",G18=""),"Faltan datos",IF(COUNTIF($A$7:$A$506,A18)>1,"ID duplicado",IF(G18<0,"Revisar signo",IF(OR(AND(C18="Saldo inicial",B18<>DATE(Configuración!$C$5,1,1)-1),AND(C18<>"Saldo inicial",OR(B18<DATE(Configuración!$C$5,1,1),B18>=DATE(Configuración!$C$5+1,1,1)))),"Revisar fecha","OK")))))
... I506: =IF(COUNTA(A506:H506)=0,"",IF(OR(A506="",B506="",C506="",D506="",F506="",G506=""),"Faltan datos",IF(COUNTIF($A$7:$A$506,A506)>1,"ID duplicado",IF(G506<0,"Revisar signo",IF(OR(AND(C506="Saldo inicial",B506<>DATE(Configuración!$C$5,1,1)-1),AND(C506<>"Saldo inicial",OR(B506<DATE(Configuración!$C$5,1,1),B506>=DATE(Configuración!$C$5+1,1,1)))),"Revisar fecha","OK")))))

Sheet Control
B2: Control
B4: MXN · enero a diciembre
B6: Concepto | C6: =DATE(Configuración!$C$5,1,1) -> 46023 | D6: =DATE(Configuración!$C$5,2,1) -> 46054 | E6: =DATE(Configuración!$C$5,3,1) -> 46082 | F6: =DATE(Configuración!$C$5,4,1) -> 46113 | G6: =DATE(Configuración!$C$5,5,1) -> 46143 | H6: =DATE(Configuración!$C$5,6,1) -> 46174 | I6: =DATE(Configuración!$C$5,7,1) -> 46204 | J6: =DATE(Configuración!$C$5,8,1) -> 46235 | K6: =DATE(Configuración!$C$5,9,1) -> 46266 | L6: =DATE(Configuración!$C$5,10,1) -> 46296 | M6: =DATE(Configuración!$C$5,11,1) -> 46327 | N6: =DATE(Configuración!$C$5,12,1) -> 46357
B7: Diferencia del balance | C7: ='Balance General'!C35 -> 0 | D7: ='Balance General'!D35 -> 0 | E7: ='Balance General'!E35 -> 0 | F7: ='Balance General'!F35 -> 0 | G7: ='Balance General'!G35 -> 0 | H7: ='Balance General'!H35 -> 0 | I7: ='Balance General'!I35 -> 0 | J7: ='Balance General'!J35 -> 0 | ... N7: ='Balance General'!N35 -> 0
B8: Efectivo: cálculo menos banco real | C8: =IF(C9="","Sin saldo real",'Balance General'!C7-C9) -> Sin saldo real | D8: =IF(D9="","Sin saldo real",'Balance General'!D7-D9) -> Sin saldo real | E8: =IF(E9="","Sin saldo real",'Balance General'!E7-E9) -> Sin saldo real | F8: =IF(F9="","Sin saldo real",'Balance General'!F7-F9) -> Sin saldo real | G8: =IF(G9="","Sin saldo real",'Balance General'!G7-G9) -> Sin saldo real | H8: =IF(H9="","Sin saldo real",'Balance General'!H7-H9) -> Sin saldo real | I8: =IF(I9="","Sin saldo real",'Balance General'!I7-I9) -> Sin saldo real | J8: =IF(J9="","Sin saldo real",'Balance General'!J7-J9) -> Sin saldo real | ... N8: =IF(N9="","Sin saldo real",'Balance General'!N7-N9) -> Sin saldo real
B9: Saldo real de bancos y caja
B10: ¿Captura mensual completa? | C10: Pendiente | D10: Pendiente | E10: Pendiente | F10: Pendiente | G10: Pendiente | H10: Pendiente | I10: Pendiente | J10: Pendiente | K10: Pendiente | L10: Pendiente | M10: Pendiente | N10: Pendiente
B12: Errores en Ingresos | C12: =COUNTIF(Ingresos!$L$7:$L$2006,"Faltan datos")+COUNTIF(Ingresos!$L$7:$L$2006,"ID duplicado")+COUNTIF(Ingresos!$L$7:$L$2006,"Fecha fuera del año")+COUNTIF(Ingresos!$L$7:$L$2006,"Revisar signo")+COUNTIF(Ingresos!$L$7:$L$2006,"IVA solo en Servicio")+COUNTIF(Ingresos!$L$7:$L$2006,"IVA solo en Gasto")+COUNTIF(Ingresos!$L$7:$L$2006,"Falta servicio")+COUNTIF(Ingresos!$L$7:$L$2006,"Falta categoría")+COUNTIF(Ingresos!$L$7:$L$2006,"Tipo o categoría inválido")+COUNTIF(Ingresos!$L$7:$L$2006,"Revisar activo")+COUNTIF(Ingresos!$L$7:$L$2006,"Dep. inicial no procede")+COUNTIF(Ingresos!$L$7:$L$2006,"Revisar fecha") -> 0 | D12: =COUNTIF(Ingresos!$L$7:$L$2006,"Faltan datos")+COUNTIF(Ingresos!$L$7:$L$2006,"ID duplicado")+COUNTIF(Ingresos!$L$7:$L$2006,"Fecha fuera del año")+COUNTIF(Ingresos!$L$7:$L$2006,"Revisar signo")+COUNTIF(Ingresos!$L$7:$L$2006,"IVA solo en Servicio")+COUNTIF(Ingresos!$L$7:$L$2006,"IVA solo en Gasto")+COUNTIF(Ingresos!$L$7:$L$2006,"Falta servicio")+COUNTIF(Ingresos!$L$7:$L$2006,"Falta categoría")+COUNTIF(Ingresos!$L$7:$L$2006,"Tipo o categoría inválido")+COUNTIF(Ingresos!$L$7:$L$2006,"Revisar activo")+COUNTIF(Ingresos!$L$7:$L$2006,"Dep. inicial no procede")+COUNTIF(Ingresos!$L$7:$L$2006,"Revisar fecha") -> 0 | E12: =COUNTIF(Ingresos!$L$7:$L$2006,"Faltan datos")+COUNTIF(Ingresos!$L$7:$L$2006,"ID duplicado")+COUNTIF(Ingresos!$L$7:$L$2006,"Fecha fuera del año")+COUNTIF(Ingresos!$L$7:$L$2006,"Revisar signo")+COUNTIF(Ingresos!$L$7:$L$2006,"IVA solo en Servicio")+COUNTIF(Ingresos!$L$7:$L$2006,"IVA solo en Gasto")+COUNTIF(Ingresos!$L$7:$L$2006,"Falta servicio")+COUNTIF(Ingresos!$L$7:$L$2006,"Falta categoría")+COUNTIF(Ingresos!$L$7:$L$2006,"Tipo o categoría inválido")+COUNTIF(Ingresos!$L$7:$L$2006,"Revisar activo")+COUNTIF(Ingresos!$L$7:$L$2006,"Dep. inicial no procede")+COUNTIF(Ingresos!$L$7:$L$2006,"Revisar fecha") -> 0 | F12: =COUNTIF(Ingresos!$L$7:$L$2006,"Faltan datos")+COUNTIF(Ingresos!$L$7:$L$2006,"ID duplicado")+COUNTIF(Ingresos!$L$7:$L$2006,"Fecha fuera del año")+COUNTIF(Ingresos!$L$7:$L$2006,"Revisar signo")+COUNTIF(Ingresos!$L$7:$L$2006,"IVA solo en Servicio")+COUNTIF(Ingresos!$L$7:$L$2006,"IVA solo en Gasto")+COUNTIF(Ingresos!$L$7:$L$2006,"Falta servicio")+COUNTIF(Ingresos!$L$7:$L$2006,"Falta categoría")+COUNTIF(Ingresos!$L$7:$L$2006,"Tipo o categoría inválido")+COUNTIF(Ingresos!$L$7:$L$2006,"Revisar activo")+COUNTIF(Ingresos!$L$7:$L$2006,"Dep. inicial no procede")+COUNTIF(Ingresos!$L$7:$L$2006,"Revisar fecha") -> 0 | G12: =COUNTIF(Ingresos!$L$7:$L$2006,"Faltan datos")+COUNTIF(Ingresos!$L$7:$L$2006,"ID duplicado")+COUNTIF(Ingresos!$L$7:$L$2006,"Fecha fuera del año")+COUNTIF(Ingresos!$L$7:$L$2006,"Revisar signo")+COUNTIF(Ingresos!$L$7:$L$2006,"IVA solo en Servicio")+COUNTIF(Ingresos!$L$7:$L$2006,"IVA solo en Gasto")+COUNTIF(Ingresos!$L$7:$L$2006,"Falta servicio")+COUNTIF(Ingresos!$L$7:$L$2006,"Falta categoría")+COUNTIF(Ingresos!$L$7:$L$2006,"Tipo o categoría inválido")+COUNTIF(Ingresos!$L$7:$L$2006,"Revisar activo")+COUNTIF(Ingresos!$L$7:$L$2006,"Dep. inicial no procede")+COUNTIF(Ingresos!$L$7:$L$2006,"Revisar fecha") -> 0 | H12: =COUNTIF(Ingresos!$L$7:$L$2006,"Faltan datos")+COUNTIF(Ingresos!$L$7:$L$2006,"ID duplicado")+COUNTIF(Ingresos!$L$7:$L$2006,"Fecha fuera del año")+COUNTIF(Ingresos!$L$7:$L$2006,"Revisar signo")+COUNTIF(Ingresos!$L$7:$L$2006,"IVA solo en Servicio")+COUNTIF(Ingresos!$L$7:$L$2006,"IVA solo en Gasto")+COUNTIF(Ingresos!$L$7:$L$2006,"Falta servicio")+COUNTIF(Ingresos!$L$7:$L$2006,"Falta categoría")+COUNTIF(Ingresos!$L$7:$L$2006,"Tipo o categoría inválido")+COUNTIF(Ingresos!$L$7:$L$2006,"Revisar activo")+COUNTIF(Ingresos!$L$7:$L$2006,"Dep. inicial no procede")+COUNTIF(Ingresos!$L$7:$L$2006,"Revisar fecha") -> 0 | I12: =COUNTIF(Ingresos!$L$7:$L$2006,"Faltan datos")+COUNTIF(Ingresos!$L$7:$L$2006,"ID duplicado")+COUNTIF(Ingresos!$L$7:$L$2006,"Fecha fuera del año")+COUNTIF(Ingresos!$L$7:$L$2006,"Revisar signo")+COUNTIF(Ingresos!$L$7:$L$2006,"IVA solo en Servicio")+COUNTIF(Ingresos!$L$7:$L$2006,"IVA solo en Gasto")+COUNTIF(Ingresos!$L$7:$L$2006,"Falta servicio")+COUNTIF(Ingresos!$L$7:$L$2006,"Falta categoría")+COUNTIF(Ingresos!$L$7:$L$2006,"Tipo o categoría inválido")+COUNTIF(Ingresos!$L$7:$L$2006,"Revisar activo")+COUNTIF(Ingresos!$L$7:$L$2006,"Dep. inicial no procede")+COUNTIF(Ingresos!$L$7:$L$2006,"Revisar fecha") -> 0 | J12: =COUNTIF(Ingresos!$L$7:$L$2006,"Faltan datos")+COUNTIF(Ingresos!$L$7:$L$2006,"ID duplicado")+COUNTIF(Ingresos!$L$7:$L$2006,"Fecha fuera del año")+COUNTIF(Ingresos!$L$7:$L$2006,"Revisar signo")+COUNTIF(Ingresos!$L$7:$L$2006,"IVA solo en Servicio")+COUNTIF(Ingresos!$L$7:$L$2006,"IVA solo en Gasto")+COUNTIF(Ingresos!$L$7:$L$2006,"Falta servicio")+COUNTIF(Ingresos!$L$7:$L$2006,"Falta categoría")+COUNTIF(Ingresos!$L$7:$L$2006,"Tipo o categoría inválido")+COUNTIF(Ingresos!$L$7:$L$2006,"Revisar activo")+COUNTIF(Ingresos!$L$7:$L$2006,"Dep. inicial no procede")+COUNTIF(Ingresos!$L$7:$L$2006,"Revisar fecha") -> 0 | ... N12: =COUNTIF(Ingresos!$L$7:$L$2006,"Faltan datos")+COUNTIF(Ingresos!$L$7:$L$2006,"ID duplicado")+COUNTIF(Ingresos!$L$7:$L$2006,"Fecha fuera del año")+COUNTIF(Ingresos!$L$7:$L$2006,"Revisar signo")+COUNTIF(Ingresos!$L$7:$L$2006,"IVA solo en Servicio")+COUNTIF(Ingresos!$L$7:$L$2006,"IVA solo en Gasto")+COUNTIF(Ingresos!$L$7:$L$2006,"Falta servicio")+COUNTIF(Ingresos!$L$7:$L$2006,"Falta categoría")+COUNTIF(Ingresos!$L$7:$L$2006,"Tipo o categoría inválido")+COUNTIF(Ingresos!$L$7:$L$2006,"Revisar activo")+COUNTIF(Ingresos!$L$7:$L$2006,"Dep. inicial no procede")+COUNTIF(Ingresos!$L$7:$L$2006,"Revisar fecha") -> 0
B13: Errores en Gastos | C13: =COUNTIF(Gastos!$L$7:$L$2006,"Faltan datos")+COUNTIF(Gastos!$L$7:$L$2006,"ID duplicado")+COUNTIF(Gastos!$L$7:$L$2006,"Fecha fuera del año")+COUNTIF(Gastos!$L$7:$L$2006,"Revisar signo")+COUNTIF(Gastos!$L$7:$L$2006,"IVA solo en Servicio")+COUNTIF(Gastos!$L$7:$L$2006,"IVA solo en Gasto")+COUNTIF(Gastos!$L$7:$L$2006,"Falta servicio")+COUNTIF(Gastos!$L$7:$L$2006,"Falta categoría")+COUNTIF(Gastos!$L$7:$L$2006,"Tipo o categoría inválido")+COUNTIF(Gastos!$L$7:$L$2006,"Revisar activo")+COUNTIF(Gastos!$L$7:$L$2006,"Dep. inicial no procede")+COUNTIF(Gastos!$L$7:$L$2006,"Revisar fecha") -> 0 | D13: =COUNTIF(Gastos!$L$7:$L$2006,"Faltan datos")+COUNTIF(Gastos!$L$7:$L$2006,"ID duplicado")+COUNTIF(Gastos!$L$7:$L$2006,"Fecha fuera del año")+COUNTIF(Gastos!$L$7:$L$2006,"Revisar signo")+COUNTIF(Gastos!$L$7:$L$2006,"IVA solo en Servicio")+COUNTIF(Gastos!$L$7:$L$2006,"IVA solo en Gasto")+COUNTIF(Gastos!$L$7:$L$2006,"Falta servicio")+COUNTIF(Gastos!$L$7:$L$2006,"Falta categoría")+COUNTIF(Gastos!$L$7:$L$2006,"Tipo o categoría inválido")+COUNTIF(Gastos!$L$7:$L$2006,"Revisar activo")+COUNTIF(Gastos!$L$7:$L$2006,"Dep. inicial no procede")+COUNTIF(Gastos!$L$7:$L$2006,"Revisar fecha") -> 0 | E13: =COUNTIF(Gastos!$L$7:$L$2006,"Faltan datos")+COUNTIF(Gastos!$L$7:$L$2006,"ID duplicado")+COUNTIF(Gastos!$L$7:$L$2006,"Fecha fuera del año")+COUNTIF(Gastos!$L$7:$L$2006,"Revisar signo")+COUNTIF(Gastos!$L$7:$L$2006,"IVA solo en Servicio")+COUNTIF(Gastos!$L$7:$L$2006,"IVA solo en Gasto")+COUNTIF(Gastos!$L$7:$L$2006,"Falta servicio")+COUNTIF(Gastos!$L$7:$L$2006,"Falta categoría")+COUNTIF(Gastos!$L$7:$L$2006,"Tipo o categoría inválido")+COUNTIF(Gastos!$L$7:$L$2006,"Revisar activo")+COUNTIF(Gastos!$L$7:$L$2006,"Dep. inicial no procede")+COUNTIF(Gastos!$L$7:$L$2006,"Revisar fecha") -> 0 | F13: =COUNTIF(Gastos!$L$7:$L$2006,"Faltan datos")+COUNTIF(Gastos!$L$7:$L$2006,"ID duplicado")+COUNTIF(Gastos!$L$7:$L$2006,"Fecha fuera del año")+COUNTIF(Gastos!$L$7:$L$2006,"Revisar signo")+COUNTIF(Gastos!$L$7:$L$2006,"IVA solo en Servicio")+COUNTIF(Gastos!$L$7:$L$2006,"IVA solo en Gasto")+COUNTIF(Gastos!$L$7:$L$2006,"Falta servicio")+COUNTIF(Gastos!$L$7:$L$2006,"Falta categoría")+COUNTIF(Gastos!$L$7:$L$2006,"Tipo o categoría inválido")+COUNTIF(Gastos!$L$7:$L$2006,"Revisar activo")+COUNTIF(Gastos!$L$7:$L$2006,"Dep. inicial no procede")+COUNTIF(Gastos!$L$7:$L$2006,"Revisar fecha") -> 0 | G13: =COUNTIF(Gastos!$L$7:$L$2006,"Faltan datos")+COUNTIF(Gastos!$L$7:$L$2006,"ID duplicado")+COUNTIF(Gastos!$L$7:$L$2006,"Fecha fuera del año")+COUNTIF(Gastos!$L$7:$L$2006,"Revisar signo")+COUNTIF(Gastos!$L$7:$L$2006,"IVA solo en Servicio")+COUNTIF(Gastos!$L$7:$L$2006,"IVA solo en Gasto")+COUNTIF(Gastos!$L$7:$L$2006,"Falta servicio")+COUNTIF(Gastos!$L$7:$L$2006,"Falta categoría")+COUNTIF(Gastos!$L$7:$L$2006,"Tipo o categoría inválido")+COUNTIF(Gastos!$L$7:$L$2006,"Revisar activo")+COUNTIF(Gastos!$L$7:$L$2006,"Dep. inicial no procede")+COUNTIF(Gastos!$L$7:$L$2006,"Revisar fecha") -> 0 | H13: =COUNTIF(Gastos!$L$7:$L$2006,"Faltan datos")+COUNTIF(Gastos!$L$7:$L$2006,"ID duplicado")+COUNTIF(Gastos!$L$7:$L$2006,"Fecha fuera del año")+COUNTIF(Gastos!$L$7:$L$2006,"Revisar signo")+COUNTIF(Gastos!$L$7:$L$2006,"IVA solo en Servicio")+COUNTIF(Gastos!$L$7:$L$2006,"IVA solo en Gasto")+COUNTIF(Gastos!$L$7:$L$2006,"Falta servicio")+COUNTIF(Gastos!$L$7:$L$2006,"Falta categoría")+COUNTIF(Gastos!$L$7:$L$2006,"Tipo o categoría inválido")+COUNTIF(Gastos!$L$7:$L$2006,"Revisar activo")+COUNTIF(Gastos!$L$7:$L$2006,"Dep. inicial no procede")+COUNTIF(Gastos!$L$7:$L$2006,"Revisar fecha") -> 0 | I13: =COUNTIF(Gastos!$L$7:$L$2006,"Faltan datos")+COUNTIF(Gastos!$L$7:$L$2006,"ID duplicado")+COUNTIF(Gastos!$L$7:$L$2006,"Fecha fuera del año")+COUNTIF(Gastos!$L$7:$L$2006,"Revisar signo")+COUNTIF(Gastos!$L$7:$L$2006,"IVA solo en Servicio")+COUNTIF(Gastos!$L$7:$L$2006,"IVA solo en Gasto")+COUNTIF(Gastos!$L$7:$L$2006,"Falta servicio")+COUNTIF(Gastos!$L$7:$L$2006,"Falta categoría")+COUNTIF(Gastos!$L$7:$L$2006,"Tipo o categoría inválido")+COUNTIF(Gastos!$L$7:$L$2006,"Revisar activo")+COUNTIF(Gastos!$L$7:$L$2006,"Dep. inicial no procede")+COUNTIF(Gastos!$L$7:$L$2006,"Revisar fecha") -> 0 | J13: =COUNTIF(Gastos!$L$7:$L$2006,"Faltan datos")+COUNTIF(Gastos!$L$7:$L$2006,"ID duplicado")+COUNTIF(Gastos!$L$7:$L$2006,"Fecha fuera del año")+COUNTIF(Gastos!$L$7:$L$2006,"Revisar signo")+COUNTIF(Gastos!$L$7:$L$2006,"IVA solo en Servicio")+COUNTIF(Gastos!$L$7:$L$2006,"IVA solo en Gasto")+COUNTIF(Gastos!$L$7:$L$2006,"Falta servicio")+COUNTIF(Gastos!$L$7:$L$2006,"Falta categoría")+COUNTIF(Gastos!$L$7:$L$2006,"Tipo o categoría inválido")+COUNTIF(Gastos!$L$7:$L$2006,"Revisar activo")+COUNTIF(Gastos!$L$7:$L$2006,"Dep. inicial no procede")+COUNTIF(Gastos!$L$7:$L$2006,"Revisar fecha") -> 0 | ... N13: =COUNTIF(Gastos!$L$7:$L$2006,"Faltan datos")+COUNTIF(Gastos!$L$7:$L$2006,"ID duplicado")+COUNTIF(Gastos!$L$7:$L$2006,"Fecha fuera del año")+COUNTIF(Gastos!$L$7:$L$2006,"Revisar signo")+COUNTIF(Gastos!$L$7:$L$2006,"IVA solo en Servicio")+COUNTIF(Gastos!$L$7:$L$2006,"IVA solo en Gasto")+COUNTIF(Gastos!$L$7:$L$2006,"Falta servicio")+COUNTIF(Gastos!$L$7:$L$2006,"Falta categoría")+COUNTIF(Gastos!$L$7:$L$2006,"Tipo o categoría inválido")+COUNTIF(Gastos!$L$7:$L$2006,"Revisar activo")+COUNTIF(Gastos!$L$7:$L$2006,"Dep. inicial no procede")+COUNTIF(Gastos!$L$7:$L$2006,"Revisar fecha") -> 0
B14: Errores en Activos | C14: =COUNTIF(Activos!$L$7:$L$106,"Faltan datos")+COUNTIF(Activos!$L$7:$L$106,"ID duplicado")+COUNTIF(Activos!$L$7:$L$106,"Fecha fuera del año")+COUNTIF(Activos!$L$7:$L$106,"Revisar signo")+COUNTIF(Activos!$L$7:$L$106,"IVA solo en Servicio")+COUNTIF(Activos!$L$7:$L$106,"IVA solo en Gasto")+COUNTIF(Activos!$L$7:$L$106,"Falta servicio")+COUNTIF(Activos!$L$7:$L$106,"Falta categoría")+COUNTIF(Activos!$L$7:$L$106,"Tipo o categoría inválido")+COUNTIF(Activos!$L$7:$L$106,"Revisar activo")+COUNTIF(Activos!$L$7:$L$106,"Dep. inicial no procede")+COUNTIF(Activos!$L$7:$L$106,"Revisar fecha") -> 0 | D14: =COUNTIF(Activos!$L$7:$L$106,"Faltan datos")+COUNTIF(Activos!$L$7:$L$106,"ID duplicado")+COUNTIF(Activos!$L$7:$L$106,"Fecha fuera del año")+COUNTIF(Activos!$L$7:$L$106,"Revisar signo")+COUNTIF(Activos!$L$7:$L$106,"IVA solo en Servicio")+COUNTIF(Activos!$L$7:$L$106,"IVA solo en Gasto")+COUNTIF(Activos!$L$7:$L$106,"Falta servicio")+COUNTIF(Activos!$L$7:$L$106,"Falta categoría")+COUNTIF(Activos!$L$7:$L$106,"Tipo o categoría inválido")+COUNTIF(Activos!$L$7:$L$106,"Revisar activo")+COUNTIF(Activos!$L$7:$L$106,"Dep. inicial no procede")+COUNTIF(Activos!$L$7:$L$106,"Revisar fecha") -> 0 | E14: =COUNTIF(Activos!$L$7:$L$106,"Faltan datos")+COUNTIF(Activos!$L$7:$L$106,"ID duplicado")+COUNTIF(Activos!$L$7:$L$106,"Fecha fuera del año")+COUNTIF(Activos!$L$7:$L$106,"Revisar signo")+COUNTIF(Activos!$L$7:$L$106,"IVA solo en Servicio")+COUNTIF(Activos!$L$7:$L$106,"IVA solo en Gasto")+COUNTIF(Activos!$L$7:$L$106,"Falta servicio")+COUNTIF(Activos!$L$7:$L$106,"Falta categoría")+COUNTIF(Activos!$L$7:$L$106,"Tipo o categoría inválido")+COUNTIF(Activos!$L$7:$L$106,"Revisar activo")+COUNTIF(Activos!$L$7:$L$106,"Dep. inicial no procede")+COUNTIF(Activos!$L$7:$L$106,"Revisar fecha") -> 0 | F14: =COUNTIF(Activos!$L$7:$L$106,"Faltan datos")+COUNTIF(Activos!$L$7:$L$106,"ID duplicado")+COUNTIF(Activos!$L$7:$L$106,"Fecha fuera del año")+COUNTIF(Activos!$L$7:$L$106,"Revisar signo")+COUNTIF(Activos!$L$7:$L$106,"IVA solo en Servicio")+COUNTIF(Activos!$L$7:$L$106,"IVA solo en Gasto")+COUNTIF(Activos!$L$7:$L$106,"Falta servicio")+COUNTIF(Activos!$L$7:$L$106,"Falta categoría")+COUNTIF(Activos!$L$7:$L$106,"Tipo o categoría inválido")+COUNTIF(Activos!$L$7:$L$106,"Revisar activo")+COUNTIF(Activos!$L$7:$L$106,"Dep. inicial no procede")+COUNTIF(Activos!$L$7:$L$106,"Revisar fecha") -> 0 | G14: =COUNTIF(Activos!$L$7:$L$106,"Faltan datos")+COUNTIF(Activos!$L$7:$L$106,"ID duplicado")+COUNTIF(Activos!$L$7:$L$106,"Fecha fuera del año")+COUNTIF(Activos!$L$7:$L$106,"Revisar signo")+COUNTIF(Activos!$L$7:$L$106,"IVA solo en Servicio")+COUNTIF(Activos!$L$7:$L$106,"IVA solo en Gasto")+COUNTIF(Activos!$L$7:$L$106,"Falta servicio")+COUNTIF(Activos!$L$7:$L$106,"Falta categoría")+COUNTIF(Activos!$L$7:$L$106,"Tipo o categoría inválido")+COUNTIF(Activos!$L$7:$L$106,"Revisar activo")+COUNTIF(Activos!$L$7:$L$106,"Dep. inicial no procede")+COUNTIF(Activos!$L$7:$L$106,"Revisar fecha") -> 0 | H14: =COUNTIF(Activos!$L$7:$L$106,"Faltan datos")+COUNTIF(Activos!$L$7:$L$106,"ID duplicado")+COUNTIF(Activos!$L$7:$L$106,"Fecha fuera del año")+COUNTIF(Activos!$L$7:$L$106,"Revisar signo")+COUNTIF(Activos!$L$7:$L$106,"IVA solo en Servicio")+COUNTIF(Activos!$L$7:$L$106,"IVA solo en Gasto")+COUNTIF(Activos!$L$7:$L$106,"Falta servicio")+COUNTIF(Activos!$L$7:$L$106,"Falta categoría")+COUNTIF(Activos!$L$7:$L$106,"Tipo o categoría inválido")+COUNTIF(Activos!$L$7:$L$106,"Revisar activo")+COUNTIF(Activos!$L$7:$L$106,"Dep. inicial no procede")+COUNTIF(Activos!$L$7:$L$106,"Revisar fecha") -> 0 | I14: =COUNTIF(Activos!$L$7:$L$106,"Faltan datos")+COUNTIF(Activos!$L$7:$L$106,"ID duplicado")+COUNTIF(Activos!$L$7:$L$106,"Fecha fuera del año")+COUNTIF(Activos!$L$7:$L$106,"Revisar signo")+COUNTIF(Activos!$L$7:$L$106,"IVA solo en Servicio")+COUNTIF(Activos!$L$7:$L$106,"IVA solo en Gasto")+COUNTIF(Activos!$L$7:$L$106,"Falta servicio")+COUNTIF(Activos!$L$7:$L$106,"Falta categoría")+COUNTIF(Activos!$L$7:$L$106,"Tipo o categoría inválido")+COUNTIF(Activos!$L$7:$L$106,"Revisar activo")+COUNTIF(Activos!$L$7:$L$106,"Dep. inicial no procede")+COUNTIF(Activos!$L$7:$L$106,"Revisar fecha") -> 0 | J14: =COUNTIF(Activos!$L$7:$L$106,"Faltan datos")+COUNTIF(Activos!$L$7:$L$106,"ID duplicado")+COUNTIF(Activos!$L$7:$L$106,"Fecha fuera del año")+COUNTIF(Activos!$L$7:$L$106,"Revisar signo")+COUNTIF(Activos!$L$7:$L$106,"IVA solo en Servicio")+COUNTIF(Activos!$L$7:$L$106,"IVA solo en Gasto")+COUNTIF(Activos!$L$7:$L$106,"Falta servicio")+COUNTIF(Activos!$L$7:$L$106,"Falta categoría")+COUNTIF(Activos!$L$7:$L$106,"Tipo o categoría inválido")+COUNTIF(Activos!$L$7:$L$106,"Revisar activo")+COUNTIF(Activos!$L$7:$L$106,"Dep. inicial no procede")+COUNTIF(Activos!$L$7:$L$106,"Revisar fecha") -> 0 | ... N14: =COUNTIF(Activos!$L$7:$L$106,"Faltan datos")+COUNTIF(Activos!$L$7:$L$106,"ID duplicado")+COUNTIF(Activos!$L$7:$L$106,"Fecha fuera del año")+COUNTIF(Activos!$L$7:$L$106,"Revisar signo")+COUNTIF(Activos!$L$7:$L$106,"IVA solo en Servicio")+COUNTIF(Activos!$L$7:$L$106,"IVA solo en Gasto")+COUNTIF(Activos!$L$7:$L$106,"Falta servicio")+COUNTIF(Activos!$L$7:$L$106,"Falta categoría")+COUNTIF(Activos!$L$7:$L$106,"Tipo o categoría inválido")+COUNTIF(Activos!$L$7:$L$106,"Revisar activo")+COUNTIF(Activos!$L$7:$L$106,"Dep. inicial no procede")+COUNTIF(Activos!$L$7:$L$106,"Revisar fecha") -> 0
B15: Errores en Pasivos | C15: =COUNTIF(Pasivos!$I$7:$I$506,"Faltan datos")+COUNTIF(Pasivos!$I$7:$I$506,"ID duplicado")+COUNTIF(Pasivos!$I$7:$I$506,"Fecha fuera del año")+COUNTIF(Pasivos!$I$7:$I$506,"Revisar signo")+COUNTIF(Pasivos!$I$7:$I$506,"IVA solo en Servicio")+COUNTIF(Pasivos!$I$7:$I$506,"IVA solo en Gasto")+COUNTIF(Pasivos!$I$7:$I$506,"Falta servicio")+COUNTIF(Pasivos!$I$7:$I$506,"Falta categoría")+COUNTIF(Pasivos!$I$7:$I$506,"Tipo o categoría inválido")+COUNTIF(Pasivos!$I$7:$I$506,"Revisar activo")+COUNTIF(Pasivos!$I$7:$I$506,"Dep. inicial no procede")+COUNTIF(Pasivos!$I$7:$I$506,"Revisar fecha") -> 0 | D15: =COUNTIF(Pasivos!$I$7:$I$506,"Faltan datos")+COUNTIF(Pasivos!$I$7:$I$506,"ID duplicado")+COUNTIF(Pasivos!$I$7:$I$506,"Fecha fuera del año")+COUNTIF(Pasivos!$I$7:$I$506,"Revisar signo")+COUNTIF(Pasivos!$I$7:$I$506,"IVA solo en Servicio")+COUNTIF(Pasivos!$I$7:$I$506,"IVA solo en Gasto")+COUNTIF(Pasivos!$I$7:$I$506,"Falta servicio")+COUNTIF(Pasivos!$I$7:$I$506,"Falta categoría")+COUNTIF(Pasivos!$I$7:$I$506,"Tipo o categoría inválido")+COUNTIF(Pasivos!$I$7:$I$506,"Revisar activo")+COUNTIF(Pasivos!$I$7:$I$506,"Dep. inicial no procede")+COUNTIF(Pasivos!$I$7:$I$506,"Revisar fecha") -> 0 | E15: =COUNTIF(Pasivos!$I$7:$I$506,"Faltan datos")+COUNTIF(Pasivos!$I$7:$I$506,"ID duplicado")+COUNTIF(Pasivos!$I$7:$I$506,"Fecha fuera del año")+COUNTIF(Pasivos!$I$7:$I$506,"Revisar signo")+COUNTIF(Pasivos!$I$7:$I$506,"IVA solo en Servicio")+COUNTIF(Pasivos!$I$7:$I$506,"IVA solo en Gasto")+COUNTIF(Pasivos!$I$7:$I$506,"Falta servicio")+COUNTIF(Pasivos!$I$7:$I$506,"Falta categoría")+COUNTIF(Pasivos!$I$7:$I$506,"Tipo o categoría inválido")+COUNTIF(Pasivos!$I$7:$I$506,"Revisar activo")+COUNTIF(Pasivos!$I$7:$I$506,"Dep. inicial no procede")+COUNTIF(Pasivos!$I$7:$I$506,"Revisar fecha") -> 0 | F15: =COUNTIF(Pasivos!$I$7:$I$506,"Faltan datos")+COUNTIF(Pasivos!$I$7:$I$506,"ID duplicado")+COUNTIF(Pasivos!$I$7:$I$506,"Fecha fuera del año")+COUNTIF(Pasivos!$I$7:$I$506,"Revisar signo")+COUNTIF(Pasivos!$I$7:$I$506,"IVA solo en Servicio")+COUNTIF(Pasivos!$I$7:$I$506,"IVA solo en Gasto")+COUNTIF(Pasivos!$I$7:$I$506,"Falta servicio")+COUNTIF(Pasivos!$I$7:$I$506,"Falta categoría")+COUNTIF(Pasivos!$I$7:$I$506,"Tipo o categoría inválido")+COUNTIF(Pasivos!$I$7:$I$506,"Revisar activo")+COUNTIF(Pasivos!$I$7:$I$506,"Dep. inicial no procede")+COUNTIF(Pasivos!$I$7:$I$506,"Revisar fecha") -> 0 | G15: =COUNTIF(Pasivos!$I$7:$I$506,"Faltan datos")+COUNTIF(Pasivos!$I$7:$I$506,"ID duplicado")+COUNTIF(Pasivos!$I$7:$I$506,"Fecha fuera del año")+COUNTIF(Pasivos!$I$7:$I$506,"Revisar signo")+COUNTIF(Pasivos!$I$7:$I$506,"IVA solo en Servicio")+COUNTIF(Pasivos!$I$7:$I$506,"IVA solo en Gasto")+COUNTIF(Pasivos!$I$7:$I$506,"Falta servicio")+COUNTIF(Pasivos!$I$7:$I$506,"Falta categoría")+COUNTIF(Pasivos!$I$7:$I$506,"Tipo o categoría inválido")+COUNTIF(Pasivos!$I$7:$I$506,"Revisar activo")+COUNTIF(Pasivos!$I$7:$I$506,"Dep. inicial no procede")+COUNTIF(Pasivos!$I$7:$I$506,"Revisar fecha") -> 0 | H15: =COUNTIF(Pasivos!$I$7:$I$506,"Faltan datos")+COUNTIF(Pasivos!$I$7:$I$506,"ID duplicado")+COUNTIF(Pasivos!$I$7:$I$506,"Fecha fuera del año")+COUNTIF(Pasivos!$I$7:$I$506,"Revisar signo")+COUNTIF(Pasivos!$I$7:$I$506,"IVA solo en Servicio")+COUNTIF(Pasivos!$I$7:$I$506,"IVA solo en Gasto")+COUNTIF(Pasivos!$I$7:$I$506,"Falta servicio")+COUNTIF(Pasivos!$I$7:$I$506,"Falta categoría")+COUNTIF(Pasivos!$I$7:$I$506,"Tipo o categoría inválido")+COUNTIF(Pasivos!$I$7:$I$506,"Revisar activo")+COUNTIF(Pasivos!$I$7:$I$506,"Dep. inicial no procede")+COUNTIF(Pasivos!$I$7:$I$506,"Revisar fecha") -> 0 | I15: =COUNTIF(Pasivos!$I$7:$I$506,"Faltan datos")+COUNTIF(Pasivos!$I$7:$I$506,"ID duplicado")+COUNTIF(Pasivos!$I$7:$I$506,"Fecha fuera del año")+COUNTIF(Pasivos!$I$7:$I$506,"Revisar signo")+COUNTIF(Pasivos!$I$7:$I$506,"IVA solo en Servicio")+COUNTIF(Pasivos!$I$7:$I$506,"IVA solo en Gasto")+COUNTIF(Pasivos!$I$7:$I$506,"Falta servicio")+COUNTIF(Pasivos!$I$7:$I$506,"Falta categoría")+COUNTIF(Pasivos!$I$7:$I$506,"Tipo o categoría inválido")+COUNTIF(Pasivos!$I$7:$I$506,"Revisar activo")+COUNTIF(Pasivos!$I$7:$I$506,"Dep. inicial no procede")+COUNTIF(Pasivos!$I$7:$I$506,"Revisar fecha") -> 0 | J15: =COUNTIF(Pasivos!$I$7:$I$506,"Faltan datos")+COUNTIF(Pasivos!$I$7:$I$506,"ID duplicado")+COUNTIF(Pasivos!$I$7:$I$506,"Fecha fuera del año")+COUNTIF(Pasivos!$I$7:$I$506,"Revisar signo")+COUNTIF(Pasivos!$I$7:$I$506,"IVA solo en Servicio")+COUNTIF(Pasivos!$I$7:$I$506,"IVA solo en Gasto")+COUNTIF(Pasivos!$I$7:$I$506,"Falta servicio")+COUNTIF(Pasivos!$I$7:$I$506,"Falta categoría")+COUNTIF(Pasivos!$I$7:$I$506,"Tipo o categoría inválido")+COUNTIF(Pasivos!$I$7:$I$506,"Revisar activo")+COUNTIF(Pasivos!$I$7:$I$506,"Dep. inicial no procede")+COUNTIF(Pasivos!$I$7:$I$506,"Revisar fecha") -> 0 | ... N15: =COUNTIF(Pasivos!$I$7:$I$506,"Faltan datos")+COUNTIF(Pasivos!$I$7:$I$506,"ID duplicado")+COUNTIF(Pasivos!$I$7:$I$506,"Fecha fuera del año")+COUNTIF(Pasivos!$I$7:$I$506,"Revisar signo")+COUNTIF(Pasivos!$I$7:$I$506,"IVA solo en Servicio")+COUNTIF(Pasivos!$I$7:$I$506,"IVA solo en Gasto")+COUNTIF(Pasivos!$I$7:$I$506,"Falta servicio")+COUNTIF(Pasivos!$I$7:$I$506,"Falta categoría")+COUNTIF(Pasivos!$I$7:$I$506,"Tipo o categoría inválido")+COUNTIF(Pasivos!$I$7:$I$506,"Revisar activo")+COUNTIF(Pasivos!$I$7:$I$506,"Dep. inicial no procede")+COUNTIF(Pasivos!$I$7:$I$506,"Revisar fecha") -> 0
B17: Diferencia de apertura | C17: =SUM(Configuración!C9:C13)+SUMIFS(Activos!$E$7:$E$106,Activos!$C$7:$C$106,"<"&DATE(Configuración!$C$5,1,1),Activos!$C$7:$C$106,">0")-SUMIFS(Activos!$I$7:$I$106,Activos!$C$7:$C$106,"<"&DATE(Configuración!$C$5,1,1),Activos!$C$7:$C$106,">0")-SUM(Configuración!C14:C19)-SUMIFS(Pasivos!$G$7:$G$506,Pasivos!$C$7:$C$506,"Saldo inicial",Pasivos!$B$7:$B$506,DATE(Configuración!$C$5,1,1)-1) -> 0
B19: Revisa saldos negativos | C19: =IF(MIN('Balance General'!C7:C8,'Balance General'!C10:C11,'Balance General'!C19:C20,'Balance General'!C22:C23,'Balance General'!C25)<-0.01,"Revisar","OK") -> OK | D19: =IF(MIN('Balance General'!D7:D8,'Balance General'!D10:D11,'Balance General'!D19:D20,'Balance General'!D22:D23,'Balance General'!D25)<-0.01,"Revisar","OK") -> OK | E19: =IF(MIN('Balance General'!E7:E8,'Balance General'!E10:E11,'Balance General'!E19:E20,'Balance General'!E22:E23,'Balance General'!E25)<-0.01,"Revisar","OK") -> OK | F19: =IF(MIN('Balance General'!F7:F8,'Balance General'!F10:F11,'Balance General'!F19:F20,'Balance General'!F22:F23,'Balance General'!F25)<-0.01,"Revisar","OK") -> OK | G19: =IF(MIN('Balance General'!G7:G8,'Balance General'!G10:G11,'Balance General'!G19:G20,'Balance General'!G22:G23,'Balance General'!G25)<-0.01,"Revisar","OK") -> OK | H19: =IF(MIN('Balance General'!H7:H8,'Balance General'!H10:H11,'Balance General'!H19:H20,'Balance General'!H22:H23,'Balance General'!H25)<-0.01,"Revisar","OK") -> OK | I19: =IF(MIN('Balance General'!I7:I8,'Balance General'!I10:I11,'Balance General'!I19:I20,'Balance General'!I22:I23,'Balance General'!I25)<-0.01,"Revisar","OK") -> OK | J19: =IF(MIN('Balance General'!J7:J8,'Balance General'!J10:J11,'Balance General'!J19:J20,'Balance General'!J22:J23,'Balance General'!J25)<-0.01,"Revisar","OK") -> OK | ... N19: =IF(MIN('Balance General'!N7:N8,'Balance General'!N10:N11,'Balance General'!N19:N20,'Balance General'!N22:N23,'Balance General'!N25)<-0.01,"Revisar","OK") -> OK
B21: Estado de revisión mensual | C21: =IF(OR(C10<>"Sí",C9=""),"Pendiente",IF(OR(ABS(C7)>0.01,ABS(C8)>0.01,ABS($C$17)>0.01,SUM(C12:C15)>0,C19<>"OK"),"Revisar","Conciliado")) -> Pendiente | D21: =IF(OR(D10<>"Sí",D9=""),"Pendiente",IF(OR(ABS(D7)>0.01,ABS(D8)>0.01,ABS($C$17)>0.01,SUM(D12:D15)>0,D19<>"OK"),"Revisar","Conciliado")) -> Pendiente | E21: =IF(OR(E10<>"Sí",E9=""),"Pendiente",IF(OR(ABS(E7)>0.01,ABS(E8)>0.01,ABS($C$17)>0.01,SUM(E12:E15)>0,E19<>"OK"),"Revisar","Conciliado")) -> Pendiente | F21: =IF(OR(F10<>"Sí",F9=""),"Pendiente",IF(OR(ABS(F7)>0.01,ABS(F8)>0.01,ABS($C$17)>0.01,SUM(F12:F15)>0,F19<>"OK"),"Revisar","Conciliado")) -> Pendiente | G21: =IF(OR(G10<>"Sí",G9=""),"Pendiente",IF(OR(ABS(G7)>0.01,ABS(G8)>0.01,ABS($C$17)>0.01,SUM(G12:G15)>0,G19<>"OK"),"Revisar","Conciliado")) -> Pendiente | H21: =IF(OR(H10<>"Sí",H9=""),"Pendiente",IF(OR(ABS(H7)>0.01,ABS(H8)>0.01,ABS($C$17)>0.01,SUM(H12:H15)>0,H19<>"OK"),"Revisar","Conciliado")) -> Pendiente | I21: =IF(OR(I10<>"Sí",I9=""),"Pendiente",IF(OR(ABS(I7)>0.01,ABS(I8)>0.01,ABS($C$17)>0.01,SUM(I12:I15)>0,I19<>"OK"),"Revisar","Conciliado")) -> Pendiente | J21: =IF(OR(J10<>"Sí",J9=""),"Pendiente",IF(OR(ABS(J7)>0.01,ABS(J8)>0.01,ABS($C$17)>0.01,SUM(J12:J15)>0,J19<>"OK"),"Revisar","Conciliado")) -> Pendiente | ... N21: =IF(OR(N10<>"Sí",N9=""),"Pendiente",IF(OR(ABS(N7)>0.01,ABS(N8)>0.01,ABS($C$17)>0.01,SUM(N12:N15)>0,N19<>"OK"),"Revisar","Conciliado")) -> Pendiente
B24: Conciliado exige: captura confirmada, banco real, apertura cuadrada y ausencia de alertas.

Sheet Instrucciones
B2: Instrucciones
B5: Inicio | C5: 1. Define el año y el mes en Configuración. Este archivo inicia en blanco: no incluye estimaciones de ventas ni gastos.
B6: Saldos de apertura | C6: 2. Captura saldos al 31/12 anterior, incluso si empiezas a reconstruir el año a mitad de ejercicio. Reúne bancos, cartera, deudas y patrimonio.
B7: Activos existentes | C7: 3. Registra equipos en Activos con costo histórico, residual, vida útil total, fecha de uso y depreciación acumulada al inicio del año.
B8: Préstamos existentes | C8: 4. En Pasivos, usa Saldo inicial con fecha 31/12 anterior. Registra únicamente deudas de Neurolumens, no deudas personales ajenas al negocio.
B9: Captura diaria | C9: 5. Llena solo celdas amarillas. Usa fechas reales, importes positivos, IDs únicos y las listas desplegables. No sustituyas las fórmulas.
B10: Una operación, dos momentos | C10: Un servicio vendido se registra como Servicio y su cobro como Cobro, en filas distintas. Un gasto y su pago también requieren dos filas.
B11: Ejemplo de venta | C11: Servicio: base 1,000 y el IVA que corresponda. Cobro: importe total recibido en Base / importe, IVA vacío. Relaciona ambos con el mismo folio.
B12: Cobros parciales | C12: Registra cada abono en una nueva fila Cobro con su fecha e importe; no repitas el Servicio. Aplica también a pagos parciales de proveedores.
B13: Paquetes y anticipos | C13: Al recibir dinero antes del servicio, usa Anticipo. Al prestar el servicio, registra Servicio y Aplicación anticipo por el importe aplicado.
B14: Aplicación de anticipo | C14: La aplicación no mueve banco: reduce el anticipo y la cuenta por cobrar. No registres otro Cobro por la misma aplicación.
B15: Sesiones | C15: En Servicio, captura las sesiones realmente prestadas. Para paquetes, distribuye ingreso y sesiones entre los meses en que se prestan.
B16: Retenciones de clientes | C16: Registra Cobro por lo que entró al banco. Registra Retención ISR y Retención IVA en filas separadas por sus importes, con el mismo folio.
... B39: Para empezar | C39: Reconstruye enero y sus saldos iniciales. Continúa mes a mes; marcar un mes completo es responsabilidad de quien captura.
